Workbook

Sheet Assumptions
A1: ASSUMPTIONS — Parkview Crossing, 901-951 NW 8th Ave, Pompano Beach, FL 33060
A3: Blue = input. Black = formula. Every number elsewhere in this workbook traces back to a cell on this tab or Unit Mix.
A5: ACQUISITION
A6: Units | C6: 97 | E6: LoopNet listing
A7: Purchase Price ($) | C7: 13800000 | E7: Broker-stated asking price (LoopNet)
A8: Broker-Stated Cap Rate | C8: 0.07 | E8: LoopNet advertised cap rate
A9: Broker-Implied NOI ($) | C9: =Assumptions!$C$7*Assumptions!$C$8 -> 966000 | E9: i.e. Price x Broker Cap (not used downstream)
A10: Closing Costs (% of Price) | C10: 0.015 | E10: Broward doc stamps $0.70/$100 + title/legal/reports
A11: Closing Costs ($) | C11: =Assumptions!$C$7*Assumptions!$C$10 -> 207000
A13: PROPERTY TAX REASSESSMENT
A14: Combined Millage Rate | C14: 0.0198394 | E14: PLACEHOLDER (Broward county-wide avg) — REPLACE with BCPA-confirmed parcel millage code rate
A15: Seller's Current TAXABLE Value ($) | C15: 10318700 | E15: PLACEHOLDER (LoopNet-disclosed 'assessed value', treated as taxable value since no exemptions apply to non-homestead rental) — REPLACE with BCPA-confirmed taxable value
A16: Cost-of-Sale Factor (DOR customary) | C16: 0.85 | E16: Fla. Stat. 193.011(8): DOR sales-ratio studies customarily net sale price by 15% cost-of-sale allowance. Set to 100% to run the conservative (full-price) case instead.
A17: Non-Homestead Annual Assessment Cap | C17: 0.1 | E17: Fla. Const. Art VII — 10% cap today; Amendment 3 (Nov 2026 ballot) would cut to 5% starting 2027 if passed — NOT modeled
A18: Reassessed Just Value at Purchase ($) | C18: =Assumptions!$C$7*Assumptions!$C$16 -> 11730000 | E18: i.e. Purchase Price x Cost-of-Sale Factor
A19: Seller's Current Annual Tax ($) | C19: =Assumptions!$C$15*Assumptions!$C$14 -> 204716.82
A20: Buyer's Year-1 Tax ($) | C20: =Assumptions!$C$18*Assumptions!$C$14 -> 232716.16
A22: RENOVATION PROGRAM — bottom-up scope, per classic unit
A23: Kitchen (cabinet refacing, counter, appliance pkg) | C23: 7000
A24: Mini-split ductless AC system | C24: 3500
A25: Vinyl slider window replacement (~3 openings) | C25: 1500
A26: Modern lighting fixtures + ceiling fans | C26: 400
A27: LVP flooring (~700 SF) | C27: 4000
A28: Bathroom refresh (vanity, fixtures, re-caulk) | C28: 1200
A29: Interior paint | C29: 500
A30: Turnover labor / make-ready cleaning | C30: 500
A31: Subtotal ($/unit) | C31: =Assumptions!$C$23+Assumptions!$C$24+Assumptions!$C$25+Assumptions!$C$26+Assumptions!$C$27+Assumptions!$C$28+Assumptions!$C$29+Assumptions!$C$30 -> 18600
A32: Contingency % | C32: 0.1
A33: Contingency ($/unit) | C33: =Assumptions!$C$31*Assumptions!$C$32 -> 1860
A34: TOTAL Renovation Cost ($/unit) | C34: =Assumptions!$C$31+Assumptions!$C$33 -> 20460
A35: Renovation Pace (units/month) | C35: 4
A36: Renovated-Unit Rent Premium ($/month) | C36: 175 | E36: Southeast Class B/C industry commentary, $100-250/mo range
A37: Renovated-Unit Rent Premium ($/year) | C37: =Assumptions!$C$36*12 -> 2100
A38: Year-1 Premium Capture % (mid-program convention) | C38: 0.5 | E38: 6-month program starting month 1 of the hold -> average unit captures ~half a year of uplift in Year 1
A40: OPERATING ASSUMPTIONS
A41: Physical Vacancy % | C41: 0.065 | E41: vs. 92% disclosed occupancy; nudged for renovation downtime
A42: Credit Loss % (of GPR) | C42: 0.01
A43: Concessions % (of GPR) | C43: 0.005
A44: Other Income ($/unit/month) | C44: 35 | E44: RUBS, pet, parking, admin fees
A45: Loss-to-Lease Burn-off % per Turnover | C45: 0.5 | E45: of remaining gap to market rent, closed at each turnover
A46: Annual Turnover Rate % | C46: 0.55 | E46: general Class B/C garden-apartment convention, not property-specific
A47: Prior-Owner-Renovated Units: Starting Capture of Total Uplift | C47: 0.65 | E47: judgment split of the disclosed 20.76% blended upside between already-renovated (partial capture) and classic (zero capture) units
A49: MARKET RENT GROWTH SCHEDULE (Broward/Pompano-sourced, capped at 3.0% terminal)
A50: Year 1 Market Rent Growth | C50: 0.01 | E50: Yardi Matrix (via MIAMI REALTORS+RWorld South Florida Rental Market Report, May 2026): Broward County Class C/C+ asking rents +0.2% YoY — near-flat current read, nudged to 1.0% for a full forward year
A51: Year 2 Market Rent Growth | C51: 0.0175 | E51: judgment, gradual convergence
A52: Year 3 Market Rent Growth | C52: 0.025 | E52: judgment, gradual convergence
A53: Year 4 Market Rent Growth | C53: 0.03 | E53: capped at 3.0% per instruction — no source supports going higher for a multi-year terminal rate
A54: Year 5 Market Rent Growth | C54: 0.03 | E54: capped
A55: Year 6 Market Rent Growth | C55: 0.03 | E55: capped
A56: Year 7 Market Rent Growth | C56: 0.03 | E56: capped
A57: Year 8 Market Rent Growth | C57: 0.03 | E57: capped
A58: Year 9 Market Rent Growth | C58: 0.03 | E58: capped
A59: Year 10 Market Rent Growth | C59: 0.03 | E59: capped
A61: EXPENSE GROWTH
A62: General Expense Growth % (ex-insurance, ex-tax) | C62: 0.035
A63: Insurance Growth % | C63: 0.07 | E63: above general expense growth given the recent ~37% two-year South Florida trend
A65: OPERATING EXPENSES (Year 1, $/unit/year unless noted)
A66: Payroll (on-site mgmt + maintenance) | C66: 1400
A67: Repairs & Maintenance | C67: 1100 | E67: nudged up for 1958 vintage / undisclosed roof
A68: Turnover / Make-Ready | C68: 350
A69: Contract Services (landscaping, pest, trash) | C69: 450
A70: Utilities (owner-paid common area/vacant) | C70: 500
A71: Insurance — Base Case ($/unit) | C71: 2400 | E71: vintage-risk-adjusted above the general $2,000/unit South Florida average
A72: Insurance — If Roof Replaced ($/unit) | C72: 1900 | E72: scenario only — see Roof section below
A73: Management Fee (% of EGI) | C73: 0.035
A74: G&A / Admin | C74: 250
A75: Marketing | C75: 150
A76: Replacement Reserves (below NOI) | C76: 300
A78: ROOF & RECERTIFICATION — diligence items, not confident estimates
A79: Roof Replacement Scenario Toggle (1=on, 0=off) | C79: 0
A80: Roof Replacement Cost ($, one-time, Year 1 if toggled) | C80: 235000 | E80: ~23,480 SF est. roof area x $8-12/SF hurricane-code TPO/mod-bit; midpoint of $188k-282k range
A81: Recertification Year (model Year #) | C81: 2 | E81: next 40/50-Year Program cycle due ~2028; Year 2 of the hold if closing is late 2026/early 2027
A82: Recertification Inspection Cost ($, one-time) | C82: 10000 | E82: placeholder — no sourced fee
A83: Recertification Remediation Contingency ($, one-time) | C83: 150000 | E83: placeholder — genuinely unknowable without an engineer's report
A85: DEBT
A86: 1-Month SOFR | C86: 0.0385 | E86: sofrrate.com, reading as of 9/18/2026
A87: Spread (bps over SOFR) | C87: 0.0325
A88: All-In Floating Rate | C88: =Assumptions!$C$86+Assumptions!$C$87 -> 0.071
A89: Maximum LTV % | C89: 0.65
A90: Minimum DSCR | C90: 1.25
A91: Minimum Debt Yield % | C91: 0.08
A92: Interest-Only Period (years) | C92: 2
A93: Amortization (years) | C93: 30
A95: HOLD & EXIT
A96: Hold Period (years) | C96: 5
A97: Exit Cap Spread over Entry — Base Case (bps) | C97: 0.005 | E97: per instruction: entry + 50bps
A98: Exit Cap Spread over Entry — Sensitivity Ceiling (bps) | C98: 0.01 | E98: per instruction: sensitivity extends to +100bps
A99: Cost of Sale at Exit (%) | C99: 0.02
A101: WATERFALL
A102: Preferred Return % | C102: 0.08
A103: Tier 2 LP Share | C103: 0.7
A104: Tier 2 GP Share | C104: 0.3
A105: Tier 2 IRR Hurdle | C105: 0.12
A106: Tier 3 LP Share | C106: 0.5
A107: Tier 3 GP Share | C107: 0.5
A108: GP Co-Invest % | C108: 0.1

Sheet Unit Mix
A1: UNIT MIX / RENT ROLL — 97 units
A3: 75% of units already renovated by prior owner (LoopNet/Crexi). Classic-unit counts below are a proportional allocation of that disclosed 75/25 split across unit types — judgment, not unit-type-level disclosed data.
A5: Unit Type | B5: Total Units | C5: Classic Units | D5: Renovated Units | E5: Avg SF | F5: Classic In-Place Rent/mo | G5: Renovated In-Place Rent/mo | H5: Market Rent/mo (at close)
A6: Studio | B6: 19 | C6: 5 | D6: =B6-C6 -> 14 | E6: 645 | F6: 1275 | G6: =F6+Assumptions!$C$47*(H6-F6) -> 1453.75 | H6: 1550
A7: 1BR/1BA | B7: 52 | C7: 13 | D7: =B7-C7 -> 39 | E7: 685 | F7: 1475 | G7: =F7+Assumptions!$C$47*(H7-F7) -> 1673.25 | H7: 1780
A8: 2BR/1BA | B8: 17 | C8: 4 | D8: =B8-C8 -> 13 | E8: 740 | F8: 1700 | G8: =F8+Assumptions!$C$47*(H8-F8) -> 1927.5 | H8: 2050
A9: 2BR/2BA | B9: 10 | C9: 2 | D9: =B9-C9 -> 8 | E9: 740 | F9: 1825 | G9: =F9+Assumptions!$C$47*(H9-F9) -> 2068.75 | H9: 2200
A10: TOTAL / WEIGHTED AVG | B10: =SUM(B6:B9) -> 98 | C10: =SUM(C6:C9) -> 24 | D10: =SUM(D6:D9) -> 74
A12: RENOVATION CAPEX BY TYPE (classic units only)
A13: Unit Type | B13: Classic Units | C13: Cost/Unit | D13: Total Cost
A14: Studio | B14: =C6 -> 5 | C14: =Assumptions!$C$34 -> 20460 | D14: =B14*C14 -> 102300
A15: 1BR/1BA | B15: =C7 -> 13 | C15: =Assumptions!$C$34 -> 20460 | D15: =B15*C15 -> 265980
A16: 2BR/1BA | B16: =C8 -> 4 | C16: =Assumptions!$C$34 -> 20460 | D16: =B16*C16 -> 81840
A17: 2BR/2BA | B17: =C9 -> 2 | C17: =Assumptions!$C$34 -> 20460 | D17: =B17*C17 -> 40920
A18: TOTAL | D18: =SUM(D14:D17) -> 491040

Sheet Operating Model
A1: OPERATING MODEL — Annual, 10 Years
A4: Year | B4: 1 | C4: 2 | D4: 3 | E4: 4 | F4: 5 | G4: 6 | H4: 7 | I4: 8 | J4: 9 | K4: 10
A5: Calendar Year | B5: 2027 | C5: =B5+1 -> 2028 | D5: =C5+1 -> 2029 | E5: =D5+1 -> 2030 | F5: =E5+1 -> 2031 | G5: =F5+1 -> 2032 | H5: =G5+1 -> 2033 | I5: =H5+1 -> 2034 | J5: =I5+1 -> 2035 | K5: =J5+1 -> 2036
A6: Market Rent Growth (this year) | B6: =Assumptions!$C$50 -> 0.01 | C6: =Assumptions!$C$51 -> 0.0175 | D6: =Assumptions!$C$52 -> 0.025 | E6: =Assumptions!$C$53 -> 0.03 | F6: =Assumptions!$C$54 -> 0.03 | G6: =Assumptions!$C$55 -> 0.03 | H6: =Assumptions!$C$56 -> 0.03 | I6: =Assumptions!$C$57 -> 0.03 | J6: =Assumptions!$C$58 -> 0.03 | K6: =Assumptions!$C$59 -> 0.03
A8: MARKET & ACHIEVED RENT BY UNIT TYPE ($/unit/month)
A9: Studio — Market Rent/mo | B9: ='Unit Mix'!$H$6*(1+B$6) -> 1565.5 | C9: =B9*(1+C$6) -> 1592.8963 | D9: =C9*(1+D$6) -> 1632.7187 | E9: =D9*(1+E$6) -> 1681.7002 | F9: =E9*(1+F$6) -> 1732.1512 | G9: =F9*(1+G$6) -> 1784.1158 | H9: =G9*(1+H$6) -> 1837.6392 | I9: =H9*(1+I$6) -> 1892.7684 | J9: =I9*(1+J$6) -> 1949.5515 | K9: =J9*(1+K$6) -> 2008.038
A10: Studio — Classic-Unit Track Rent/mo | B10: ='Unit Mix'!$F$6*(1-Assumptions!$C$38)+(B9+Assumptions!$C$36)*Assumptions!$C$38 -> 1507.75 | C10: =B10*(1+C$6) -> 1534.1356 | D10: =C10*(1+D$6) -> 1572.489 | E10: =D10*(1+E$6) -> 1619.6637 | F10: =E10*(1+F$6) -> 1668.2536 | G10: =F10*(1+G$6) -> 1718.3012 | H10: =G10*(1+H$6) -> 1769.8502 | I10: =H10*(1+I$6) -> 1822.9457 | J10: =I10*(1+J$6) -> 1877.6341 | K10: =J10*(1+K$6) -> 1933.9631
A11: Studio — Prior-Renovated Track Rent/mo | B11: ='Unit Mix'!$G$6+Assumptions!$C$46*Assumptions!$C$45*(B9-'Unit Mix'!$G$6) -> 1484.4813 | C11: =B11+Assumptions!$C$46*Assumptions!$C$45*(C9-B11) -> 1514.2954 | D11: =C11+Assumptions!$C$46*Assumptions!$C$45*(D9-C11) -> 1546.8618 | E11: =D11+Assumptions!$C$46*Assumptions!$C$45*(E9-D11) -> 1583.9423 | F11: =E11+Assumptions!$C$46*Assumptions!$C$45*(F9-E11) -> 1624.6998 | G11: =F11+Assumptions!$C$46*Assumptions!$C$45*(G9-F11) -> 1668.5392 | H11: =G11+Assumptions!$C$46*Assumptions!$C$45*(H9-G11) -> 1715.0417 | I11: =H11+Assumptions!$C$46*Assumptions!$C$45*(I9-H11) -> 1763.9165 | J11: =I11+Assumptions!$C$46*Assumptions!$C$45*(J9-I11) -> 1814.9661 | K11: =J11+Assumptions!$C$46*Assumptions!$C$45*(K9-J11) -> 1868.0609
A12: 1BR/1BA — Market Rent/mo | B12: ='Unit Mix'!$H$7*(1+B$6) -> 1797.8 | C12: =B12*(1+C$6) -> 1829.2615 | D12: =C12*(1+D$6) -> 1874.993 | E12: =D12*(1+E$6) -> 1931.2428 | F12: =E12*(1+F$6) -> 1989.1801 | G12: =F12*(1+G$6) -> 2048.8555 | H12: =G12*(1+H$6) -> 2110.3212 | I12: =H12*(1+I$6) -> 2173.6308 | J12: =I12*(1+J$6) -> 2238.8397 | K12: =J12*(1+K$6) -> 2306.0049
A13: 1BR/1BA — Classic-Unit Track Rent/mo | B13: ='Unit Mix'!$F$7*(1-Assumptions!$C$38)+(B12+Assumptions!$C$36)*Assumptions!$C$38 -> 1723.9 | C13: =B13*(1+C$6) -> 1754.0683 | D13: =C13*(1+D$6) -> 1797.92 | E13: =D13*(1+E$6) -> 1851.8576 | F13: =E13*(1+F$6) -> 1907.4133 | G13: =F13*(1+G$6) -> 1964.6357 | H13: =G13*(1+H$6) -> 2023.5748 | I13: =H13*(1+I$6) -> 2084.282 | J13: =I13*(1+J$6) -> 2146.8105 | K13: =J13*(1+K$6) -> 2211.2148
A14: 1BR/1BA — Prior-Renovated Track Rent/mo | B14: ='Unit Mix'!$G$7+Assumptions!$C$46*Assumptions!$C$45*(B12-'Unit Mix'!$G$7) -> 1707.5013 | C14: =B14+Assumptions!$C$46*Assumptions!$C$45*(C12-B14) -> 1740.9853 | D14: =C14+Assumptions!$C$46*Assumptions!$C$45*(D12-C14) -> 1777.8374 | E14: =D14+Assumptions!$C$46*Assumptions!$C$45*(E12-D14) -> 1820.0239 | F14: =E14+Assumptions!$C$46*Assumptions!$C$45*(F12-E14) -> 1866.5419 | G14: =F14+Assumptions!$C$46*Assumptions!$C$45*(G12-F14) -> 1916.6781 | H14: =G14+Assumptions!$C$46*Assumptions!$C$45*(H12-G14) -> 1969.93 | I14: =H14+Assumptions!$C$46*Assumptions!$C$45*(I12-H14) -> 2025.9477 | J14: =I14+Assumptions!$C$46*Assumptions!$C$45*(J12-I14) -> 2084.493 | K14: =J14+Assumptions!$C$46*Assumptions!$C$45*(K12-J14) -> 2145.4088
A15: 2BR/1BA — Market Rent/mo | B15: ='Unit Mix'!$H$8*(1+B$6) -> 2070.5 | C15: =B15*(1+C$6) -> 2106.7337 | D15: =C15*(1+D$6) -> 2159.4021 | E15: =D15*(1+E$6) -> 2224.1842 | F15: =E15*(1+F$6) -> 2290.9097 | G15: =F15*(1+G$6) -> 2359.637 | H15: =G15*(1+H$6) -> 2430.4261 | I15: =H15*(1+I$6) -> 2503.3389 | J15: =I15*(1+J$6) -> 2578.439 | K15: =J15*(1+K$6) -> 2655.7922
A16: 2BR/1BA — Classic-Unit Track Rent/mo | B16: ='Unit Mix'!$F$8*(1-Assumptions!$C$38)+(B15+Assumptions!$C$36)*Assumptions!$C$38 -> 1972.75 | C16: =B16*(1+C$6) -> 2007.2731 | D16: =C16*(1+D$6) -> 2057.455 | E16: =D16*(1+E$6) -> 2119.1786 | F16: =E16*(1+F$6) -> 2182.754 | G16: =F16*(1+G$6) -> 2248.2366 | H16: =G16*(1+H$6) -> 2315.6837 | I16: =H16*(1+I$6) -> 2385.1542 | J16: =I16*(1+J$6) -> 2456.7088 | K16: =J16*(1+K$6) -> 2530.4101
A17: 2BR/1BA — Prior-Renovated Track Rent/mo | B17: ='Unit Mix'!$G$8+Assumptions!$C$46*Assumptions!$C$45*(B15-'Unit Mix'!$G$8) -> 1966.825 | C17: =B17+Assumptions!$C$46*Assumptions!$C$45*(C15-B17) -> 2005.2999 | D17: =C17+Assumptions!$C$46*Assumptions!$C$45*(D15-C17) -> 2047.678 | E17: =D17+Assumptions!$C$46*Assumptions!$C$45*(E15-D17) -> 2096.2172 | F17: =E17+Assumptions!$C$46*Assumptions!$C$45*(F15-E17) -> 2149.7576 | G17: =F17+Assumptions!$C$46*Assumptions!$C$45*(G15-F17) -> 2207.4744 | H17: =G17+Assumptions!$C$46*Assumptions!$C$45*(H15-G17) -> 2268.7861 | I17: =H17+Assumptions!$C$46*Assumptions!$C$45*(I15-H17) -> 2333.2881 | J17: =I17+Assumptions!$C$46*Assumptions!$C$45*(J15-I17) -> 2400.7046 | K17: =J17+Assumptions!$C$46*Assumptions!$C$45*(K15-J17) -> 2470.8537
A18: 2BR/2BA — Market Rent/mo | B18: ='Unit Mix'!$H$9*(1+B$6) -> 2222 | C18: =B18*(1+C$6) -> 2260.885 | D18: =C18*(1+D$6) -> 2317.4071 | E18: =D18*(1+E$6) -> 2386.9293 | F18: =E18*(1+F$6) -> 2458.5372 | G18: =F18*(1+G$6) -> 2532.2933 | H18: =G18*(1+H$6) -> 2608.2621 | I18: =H18*(1+I$6) -> 2686.51 | J18: =I18*(1+J$6) -> 2767.1053 | K18: =J18*(1+K$6) -> 2850.1185
A19: 2BR/2BA — Classic-Unit Track Rent/mo | B19: ='Unit Mix'!$F$9*(1-Assumptions!$C$38)+(B18+Assumptions!$C$36)*Assumptions!$C$38 -> 2111 | C19: =B19*(1+C$6) -> 2147.9425 | D19: =C19*(1+D$6) -> 2201.6411 | E19: =D19*(1+E$6) -> 2267.6903 | F19: =E19*(1+F$6) -> 2335.721 | G19: =F19*(1+G$6) -> 2405.7926 | H19: =G19*(1+H$6) -> 2477.9664 | I19: =H19*(1+I$6) -> 2552.3054 | J19: =I19*(1+J$6) -> 2628.8746 | K19: =J19*(1+K$6) -> 2707.7408
A20: 2BR/2BA — Prior-Renovated Track Rent/mo | B20: ='Unit Mix'!$G$9+Assumptions!$C$46*Assumptions!$C$45*(B18-'Unit Mix'!$G$9) -> 2110.8938 | C20: =B20+Assumptions!$C$46*Assumptions!$C$45*(C18-B20) -> 2152.1413 | D20: =C20+Assumptions!$C$46*Assumptions!$C$45*(D18-C20) -> 2197.5894 | E20: =D20+Assumptions!$C$46*Assumptions!$C$45*(E18-D20) -> 2249.6579 | F20: =E20+Assumptions!$C$46*Assumptions!$C$45*(F18-E20) -> 2307.0997 | G20: =F20+Assumptions!$C$46*Assumptions!$C$45*(G18-F20) -> 2369.028 | H20: =G20+Assumptions!$C$46*Assumptions!$C$45*(H18-G20) -> 2434.8174 | I20: =H20+Assumptions!$C$46*Assumptions!$C$45*(I18-H20) -> 2504.0328 | J20: =I20+Assumptions!$C$46*Assumptions!$C$45*(J18-I20) -> 2576.3778 | K20: =J20+Assumptions!$C$46*Assumptions!$C$45*(K18-J20) -> 2651.6565
A22: INCOME
A23: Gross Potential Rent (GPR) | B23: =('Unit Mix'!$C$6*B10+'Unit Mix'!$D$6*B11+'Unit Mix'!$C$7*B13+'Unit Mix'!$D$7*B14+'Unit Mix'!$C$8*B16+'Unit Mix'!$D$8*B17+'Unit Mix'!$C$9*B19+'Unit Mix'!$D$9*B20)*12 -> 2062723.3 | C23: =('Unit Mix'!$C$6*C10+'Unit Mix'!$D$6*C11+'Unit Mix'!$C$7*C13+'Unit Mix'!$D$7*C14+'Unit Mix'!$C$8*C16+'Unit Mix'!$D$8*C17+'Unit Mix'!$C$9*C19+'Unit Mix'!$D$9*C20)*12 -> 2102197.6 | D23: =('Unit Mix'!$C$6*D10+'Unit Mix'!$D$6*D11+'Unit Mix'!$C$7*D13+'Unit Mix'!$D$7*D14+'Unit Mix'!$C$8*D16+'Unit Mix'!$D$8*D17+'Unit Mix'!$C$9*D19+'Unit Mix'!$D$9*D20)*12 -> 2148729.1 | E23: =('Unit Mix'!$C$6*E10+'Unit Mix'!$D$6*E11+'Unit Mix'!$C$7*E13+'Unit Mix'!$D$7*E14+'Unit Mix'!$C$8*E16+'Unit Mix'!$D$8*E17+'Unit Mix'!$C$9*E19+'Unit Mix'!$D$9*E20)*12 -> 2203065.3 | F23: =('Unit Mix'!$C$6*F10+'Unit Mix'!$D$6*F11+'Unit Mix'!$C$7*F13+'Unit Mix'!$D$7*F14+'Unit Mix'!$C$8*F16+'Unit Mix'!$D$8*F17+'Unit Mix'!$C$9*F19+'Unit Mix'!$D$9*F20)*12 -> 2261816.1 | G23: =('Unit Mix'!$C$6*G10+'Unit Mix'!$D$6*G11+'Unit Mix'!$C$7*G13+'Unit Mix'!$D$7*G14+'Unit Mix'!$C$8*G16+'Unit Mix'!$D$8*G17+'Unit Mix'!$C$9*G19+'Unit Mix'!$D$9*G20)*12 -> 2324348.3 | H23: =('Unit Mix'!$C$6*H10+'Unit Mix'!$D$6*H11+'Unit Mix'!$C$7*H13+'Unit Mix'!$D$7*H14+'Unit Mix'!$C$8*H16+'Unit Mix'!$D$8*H17+'Unit Mix'!$C$9*H19+'Unit Mix'!$D$9*H20)*12 -> 2390220 | I23: =('Unit Mix'!$C$6*I10+'Unit Mix'!$D$6*I11+'Unit Mix'!$C$7*I13+'Unit Mix'!$D$7*I14+'Unit Mix'!$C$8*I16+'Unit Mix'!$D$8*I17+'Unit Mix'!$C$9*I19+'Unit Mix'!$D$9*I20)*12 -> 2459129.1 | ... K23: =('Unit Mix'!$C$6*K10+'Unit Mix'!$D$6*K11+'Unit Mix'!$C$7*K13+'Unit Mix'!$D$7*K14+'Unit Mix'!$C$8*K16+'Unit Mix'!$D$8*K17+'Unit Mix'!$C$9*K19+'Unit Mix'!$D$9*K20)*12 -> 2605330.5
A24: Less: Physical Vacancy | B24: =-B23*Assumptions!$C$41 -> -134077.02 | C24: =-C23*Assumptions!$C$41 -> -136642.85 | D24: =-D23*Assumptions!$C$41 -> -139667.39 | E24: =-E23*Assumptions!$C$41 -> -143199.24 | F24: =-F23*Assumptions!$C$41 -> -147018.05 | G24: =-G23*Assumptions!$C$41 -> -151082.64 | H24: =-H23*Assumptions!$C$41 -> -155364.3 | I24: =-I23*Assumptions!$C$41 -> -159843.39 | ... K24: =-K23*Assumptions!$C$41 -> -169346.48
A25: Less: Credit Loss | B25: =-B23*Assumptions!$C$42 -> -20627.233 | C25: =-C23*Assumptions!$C$42 -> -21021.976 | D25: =-D23*Assumptions!$C$42 -> -21487.291 | E25: =-E23*Assumptions!$C$42 -> -22030.653 | F25: =-F23*Assumptions!$C$42 -> -22618.161 | G25: =-G23*Assumptions!$C$42 -> -23243.483 | H25: =-H23*Assumptions!$C$42 -> -23902.2 | I25: =-I23*Assumptions!$C$42 -> -24591.291 | ... K25: =-K23*Assumptions!$C$42 -> -26053.305
A26: Less: Concessions | B26: =-B23*Assumptions!$C$43 -> -10313.617 | C26: =-C23*Assumptions!$C$43 -> -10510.988 | D26: =-D23*Assumptions!$C$43 -> -10743.646 | E26: =-E23*Assumptions!$C$43 -> -11015.326 | F26: =-F23*Assumptions!$C$43 -> -11309.081 | G26: =-G23*Assumptions!$C$43 -> -11621.741 | H26: =-H23*Assumptions!$C$43 -> -11951.1 | I26: =-I23*Assumptions!$C$43 -> -12295.645 | ... K26: =-K23*Assumptions!$C$43 -> -13026.653
A27: Plus: Other Income | B27: =Assumptions!$C$6*Assumptions!$C$44*12*(1+Assumptions!$C$62)^(B$4-1) -> 40740 | C27: =Assumptions!$C$6*Assumptions!$C$44*12*(1+Assumptions!$C$62)^(C$4-1) -> 42165.9 | D27: =Assumptions!$C$6*Assumptions!$C$44*12*(1+Assumptions!$C$62)^(D$4-1) -> 43641.707 | E27: =Assumptions!$C$6*Assumptions!$C$44*12*(1+Assumptions!$C$62)^(E$4-1) -> 45169.166 | F27: =Assumptions!$C$6*Assumptions!$C$44*12*(1+Assumptions!$C$62)^(F$4-1) -> 46750.087 | G27: =Assumptions!$C$6*Assumptions!$C$44*12*(1+Assumptions!$C$62)^(G$4-1) -> 48386.34 | H27: =Assumptions!$C$6*Assumptions!$C$44*12*(1+Assumptions!$C$62)^(H$4-1) -> 50079.862 | I27: =Assumptions!$C$6*Assumptions!$C$44*12*(1+Assumptions!$C$62)^(I$4-1) -> 51832.657 | ... K27: =Assumptions!$C$6*Assumptions!$C$44*12*(1+Assumptions!$C$62)^(K$4-1) -> 55524.438
A28: Effective Gross Income (EGI) | B28: =SUM(B23:B27) -> 1938445.5 | C28: =SUM(C23:C27) -> 1976187.7 | D28: =SUM(D23:D27) -> 2020472.5 | E28: =SUM(E23:E27) -> 2071989.2 | F28: =SUM(F23:F27) -> 2127620.9 | G28: =SUM(G23:G27) -> 2186786.7 | H28: =SUM(H23:H27) -> 2249082.3 | I28: =SUM(I23:I27) -> 2314231.4 | ... K28: =SUM(K23:K27) -> 2452428.5
A30: OPERATING EXPENSES
A31: Payroll | B31: =-Assumptions!$C$6*Assumptions!$C$66*(1+Assumptions!$C$62)^(B$4-1) -> -135800 | C31: =-Assumptions!$C$6*Assumptions!$C$66*(1+Assumptions!$C$62)^(C$4-1) -> -140553 | D31: =-Assumptions!$C$6*Assumptions!$C$66*(1+Assumptions!$C$62)^(D$4-1) -> -145472.36 | E31: =-Assumptions!$C$6*Assumptions!$C$66*(1+Assumptions!$C$62)^(E$4-1) -> -150563.89 | F31: =-Assumptions!$C$6*Assumptions!$C$66*(1+Assumptions!$C$62)^(F$4-1) -> -155833.62 | G31: =-Assumptions!$C$6*Assumptions!$C$66*(1+Assumptions!$C$62)^(G$4-1) -> -161287.8 | H31: =-Assumptions!$C$6*Assumptions!$C$66*(1+Assumptions!$C$62)^(H$4-1) -> -166932.87 | I31: =-Assumptions!$C$6*Assumptions!$C$66*(1+Assumptions!$C$62)^(I$4-1) -> -172775.52 | ... K31: =-Assumptions!$C$6*Assumptions!$C$66*(1+Assumptions!$C$62)^(K$4-1) -> -185081.46
A32: Repairs & Maintenance | B32: =-Assumptions!$C$6*Assumptions!$C$67*(1+Assumptions!$C$62)^(B$4-1) -> -106700 | C32: =-Assumptions!$C$6*Assumptions!$C$67*(1+Assumptions!$C$62)^(C$4-1) -> -110434.5 | D32: =-Assumptions!$C$6*Assumptions!$C$67*(1+Assumptions!$C$62)^(D$4-1) -> -114299.71 | E32: =-Assumptions!$C$6*Assumptions!$C$67*(1+Assumptions!$C$62)^(E$4-1) -> -118300.2 | F32: =-Assumptions!$C$6*Assumptions!$C$67*(1+Assumptions!$C$62)^(F$4-1) -> -122440.7 | G32: =-Assumptions!$C$6*Assumptions!$C$67*(1+Assumptions!$C$62)^(G$4-1) -> -126726.13 | H32: =-Assumptions!$C$6*Assumptions!$C$67*(1+Assumptions!$C$62)^(H$4-1) -> -131161.54 | I32: =-Assumptions!$C$6*Assumptions!$C$67*(1+Assumptions!$C$62)^(I$4-1) -> -135752.2 | ... K32: =-Assumptions!$C$6*Assumptions!$C$67*(1+Assumptions!$C$62)^(K$4-1) -> -145421.15
A33: Turnover / Make-Ready | B33: =-Assumptions!$C$6*Assumptions!$C$68*(1+Assumptions!$C$62)^(B$4-1) -> -33950 | C33: =-Assumptions!$C$6*Assumptions!$C$68*(1+Assumptions!$C$62)^(C$4-1) -> -35138.25 | D33: =-Assumptions!$C$6*Assumptions!$C$68*(1+Assumptions!$C$62)^(D$4-1) -> -36368.089 | E33: =-Assumptions!$C$6*Assumptions!$C$68*(1+Assumptions!$C$62)^(E$4-1) -> -37640.972 | F33: =-Assumptions!$C$6*Assumptions!$C$68*(1+Assumptions!$C$62)^(F$4-1) -> -38958.406 | G33: =-Assumptions!$C$6*Assumptions!$C$68*(1+Assumptions!$C$62)^(G$4-1) -> -40321.95 | H33: =-Assumptions!$C$6*Assumptions!$C$68*(1+Assumptions!$C$62)^(H$4-1) -> -41733.218 | I33: =-Assumptions!$C$6*Assumptions!$C$68*(1+Assumptions!$C$62)^(I$4-1) -> -43193.881 | ... K33: =-Assumptions!$C$6*Assumptions!$C$68*(1+Assumptions!$C$62)^(K$4-1) -> -46270.365
A34: Contract Services | B34: =-Assumptions!$C$6*Assumptions!$C$69*(1+Assumptions!$C$62)^(B$4-1) -> -43650 | C34: =-Assumptions!$C$6*Assumptions!$C$69*(1+Assumptions!$C$62)^(C$4-1) -> -45177.75 | D34: =-Assumptions!$C$6*Assumptions!$C$69*(1+Assumptions!$C$62)^(D$4-1) -> -46758.971 | E34: =-Assumptions!$C$6*Assumptions!$C$69*(1+Assumptions!$C$62)^(E$4-1) -> -48395.535 | F34: =-Assumptions!$C$6*Assumptions!$C$69*(1+Assumptions!$C$62)^(F$4-1) -> -50089.379 | G34: =-Assumptions!$C$6*Assumptions!$C$69*(1+Assumptions!$C$62)^(G$4-1) -> -51842.507 | H34: =-Assumptions!$C$6*Assumptions!$C$69*(1+Assumptions!$C$62)^(H$4-1) -> -53656.995 | I34: =-Assumptions!$C$6*Assumptions!$C$69*(1+Assumptions!$C$62)^(I$4-1) -> -55534.99 | ... K34: =-Assumptions!$C$6*Assumptions!$C$69*(1+Assumptions!$C$62)^(K$4-1) -> -59490.469
A35: Utilities (owner-paid) | B35: =-Assumptions!$C$6*Assumptions!$C$70*(1+Assumptions!$C$62)^(B$4-1) -> -48500 | C35: =-Assumptions!$C$6*Assumptions!$C$70*(1+Assumptions!$C$62)^(C$4-1) -> -50197.5 | D35: =-Assumptions!$C$6*Assumptions!$C$70*(1+Assumptions!$C$62)^(D$4-1) -> -51954.412 | E35: =-Assumptions!$C$6*Assumptions!$C$70*(1+Assumptions!$C$62)^(E$4-1) -> -53772.817 | F35: =-Assumptions!$C$6*Assumptions!$C$70*(1+Assumptions!$C$62)^(F$4-1) -> -55654.866 | G35: =-Assumptions!$C$6*Assumptions!$C$70*(1+Assumptions!$C$62)^(G$4-1) -> -57602.786 | H35: =-Assumptions!$C$6*Assumptions!$C$70*(1+Assumptions!$C$62)^(H$4-1) -> -59618.883 | I35: =-Assumptions!$C$6*Assumptions!$C$70*(1+Assumptions!$C$62)^(I$4-1) -> -61705.544 | ... K35: =-Assumptions!$C$6*Assumptions!$C$70*(1+Assumptions!$C$62)^(K$4-1) -> -66100.522
A36: Insurance | B36: =-Assumptions!$C$6*(IF(Assumptions!$C$79=1,Assumptions!$C$72,Assumptions!$C$71))*(1+Assumptions!$C$63)^(B$4-1) -> -232800 | C36: =-Assumptions!$C$6*(IF(Assumptions!$C$79=1,Assumptions!$C$72,Assumptions!$C$71))*(1+Assumptions!$C$63)^(C$4-1) -> -249096 | D36: =-Assumptions!$C$6*(IF(Assumptions!$C$79=1,Assumptions!$C$72,Assumptions!$C$71))*(1+Assumptions!$C$63)^(D$4-1) -> -266532.72 | E36: =-Assumptions!$C$6*(IF(Assumptions!$C$79=1,Assumptions!$C$72,Assumptions!$C$71))*(1+Assumptions!$C$63)^(E$4-1) -> -285190.01 | F36: =-Assumptions!$C$6*(IF(Assumptions!$C$79=1,Assumptions!$C$72,Assumptions!$C$71))*(1+Assumptions!$C$63)^(F$4-1) -> -305153.31 | G36: =-Assumptions!$C$6*(IF(Assumptions!$C$79=1,Assumptions!$C$72,Assumptions!$C$71))*(1+Assumptions!$C$63)^(G$4-1) -> -326514.04 | H36: =-Assumptions!$C$6*(IF(Assumptions!$C$79=1,Assumptions!$C$72,Assumptions!$C$71))*(1+Assumptions!$C$63)^(H$4-1) -> -349370.03 | I36: =-Assumptions!$C$6*(IF(Assumptions!$C$79=1,Assumptions!$C$72,Assumptions!$C$71))*(1+Assumptions!$C$63)^(I$4-1) -> -373825.93 | ... K36: =-Assumptions!$C$6*(IF(Assumptions!$C$79=1,Assumptions!$C$72,Assumptions!$C$71))*(1+Assumptions!$C$63)^(K$4-1) -> -427993.3
A37: Property Tax (reassessed basis, capped growth) | B37: =-Assumptions!$C$20 -> -232716.16 | C37: =B37*(1+Assumptions!$C$17) -> -255987.78 | D37: =C37*(1+Assumptions!$C$17) -> -281586.56 | E37: =D37*(1+Assumptions!$C$17) -> -309745.21 | F37: =E37*(1+Assumptions!$C$17) -> -340719.73 | G37: =F37*(1+Assumptions!$C$17) -> -374791.71 | H37: =G37*(1+Assumptions!$C$17) -> -412270.88 | I37: =H37*(1+Assumptions!$C$17) -> -453497.96 | J37: =I37*(1+Assumptions!$C$17) -> -498847.76 | K37: =J37*(1+Assumptions!$C$17) -> -548732.54
A38: Management Fee (% of EGI) | B38: =-B28*Assumptions!$C$73 -> -67845.591 | C38: =-C28*Assumptions!$C$73 -> -69166.57 | D38: =-D28*Assumptions!$C$73 -> -70716.538 | E38: =-E28*Assumptions!$C$73 -> -72519.623 | F38: =-F28*Assumptions!$C$73 -> -74466.732 | G38: =-G28*Assumptions!$C$73 -> -76537.536 | H38: =-H28*Assumptions!$C$73 -> -78717.88 | I38: =-I28*Assumptions!$C$73 -> -80998.099 | ... K38: =-K28*Assumptions!$C$73 -> -85834.997
A39: G&A / Admin | B39: =-Assumptions!$C$6*Assumptions!$C$74*(1+Assumptions!$C$62)^(B$4-1) -> -24250 | C39: =-Assumptions!$C$6*Assumptions!$C$74*(1+Assumptions!$C$62)^(C$4-1) -> -25098.75 | D39: =-Assumptions!$C$6*Assumptions!$C$74*(1+Assumptions!$C$62)^(D$4-1) -> -25977.206 | E39: =-Assumptions!$C$6*Assumptions!$C$74*(1+Assumptions!$C$62)^(E$4-1) -> -26886.408 | F39: =-Assumptions!$C$6*Assumptions!$C$74*(1+Assumptions!$C$62)^(F$4-1) -> -27827.433 | G39: =-Assumptions!$C$6*Assumptions!$C$74*(1+Assumptions!$C$62)^(G$4-1) -> -28801.393 | H39: =-Assumptions!$C$6*Assumptions!$C$74*(1+Assumptions!$C$62)^(H$4-1) -> -29809.442 | I39: =-Assumptions!$C$6*Assumptions!$C$74*(1+Assumptions!$C$62)^(I$4-1) -> -30852.772 | ... K39: =-Assumptions!$C$6*Assumptions!$C$74*(1+Assumptions!$C$62)^(K$4-1) -> -33050.261
A40: Marketing | B40: =-Assumptions!$C$6*Assumptions!$C$75*(1+Assumptions!$C$62)^(B$4-1) -> -14550 | C40: =-Assumptions!$C$6*Assumptions!$C$75*(1+Assumptions!$C$62)^(C$4-1) -> -15059.25 | D40: =-Assumptions!$C$6*Assumptions!$C$75*(1+Assumptions!$C$62)^(D$4-1) -> -15586.324 | E40: =-Assumptions!$C$6*Assumptions!$C$75*(1+Assumptions!$C$62)^(E$4-1) -> -16131.845 | F40: =-Assumptions!$C$6*Assumptions!$C$75*(1+Assumptions!$C$62)^(F$4-1) -> -16696.46 | G40: =-Assumptions!$C$6*Assumptions!$C$75*(1+Assumptions!$C$62)^(G$4-1) -> -17280.836 | H40: =-Assumptions!$C$6*Assumptions!$C$75*(1+Assumptions!$C$62)^(H$4-1) -> -17885.665 | I40: =-Assumptions!$C$6*Assumptions!$C$75*(1+Assumptions!$C$62)^(I$4-1) -> -18511.663 | ... K40: =-Assumptions!$C$6*Assumptions!$C$75*(1+Assumptions!$C$62)^(K$4-1) -> -19830.156
A41: Total Operating Expenses | B41: =SUM(B31:B40) -> -940761.75 | C41: =SUM(C31:C40) -> -995909.35 | D41: =SUM(D31:D40) -> -1055252.9 | E41: =SUM(E31:E40) -> -1119146.5 | F41: =SUM(F31:F40) -> -1187840.6 | G41: =SUM(G31:G40) -> -1261706.7 | H41: =SUM(H31:H40) -> -1341157.4 | I41: =SUM(I31:I40) -> -1426648.6 | ... K41: =SUM(K31:K40) -> -1617805.2
A43: NET OPERATING INCOME (NOI) | B43: =B28+B41 -> 997683.71 | C43: =C28+C41 -> 980278.36 | D43: =D28+D41 -> 965219.63 | E43: =E28+E41 -> 952842.73 | F43: =F28+F41 -> 939780.26 | G43: =G28+G41 -> 925080.05 | H43: =H28+H41 -> 907924.88 | I43: =I28+I41 -> 887582.84 | ... K43: =K28+K41 -> 834623.28
A44: memo: NOI Before Property Tax (for exit valuation) | B44: =B43-B37 -> 1230399.9 | C44: =C43-C37 -> 1236266.1 | D44: =D43-D37 -> 1246806.2 | E44: =E43-E37 -> 1262587.9 | F44: =F43-F37 -> 1280500 | G44: =G43-G37 -> 1299871.8 | H44: =H43-H37 -> 1320195.8 | I44: =I43-I37 -> 1341080.8 | ... K44: =K43-K37 -> 1383355.8
A46: BELOW-NOI ITEMS
A47: Less: Replacement Reserves | B47: =-Assumptions!$C$6*Assumptions!$C$76*(1+Assumptions!$C$62)^(B$4-1) -> -29100 | C47: =-Assumptions!$C$6*Assumptions!$C$76*(1+Assumptions!$C$62)^(C$4-1) -> -30118.5 | D47: =-Assumptions!$C$6*Assumptions!$C$76*(1+Assumptions!$C$62)^(D$4-1) -> -31172.647 | E47: =-Assumptions!$C$6*Assumptions!$C$76*(1+Assumptions!$C$62)^(E$4-1) -> -32263.69 | F47: =-Assumptions!$C$6*Assumptions!$C$76*(1+Assumptions!$C$62)^(F$4-1) -> -33392.919 | G47: =-Assumptions!$C$6*Assumptions!$C$76*(1+Assumptions!$C$62)^(G$4-1) -> -34561.671 | H47: =-Assumptions!$C$6*Assumptions!$C$76*(1+Assumptions!$C$62)^(H$4-1) -> -35771.33 | I47: =-Assumptions!$C$6*Assumptions!$C$76*(1+Assumptions!$C$62)^(I$4-1) -> -37023.327 | ... K47: =-Assumptions!$C$6*Assumptions!$C$76*(1+Assumptions!$C$62)^(K$4-1) -> -39660.313
A48: Less: One-Time Capex (roof scenario / recertification) | B48: =-IF(B$4=1,Assumptions!$C$79*Assumptions!$C$80,0)-IF(B$4=Assumptions!$C$81,Assumptions!$C$82+Assumptions!$C$83,0) -> 0 | C48: =-IF(C$4=1,Assumptions!$C$79*Assumptions!$C$80,0)-IF(C$4=Assumptions!$C$81,Assumptions!$C$82+Assumptions!$C$83,0) -> -160000 | D48: =-IF(D$4=1,Assumptions!$C$79*Assumptions!$C$80,0)-IF(D$4=Assumptions!$C$81,Assumptions!$C$82+Assumptions!$C$83,0) -> 0 | E48: =-IF(E$4=1,Assumptions!$C$79*Assumptions!$C$80,0)-IF(E$4=Assumptions!$C$81,Assumptions!$C$82+Assumptions!$C$83,0) -> 0 | F48: =-IF(F$4=1,Assumptions!$C$79*Assumptions!$C$80,0)-IF(F$4=Assumptions!$C$81,Assumptions!$C$82+Assumptions!$C$83,0) -> 0 | G48: =-IF(G$4=1,Assumptions!$C$79*Assumptions!$C$80,0)-IF(G$4=Assumptions!$C$81,Assumptions!$C$82+Assumptions!$C$83,0) -> 0 | H48: =-IF(H$4=1,Assumptions!$C$79*Assumptions!$C$80,0)-IF(H$4=Assumptions!$C$81,Assumptions!$C$82+Assumptions!$C$83,0) -> 0 | I48: =-IF(I$4=1,Assumptions!$C$79*Assumptions!$C$80,0)-IF(I$4=Assumptions!$C$81,Assumptions!$C$82+Assumptions!$C$83,0) -> 0 | ... K48: =-IF(K$4=1,Assumptions!$C$79*Assumptions!$C$80,0)-IF(K$4=Assumptions!$C$81,Assumptions!$C$82+Assumptions!$C$83,0) -> 0
A49: UNLEVERED CASH FLOW (before renovation capex, before debt) | B49: =B43+B47+B48 -> 968583.71 | C49: =C43+C47+C48 -> 790159.86 | D49: =D43+D47+D48 -> 934046.98 | E49: =E43+E47+E48 -> 920579.04 | F49: =F43+F47+F48 -> 906387.34 | G49: =G43+G47+G48 -> 890518.38 | H49: =H43+H47+H48 -> 872153.55 | I49: =I43+I47+I48 -> 850559.51 | ... K49: =K43+K47+K48 -> 794962.97

Sheet Debt
A1: DEBT — sized explicitly on the binding constraint (no circularity, no iteration)
A4: SIZING
A5: Year 1 NOI (from Operating Model) | C5: ='Operating Model'!$B$43 -> 997683.71
A6: Loan Amount — LTV Constraint | C6: =Assumptions!$C$7*Assumptions!$C$89 -> 8970000
A7: Loan Amount — Debt Yield Constraint | C7: =Debt!$C$5/Assumptions!$C$91 -> 12471046
A8: Loan Amount — DSCR Constraint (IO-period debt service) | C8: =Debt!$C$5/(Assumptions!$C$90*Assumptions!$C$88) -> 11241507
A9: SIZED LOAN AMOUNT (binding = minimum) | C9: =MIN(C6,C7,C8) -> 8970000
A10: Binding Constraint | C10: =IF(C9=C6,"LTV",IF(C9=C7,"Debt Yield","DSCR")) -> LTV
A11: Resulting LTV | C11: =Debt!$C$9/Assumptions!$C$7 -> 0.65
A12: Resulting Debt Yield | C12: =Debt!$C$5/Debt!$C$9 -> 0.11122449
A13: Resulting DSCR (Year 1, IO) | C13: =Debt!$C$5/(Debt!$C$9*Assumptions!$C$88) -> 1.5665422
A15: AMORTIZATION SCHEDULE (Years 1-5, matching the hold period)
A16: Year | B16: Beg. Balance | C16: Interest | D16: Principal | E16: Debt Service | F16: End Balance
A17: Annual P&I Payment (post-IO) | B17: =-PMT(Assumptions!$C$88,Assumptions!$C$93,Debt!$C$9) -> 730135.09
A18: 1 | B18: =Debt!$C$9 -> 8970000 | C18: =B18*Assumptions!$C$88 -> 636870 | D18: 0 | E18: =C18 -> 636870 | F18: =B18-D18 -> 8970000
A19: 2 | B19: =F18 -> 8970000 | C19: =B19*Assumptions!$C$88 -> 636870 | D19: 0 | E19: =C19 -> 636870 | F19: =B19-D19 -> 8970000
A20: 3 | B20: =F19 -> 8970000 | C20: =B20*Assumptions!$C$88 -> 636870 | D20: =Debt!$B$17-C20 -> 93265.086 | E20: =Debt!$B$17 -> 730135.09 | F20: =B20-D20 -> 8876734.9
A21: 4 | B21: =F20 -> 8876734.9 | C21: =B21*Assumptions!$C$88 -> 630248.18 | D21: =Debt!$B$17-C21 -> 99886.907 | E21: =Debt!$B$17 -> 730135.09 | F21: =B21-D21 -> 8776848
A22: 5 | B22: =F21 -> 8776848 | C22: =B22*Assumptions!$C$88 -> 623156.21 | D22: =Debt!$B$17-C22 -> 106978.88 | E22: =Debt!$B$17 -> 730135.09 | F22: =B22-D22 -> 8669869.1

Sheet Capital
A1: CAPITAL — Sources & Uses
A4: USES
A5: Purchase Price | B5: =Assumptions!$C$7 -> 13800000
A6: Closing Costs | B6: =Assumptions!$C$11 -> 207000
A7: Renovation Capex (24 classic units) | B7: ='Unit Mix'!$D$18 -> 491040
A8: TOTAL USES | B8: =SUM(B5:B7) -> 14498040
A10: SOURCES
A11: Senior Loan (sized on Debt tab) | B11: =Debt!$C$9 -> 8970000
A12: Sponsor Equity (plug) | B12: =Capital!$B$8-B11 -> 5528040
A13: TOTAL SOURCES | B13: =SUM(B11:B12) -> 14498040
A15: EQUITY SPLIT
A16: LP Equity | B16: =Capital!$B$12*(1-Assumptions!$C$108) -> 4975236
A17: GP Equity (co-invest) | B17: =Capital!$B$12*Assumptions!$C$108 -> 552804
A19: CHECK: Sources - Uses | B19: =Capital!$B$13-Capital!$B$8 -> 0

Sheet Returns
A1: RETURNS — Unlevered & Levered, 5-Year Hold
A4: EXIT VALUATION — tax-adjusted
A5: Entry Cap Rate (Year-1 model NOI / Purchase Price) | B5: ='Operating Model'!$B$43/Assumptions!$C$7 -> 0.072295921
A6: Exit Cap Rate — base case (entry + 50bps) | B6: =Returns!$B$5+Assumptions!$C$97 -> 0.077295921
A7: Exit Cap Rate — sensitivity ceiling (entry + 100bps) | B7: =Returns!$B$5+Assumptions!$C$98 -> 0.082295921
A8: Effective Tax Rate at Exit (same cost-of-sale factor as entry) | B8: =Assumptions!$C$14*Assumptions!$C$16 -> 0.01686349
A9: Forward NOI Before Property Tax (Year 6, for exit) | B9: ='Operating Model'!$G$44 -> 1299871.8
A10: EXIT PRICE = Fwd NOI pretax / (Exit Cap + Eff. Tax Rate) | B10: =Returns!$B$9/(Returns!$B$6+Returns!$B$8) -> 13805012
A11: Less: Cost of Sale | B11: =-Returns!$B$10*Assumptions!$C$99 -> -276100.23
A12: Less: Loan Payoff (Debt tab, End Balance Year 5) | B12: =-Debt!$F$22 -> -8669869.1
A13: NET SALE PROCEEDS TO EQUITY | B13: =Returns!$B$10+Returns!$B$11+Returns!$B$12 -> 4859042.2
A14: Net Sale Proceeds, UNLEVERED (no loan payoff) | B14: =Returns!$B$10+Returns!$B$11 -> 13528911
A16: CASH FLOWS ($) — Year 0 = closing, Years 1-5 = operations + exit in Year 5
B17: Year 0 | C17: Year 1 | D17: Year 2 | E17: Year 3 | F17: Year 4 | G17: Year 5
A18: Unlevered CF (NOI + reserves + roof/recert capex) | C18: ='Operating Model'!$B$49 -> 968583.71 | D18: ='Operating Model'!$C$49 -> 790159.86 | E18: ='Operating Model'!$D$49 -> 934046.98 | F18: ='Operating Model'!$E$49 -> 920579.04 | G18: ='Operating Model'!$F$49 -> 906387.34
A19: + Net Sale Proceeds (Year 5 only, unlevered) | C19: 0 | D19: 0 | E19: 0 | F19: 0 | G19: =Returns!$B$14 -> 13528911
A20: TOTAL UNLEVERED CASH FLOW TO EQUITY | B20: =-B28 -> -14498040 | C20: =C18+C19 -> 968583.71 | D20: =D18+D19 -> 790159.86 | E20: =E18+E19 -> 934046.98 | F20: =F18+F19 -> 920579.04 | G20: =G18+G19 -> 14435299
A21: Less: Debt Service | C21: =-Debt!$E$17 -> 0 | D21: =-Debt!$E$18 -> -636870 | E21: =-Debt!$E$19 -> -636870 | F21: =-Debt!$E$20 -> -730135.09 | G21: =-Debt!$E$21 -> -730135.09
A22: Levered CF from Operations | C22: =C18+C21 -> 968583.71 | D22: =D18+D21 -> 153289.86 | E22: =E18+E21 -> 297176.98 | F22: =F18+F21 -> 190443.95 | G22: =G18+G21 -> 176252.25
A23: + Net Sale Proceeds (Year 5 only, levered) | C23: 0 | D23: 0 | E23: 0 | F23: 0 | G23: =Returns!$B$13 -> 4859042.2
A24: TOTAL LEVERED CASH FLOW TO EQUITY | B24: =-B27 -> -5528040 | C24: =C22+C23 -> 968583.71 | D24: =D22+D23 -> 153289.86 | E24: =E22+E23 -> 297176.98 | F24: =F22+F23 -> 190443.95 | G24: =G22+G23 -> 5035294.4
A26: RETURNS SUMMARY
A27: Total Equity Invested (Year 0) | B27: =Capital!$B$12 -> 5528040
A28: Total Uses, All-Cash (Year 0, unlevered basis) | B28: =Capital!$B$8 -> 14498040
A29: Unlevered IRR | B29: =IFERROR(IRR(B20:G20),"N/A - no sign change / undefined") -> 0.050257644
A30: Levered IRR | B30: =IFERROR(IRR(B24:G24),"N/A - no sign change / undefined") -> 0.044995327
A31: Unlevered Equity Multiple | B31: =SUM(C20:G20)/B28 -> 1.244904
A32: Levered Equity Multiple | B32: =SUM(C24:G24)/B27 -> 1.2020154
A33: Peak Equity (single close, no follow-on calls) | B33: =B27 -> 5528040
A35: CASH-ON-CASH BY YEAR (levered)
C36: =C22/B27 -> 0.17521286 | D36: =D22/B27 -> 0.027729514 | E36: =E22/B27 -> 0.05375811 | F36: =F22/B27 -> 0.034450538 | G36: =G22/B27 -> 0.031883318

Sheet Waterfall
A1: WATERFALL — 8% Pref -> ROC -> 70/30 to 12% IRR -> 50/50
A3: Method: each tier tracks a compounding 'hurdle balance' (what LP is owed at that tier's rate) that is debited by every LP dollar received. The balance hitting zero is mathematically equivalent to LP achieving exactly that IRR — no iterative solver needed.
B5: Year 0 | C5: Year 1 | D5: Year 2 | E5: Year 3 | F5: Year 4 | G5: Year 5
A6: Available Cash for Distribution | B6: 0 | C6: =Returns!C$24 -> 968583.71 | D6: =Returns!D$24 -> 153289.86 | E6: =Returns!E$24 -> 297176.98 | F6: =Returns!F$24 -> 190443.95 | G6: =Returns!G$24 -> 5035294.4
A7: LP Investment / GP Investment (Year 0) | B7: =-Capital!$B$16 -> -4975236
B8: =-Capital!$B$17 -> -552804
A10: TIER 1 — Return of Capital + 8% Preferred Return (100% LP)
A11: Hurdle Balance, End of Year (8% compounding) | B11: =Capital!$B$16 -> 4975236 | C11: =B11*(1+Assumptions!$C$102)-C12 -> 4404671.2 | D11: =C11*(1+Assumptions!$C$102)-D12 -> 4603755 | E11: =D11*(1+Assumptions!$C$102)-E12 -> 4674878.4 | F11: =E11*(1+Assumptions!$C$102)-F12 -> 4858424.7 | G11: =F11*(1+Assumptions!$C$102)-G12 -> 211804.27
A12: Tier 1 Distribution to LP | C12: =MIN(C6,B11*(1+Assumptions!$C$102)) -> 968583.71 | D12: =MIN(D6,C11*(1+Assumptions!$C$102)) -> 153289.86 | E12: =MIN(E6,D11*(1+Assumptions!$C$102)) -> 297176.98 | F12: =MIN(F6,E11*(1+Assumptions!$C$102)) -> 190443.95 | G12: =MIN(G6,F11*(1+Assumptions!$C$102)) -> 5035294.4
A14: Remaining Cash After Tier 1 | C14: =C6-C12 -> 0 | D14: =D6-D12 -> 0 | E14: =E6-E12 -> 0 | F14: =F6-F12 -> 0 | G14: =G6-G12 -> 0
A16: TIER 2 — 70/30 LP/GP up to a 12% LP IRR
A17: 12% Hurdle Balance, End of Year (compounding, net of ALL LP $ incl. Tier 1) | B17: =Capital!$B$16 -> 4975236 | C17: =C18-C20 -> 4603680.6 | D17: =D18-D20 -> 5002832.4 | E17: =E18-E20 -> 5305995.3 | F17: =F18-F20 -> 5752270.8 | G17: =G18-G20 -> 1407248.9
A18: 12% Hurdle Balance After Tier-1 Cash Applied | C18: =B17*(1+Assumptions!$C$105)-C12 -> 4603680.6 | D18: =C17*(1+Assumptions!$C$105)-D12 -> 5002832.4 | E18: =D17*(1+Assumptions!$C$105)-E12 -> 5305995.3 | F18: =E17*(1+Assumptions!$C$105)-F12 -> 5752270.8 | G18: =F17*(1+Assumptions!$C$105)-G12 -> 1407248.9
A19: Tier 2 Total Distribution (LP+GP) | C19: =MIN(C14,MAX(0,C18)/Assumptions!$C$103) -> 0 | D19: =MIN(D14,MAX(0,D18)/Assumptions!$C$103) -> 0 | E19: =MIN(E14,MAX(0,E18)/Assumptions!$C$103) -> 0 | F19: =MIN(F14,MAX(0,F18)/Assumptions!$C$103) -> 0 | G19: =MIN(G14,MAX(0,G18)/Assumptions!$C$103) -> 0
A20: LP share (70%) | C20: =C19*Assumptions!$C$103 -> 0 | D20: =D19*Assumptions!$C$103 -> 0 | E20: =E19*Assumptions!$C$103 -> 0 | F20: =F19*Assumptions!$C$103 -> 0 | G20: =G19*Assumptions!$C$103 -> 0
A21: GP share (30%) | C21: =C19*Assumptions!$C$104 -> 0 | D21: =D19*Assumptions!$C$104 -> 0 | E21: =E19*Assumptions!$C$104 -> 0 | F21: =F19*Assumptions!$C$104 -> 0 | G21: =G19*Assumptions!$C$104 -> 0
A22: Remaining Cash After Tier 2 | C22: =C14-C19 -> 0 | D22: =D14-D19 -> 0 | E22: =E14-E19 -> 0 | F22: =F14-F19 -> 0 | G22: =G14-G19 -> 0
A24: TIER 3 — 50/50 LP/GP thereafter
A25: Tier 3 Total Distribution (LP+GP) | C25: =C22 -> 0 | D25: =D22 -> 0 | E25: =E22 -> 0 | F25: =F22 -> 0 | G25: =G22 -> 0
A26: LP share (50%) | C26: =C25*Assumptions!$C$106 -> 0 | D26: =D25*Assumptions!$C$106 -> 0 | E26: =E25*Assumptions!$C$106 -> 0 | F26: =F25*Assumptions!$C$106 -> 0 | G26: =G25*Assumptions!$C$106 -> 0
A27: GP share (50%) | C27: =C25*Assumptions!$C$107 -> 0 | D27: =D25*Assumptions!$C$107 -> 0 | E27: =E25*Assumptions!$C$107 -> 0 | F27: =F25*Assumptions!$C$107 -> 0 | G27: =G25*Assumptions!$C$107 -> 0
A29: TOTALS BY PARTY
A30: LP Total Distribution | B30: =-Capital!$B$16 -> -4975236 | C30: =C12+C20+C26 -> 968583.71 | D30: =D12+D20+D26 -> 153289.86 | E30: =E12+E20+E26 -> 297176.98 | F30: =F12+F20+F26 -> 190443.95 | G30: =G12+G20+G26 -> 5035294.4
A31: GP Total Distribution | B31: =-Capital!$B$17 -> -552804 | C31: =C21+C27 -> 0 | D31: =D21+D27 -> 0 | E31: =E21+E27 -> 0 | F31: =F21+F27 -> 0 | G31: =G21+G27 -> 0
A33: CHECK — LP + GP distributions must equal Available Cash each year
C34: =C30+C31-C6 -> 0 | D34: =D30+D31-D6 -> 0 | E34: =E30+E31-E6 -> 0 | F34: =F30+F31-F6 -> 0 | G34: =G30+G31-G6 -> 0
A36: LP / GP RETURNS
A37: LP IRR | B37: =IFERROR(IRR(B30:G30),"N/A - no sign change / undefined") -> 0.072203953
A38: GP IRR | B38: =IFERROR(IRR(B31:G31),"N/A - GP receives $0 in this scenario, IRR undefined") -> N/A - GP receives $0 in this scenario, IRR undefined
A39: LP Equity Multiple | B39: =SUM(C30:G30)/Capital!$B$16 -> 1.3355726
A40: GP Equity Multiple | B40: =SUM(C31:G31)/Capital!$B$17 -> 0

Sheet Sensitivity
A1: SENSITIVITY
A3: Each grid is a self-contained proxy calc: Year-1 NOI starts from the Operating Model's base case and is adjusted only for what that table's two axes change (tax, debt sizing, renovation NOI/capex, or a flat rent-growth override); it does not re-run the full 97-unit/burn-off engine 25 times. Debt is re-sized where price or capex changes; held at the base-case loan where it doesn't. IRR/EM values are pulled from the 'calculation detail' rows near the bottom of this tab.
A5: TABLE 1 — Exit Cap Rate (rows) x Flat Rent Growth Override (cols) | Levered IRR (top) / Equity Multiple (bottom)
A6: Exit Cap \ Rent Gr. | B6: 0.015 | C6: 0.02 | D6: 0.025 | E6: 0.03 | F6: 0.035
A7: Entry+0bps | B7: =Sensitivity!$H$53 -> -0.019719867 | C7: =Sensitivity!$H$54 -> -0.00069671481 | D7: =Sensitivity!$H$55 -> 0.017418735 | E7: =Sensitivity!$H$56 -> 0.034749027 | F7: =Sensitivity!$H$57 -> 0.051393293
A8: Entry+25bps | B8: =Sensitivity!$H$58 -> -0.035069698 | C8: =Sensitivity!$H$59 -> -0.015279855 | D8: =Sensitivity!$H$60 -> 0.0034874537 | E8: =Sensitivity!$H$61 -> 0.021378239 | F8: =Sensitivity!$H$62 -> 0.03850904
A9: Entry+50bps (base) | B9: =Sensitivity!$H$63 -> -0.050647209 | C9: =Sensitivity!$H$64 -> -0.030005193 | D9: =Sensitivity!$H$65 -> -0.010520647 | E9: =Sensitivity!$H$66 -> 0.0079816532 | F9: =Sensitivity!$H$67 -> 0.025639501
A10: Entry+75bps | B10: =Sensitivity!$H$68 -> -0.06651956 | C10: =Sensitivity!$H$69 -> -0.044924497 | D10: =Sensitivity!$H$70 -> -0.024646948 | E10: =Sensitivity!$H$71 -> -0.0054748984 | F10: =Sensitivity!$H$72 -> 0.012755636
A11: Entry+100bps | B11: =Sensitivity!$H$73 -> -0.082764171 | C11: =Sensitivity!$H$74 -> -0.060095659 | D11: =Sensitivity!$H$75 -> -0.038936483 | E11: =Sensitivity!$H$76 -> -0.019027706 | F11: =Sensitivity!$H$77 -> -0.00017273995
A12: (same grid, Equity Multiple)
A13: Entry+0bps | B13: =Sensitivity!$I$53 -> 0.91790572 | C13: =Sensitivity!$I$54 -> 0.99699148 | D13: =Sensitivity!$I$55 -> 1.0778764 | E13: =Sensitivity!$I$56 -> 1.1605945 | F13: =Sensitivity!$I$57 -> 1.2451801
A14: Entry+25bps | B14: =Sensitivity!$I$58 -> 0.85874414 | C14: =Sensitivity!$I$59 -> 0.9360596 | D14: =Sensitivity!$I$60 -> 1.0151303 | E14: =Sensitivity!$I$61 -> 1.0959894 | F14: =Sensitivity!$I$62 -> 1.1786703
A15: Entry+50bps (base) | B15: =Sensitivity!$I$63 -> 0.80272412 | C15: =Sensitivity!$I$64 -> 0.87836329 | D15: =Sensitivity!$I$65 -> 0.95571615 | E15: =Sensitivity!$I$66 -> 1.0348149 | F15: =Sensitivity!$I$67 -> 1.1156923
A16: Entry+75bps | B16: =Sensitivity!$I$68 -> 0.74960191 | C16: =Sensitivity!$I$69 -> 0.8236515 | D16: =Sensitivity!$I$70 -> 0.89937533 | E16: =Sensitivity!$I$71 -> 0.97680486 | F16: =Sensitivity!$I$72 -> 1.055972
A17: Entry+100bps | B17: =Sensitivity!$I$73 -> 0.69915832 | C17: =Sensitivity!$I$74 -> 0.77169849 | D17: =Sensitivity!$I$75 -> 0.84587544 | E17: =Sensitivity!$I$76 -> 0.92171989 | F17: =Sensitivity!$I$77 -> 0.99926298
A20: TABLE 2 — Purchase Price (rows) x Exit Cap Spread over Entry (cols) | Levered IRR (top) / Equity Multiple (bottom)
A21: Price \ Exit Spread | B21: Entry+0bps | C21: Entry+25bps | D21: Entry+50bps (base) | E21: Entry+75bps | F21: Entry+100bps
A22: -10% | B22: =Sensitivity!$H$78 -> 0.051332659 | C22: =Sensitivity!$H$79 -> 0.039832924 | D22: =Sensitivity!$H$80 -> 0.028340946 | E22: =Sensitivity!$H$81 -> 0.016835101 | F22: =Sensitivity!$H$82 -> 0.0052929423
A23: -5% | B23: =Sensitivity!$H$83 -> 0.032313923 | C23: =Sensitivity!$H$84 -> 0.019597144 | D23: =Sensitivity!$H$85 -> 0.0068504523 | E23: =Sensitivity!$H$86 -> -0.0059563133 | F23: =Sensitivity!$H$87 -> -0.018855204
A24: Base ($13.8M) | B24: =Sensitivity!$H$88 -> 0.014043546 | C24: =Sensitivity!$H$89 -> 3.1200431e-05 | D24: =Sensitivity!$H$90 -> -0.014063502 | E24: =Sensitivity!$H$91 -> -0.028282761 | F24: =Sensitivity!$H$92 -> -0.042672601
A25: +5% | B25: =Sensitivity!$H$93 -> -0.0036394209 | C25: =Sensitivity!$H$94 -> -0.019035295 | D25: =Sensitivity!$H$95 -> -0.034584761 | E25: =Sensitivity!$H$96 -> -0.050347067 | F25: =Sensitivity!$H$97 -> -0.066388702
A26: +10% | B26: =Sensitivity!$H$98 -> -0.020874882 | C26: =Sensitivity!$H$99 -> -0.037753717 | D26: =Sensitivity!$H$100 -> -0.054881374 | E26: =Sensitivity!$H$101 -> -0.072341368 | F26: =Sensitivity!$H$102 -> -0.090230416
A27: (same grid, Equity Multiple)
A28: -10% | B28: =Sensitivity!$I$78 -> 1.2356028 | C28: =Sensitivity!$I$79 -> 1.1782431 | D28: =Sensitivity!$I$80 -> 1.1236394 | E28: =Sensitivity!$I$81 -> 1.0715976 | F28: =Sensitivity!$I$82 -> 1.0219416
A29: -5% | B29: =Sensitivity!$I$83 -> 1.1465131 | C29: =Sensitivity!$I$84 -> 1.0864295 | D29: =Sensitivity!$I$85 -> 1.0293849 | E29: =Sensitivity!$I$86 -> 0.97515457 | F29: =Sensitivity!$I$87 -> 0.92353514
A30: Base ($13.8M) | B30: =Sensitivity!$I$88 -> 1.0628589 | C30: =Sensitivity!$I$89 -> 1.0001355 | D30: =Sensitivity!$I$90 -> 0.9407428 | E30: =Sensitivity!$I$91 -> 0.88442237 | F30: =Sensitivity!$I$92 -> 0.83094182
A31: +5% | B31: =Sensitivity!$I$93 -> 0.98392974 | C31: =Sensitivity!$I$94 -> 0.91865079 | D31: =Sensitivity!$I$95 -> 0.85700194 | E31: =Sensitivity!$I$96 -> 0.79868856 | F31: =Sensitivity!$I$97 -> 0.7434471
A32: +10% | B32: =Sensitivity!$I$98 -> 0.9091337 | C32: =Sensitivity!$I$99 -> 0.84138352 | D32: =Sensitivity!$I$100 -> 0.77756983 | E32: =Sensitivity!$I$101 -> 0.71735924 | F32: =Sensitivity!$I$102 -> 0.66045495
A35: TABLE 3 — Renovation Premium/mo (rows) x Renovation Cost/unit (cols) | Levered IRR (top) / Equity Multiple (bottom)
A36: Premium \ Cost | B36: -20% | C36: -10% | D36: Base ($20,460) | E36: +10% | F36: +20%
A37: $100/mo | B37: =Sensitivity!$H$103 -> -0.12952934 | C37: =Sensitivity!$H$104 -> -0.13136725 | D37: =Sensitivity!$H$105 -> -0.13318343 | E37: =Sensitivity!$H$106 -> -0.13497834 | F37: =Sensitivity!$H$107 -> -0.13675241
A38: $137.50/mo | B38: =Sensitivity!$H$108 -> -0.11279001 | C38: =Sensitivity!$H$109 -> -0.11466408 | D38: =Sensitivity!$H$110 -> -0.11651598 | E38: =Sensitivity!$H$111 -> -0.11834618 | F38: =Sensitivity!$H$112 -> -0.12015514
A39: $175/mo (base) | B39: =Sensitivity!$H$113 -> -0.097114495 | C39: =Sensitivity!$H$114 -> -0.09902288 | D39: =Sensitivity!$H$115 -> -0.10090868 | E39: =Sensitivity!$H$116 -> -0.10277238 | F39: =Sensitivity!$H$117 -> -0.10461444
A40: $212.50/mo | B40: =Sensitivity!$H$118 -> -0.082353662 | C40: =Sensitivity!$H$119 -> -0.084294765 | D40: =Sensitivity!$H$120 -> -0.08621289 | E40: =Sensitivity!$H$121 -> -0.088108522 | F40: =Sensitivity!$H$122 -> -0.089982132
A41: $250/mo | B41: =Sensitivity!$H$123 -> -0.06838871 | C41: =Sensitivity!$H$124 -> -0.070361132 | D41: =Sensitivity!$H$125 -> -0.072310194 | E41: =Sensitivity!$H$126 -> -0.074236388 | F41: =Sensitivity!$H$127 -> -0.076140194
A42: (same grid, Equity Multiple)
A43: $100/mo | B43: =Sensitivity!$I$103 -> 0.56391423 | C43: =Sensitivity!$I$104 -> 0.55886024 | D43: =Sensitivity!$I$105 -> 0.55389605 | E43: =Sensitivity!$I$106 -> 0.54901927 | F43: =Sensitivity!$I$107 -> 0.54422761
A44: $137.50/mo | B44: =Sensitivity!$I$108 -> 0.60882646 | C44: =Sensitivity!$I$109 -> 0.60336996 | D44: =Sensitivity!$I$110 -> 0.5980104 | E44: =Sensitivity!$I$111 -> 0.59274521 | F44: =Sensitivity!$I$112 -> 0.58757193
A45: $175/mo (base) | B45: =Sensitivity!$I$113 -> 0.6537387 | C45: =Sensitivity!$I$114 -> 0.64787968 | D45: =Sensitivity!$I$115 -> 0.64212475 | E45: =Sensitivity!$I$116 -> 0.63647116 | F45: =Sensitivity!$I$117 -> 0.63091626
A46: $212.50/mo | B46: =Sensitivity!$I$118 -> 0.69865094 | C46: =Sensitivity!$I$119 -> 0.69238941 | D46: =Sensitivity!$I$120 -> 0.68623911 | E46: =Sensitivity!$I$121 -> 0.68019711 | F46: =Sensitivity!$I$122 -> 0.67426058
A47: $250/mo | B47: =Sensitivity!$I$123 -> 0.74356318 | C47: =Sensitivity!$I$124 -> 0.73689913 | D47: =Sensitivity!$I$125 -> 0.73035346 | E47: =Sensitivity!$I$126 -> 0.72392306 | F47: =Sensitivity!$I$127 -> 0.7176049
A51: CALCULATION DETAIL (per-scenario cash flows -- not for review, feeds the grids above)
A52: Scenario | B52: Year 0 | C52: Year 1 | D52: Year 2 | E52: Year 3 | F52: Year 4 | G52: Year 5 | H52: IRR | I52: EM
A53: T1 Entry+0bps / 1.5% | B53: =-(Capital!$B$12) -> -5528040 | C53: =(('Operating Model'!$B$43*(1+0.015)^1)-(Debt!$C$9*Assumptions!$C$88)) -> 375778.97 | D53: =(('Operating Model'!$B$43*(1+0.015)^2)-(Debt!$C$9*Assumptions!$C$88)) -> 390968.71 | E53: =(('Operating Model'!$B$43*(1+0.015)^3)-(-PMT(Assumptions!$C$88,Assumptions!$C$93,Debt!$C$9))) -> 313121.2 | F53: =(('Operating Model'!$B$43*(1+0.015)^4)-(-PMT(Assumptions!$C$88,Assumptions!$C$93,Debt!$C$9))) -> 328770.04 | G53: =(('Operating Model'!$B$43*(1+0.015)^5)-(-PMT(Assumptions!$C$88,Assumptions!$C$93,Debt!$C$9))+((('Operating Model'!$B$43*(1+0.015)^6)/((Returns!$B$5+0)+Returns!$B$8))*(1-Assumptions!$C$99)-(Debt!$C$9+CUMPRINC(Assumptions!$C$88,Assumptions!$C$93,Debt!$C$9,1,3,0)))) -> 3665580.6 | H53: =IFERROR(IRR(B53:G53),"N/A") -> -0.019719867 | I53: =SUM(C53:G53)/(Capital!$B$12) -> 0.91790572
A54: T1 Entry+0bps / 2.0% | B54: =-(Capital!$B$12) -> -5528040 | C54: =(('Operating Model'!$B$43*(1+0.02)^1)-(Debt!$C$9*Assumptions!$C$88)) -> 380767.39 | D54: =(('Operating Model'!$B$43*(1+0.02)^2)-(Debt!$C$9*Assumptions!$C$88)) -> 401120.14 | E54: =(('Operating Model'!$B$43*(1+0.02)^3)-(-PMT(Assumptions!$C$88,Assumptions!$C$93,Debt!$C$9))) -> 328614.85 | F54: =(('Operating Model'!$B$43*(1+0.02)^4)-(-PMT(Assumptions!$C$88,Assumptions!$C$93,Debt!$C$9))) -> 349789.85 | G54: =(('Operating Model'!$B$43*(1+0.02)^5)-(-PMT(Assumptions!$C$88,Assumptions!$C$93,Debt!$C$9))+((('Operating Model'!$B$43*(1+0.02)^6)/((Returns!$B$5+0)+Returns!$B$8))*(1-Assumptions!$C$99)-(Debt!$C$9+CUMPRINC(Assumptions!$C$88,Assumptions!$C$93,Debt!$C$9,1,3,0)))) -> 4051116.5 | H54: =IFERROR(IRR(B54:G54),"N/A") -> -0.00069671481 | I54: =SUM(C54:G54)/(Capital!$B$12) -> 0.99699148
A55: T1 Entry+0bps / 2.5% | B55: =-(Capital!$B$12) -> -5528040 | C55: =(('Operating Model'!$B$43*(1+0.025)^1)-(Debt!$C$9*Assumptions!$C$88)) -> 385755.81 | D55: =(('Operating Model'!$B$43*(1+0.025)^2)-(Debt!$C$9*Assumptions!$C$88)) -> 411321.45 | E55: =(('Operating Model'!$B$43*(1+0.025)^3)-(-PMT(Assumptions!$C$88,Assumptions!$C$93,Debt!$C$9))) -> 344261.15 | F55: =(('Operating Model'!$B$43*(1+0.025)^4)-(-PMT(Assumptions!$C$88,Assumptions!$C$93,Debt!$C$9))) -> 371121.06 | G55: =(('Operating Model'!$B$43*(1+0.025)^5)-(-PMT(Assumptions!$C$88,Assumptions!$C$93,Debt!$C$9))+((('Operating Model'!$B$43*(1+0.025)^6)/((Returns!$B$5+0)+Returns!$B$8))*(1-Assumptions!$C$99)-(Debt!$C$9+CUMPRINC(Assumptions!$C$88,Assumptions!$C$93,Debt!$C$9,1,3,0)))) -> 4446084.6 | H55: =IFERROR(IRR(B55:G55),"N/A") -> 0.017418735 | I55: =SUM(C55:G55)/(Capital!$B$12) -> 1.0778764
A56: T1 Entry+0bps / 3.0% | B56: =-(Capital!$B$12) -> -5528040 | C56: =(('Operating Model'!$B$43*(1+0.03)^1)-(Debt!$C$9*Assumptions!$C$88)) -> 390744.23 | D56: =(('Operating Model'!$B$43*(1+0.03)^2)-(Debt!$C$9*Assumptions!$C$88)) -> 421572.65 | E56: =(('Operating Model'!$B$43*(1+0.03)^3)-(-PMT(Assumptions!$C$88,Assumptions!$C$93,Debt!$C$9))) -> 360060.85 | F56: =(('Operating Model'!$B$43*(1+0.03)^4)-(-PMT(Assumptions!$C$88,Assumptions!$C$93,Debt!$C$9))) -> 392766.72 | G56: =(('Operating Model'!$B$43*(1+0.03)^5)-(-PMT(Assumptions!$C$88,Assumptions!$C$93,Debt!$C$9))+((('Operating Model'!$B$43*(1+0.03)^6)/((Returns!$B$5+0)+Returns!$B$8))*(1-Assumptions!$C$99)-(Debt!$C$9+CUMPRINC(Assumptions!$C$88,Assumptions!$C$93,Debt!$C$9,1,3,0)))) -> 4850668.4 | H56: =IFERROR(IRR(B56:G56),"N/A") -> 0.034749027 | I56: =SUM(C56:G56)/(Capital!$B$12) -> 1.1605945
A57: T1 Entry+0bps / 3.5% | B57: =-(Capital!$B$12) -> -5528040 | C57: =(('Operating Model'!$B$43*(1+0.035)^1)-(Debt!$C$9*Assumptions!$C$88)) -> 395732.64 | D57: =(('Operating Model'!$B$43*(1+0.035)^2)-(Debt!$C$9*Assumptions!$C$88)) -> 431873.74 | E57: =(('Operating Model'!$B$43*(1+0.035)^3)-(-PMT(Assumptions!$C$88,Assumptions!$C$93,Debt!$C$9))) -> 376014.68 | F57: =(('Operating Model'!$B$43*(1+0.035)^4)-(-PMT(Assumptions!$C$88,Assumptions!$C$93,Debt!$C$9))) -> 414729.92 | G57: =(('Operating Model'!$B$43*(1+0.035)^5)-(-PMT(Assumptions!$C$88,Assumptions!$C$93,Debt!$C$9))+((('Operating Model'!$B$43*(1+0.035)^6)/((Returns!$B$5+0)+Returns!$B$8))*(1-Assumptions!$C$99)-(Debt!$C$9+CUMPRINC(Assumptions!$C$88,Assumptions!$C$93,Debt!$C$9,1,3,0)))) -> 5265054.4 | H57: =IFERROR(IRR(B57:G57),"N/A") -> 0.051393293 | I57: =SUM(C57:G57)/(Capital!$B$12) -> 1.2451801
A58: T1 Entry+25bps / 1.5% | B58: =-(Capital!$B$12) -> -5528040 | C58: =(('Operating Model'!$B$43*(1+0.015)^1)-(Debt!$C$9*Assumptions!$C$88)) -> 375778.97 | D58: =(('Operating Model'!$B$43*(1+0.015)^2)-(Debt!$C$9*Assumptions!$C$88)) -> 390968.71 | E58: =(('Operating Model'!$B$43*(1+0.015)^3)-(-PMT(Assumptions!$C$88,Assumptions!$C$93,Debt!$C$9))) -> 313121.2 | F58: =(('Operating Model'!$B$43*(1+0.015)^4)-(-PMT(Assumptions!$C$88,Assumptions!$C$93,Debt!$C$9))) -> 328770.04 | G58: =(('Operating Model'!$B$43*(1+0.015)^5)-(-PMT(Assumptions!$C$88,Assumptions!$C$93,Debt!$C$9))+((('Operating Model'!$B$43*(1+0.015)^6)/((Returns!$B$5+0.0025)+Returns!$B$8))*(1-Assumptions!$C$99)-(Debt!$C$9+CUMPRINC(Assumptions!$C$88,Assumptions!$C$93,Debt!$C$9,1,3,0)))) -> 3338533 | H58: =IFERROR(IRR(B58:G58),"N/A") -> -0.035069698 | I58: =SUM(C58:G58)/(Capital!$B$12) -> 0.85874414
A59: T1 Entry+25bps / 2.0% | B59: =-(Capital!$B$12) -> -5528040 | C59: =(('Operating Model'!$B$43*(1+0.02)^1)-(Debt!$C$9*Assumptions!$C$88)) -> 380767.39 | D59: =(('Operating Model'!$B$43*(1+0.02)^2)-(Debt!$C$9*Assumptions!$C$88)) -> 401120.14 | E59: =(('Operating Model'!$B$43*(1+0.02)^3)-(-PMT(Assumptions!$C$88,Assumptions!$C$93,Debt!$C$9))) -> 328614.85 | F59: =(('Operating Model'!$B$43*(1+0.02)^4)-(-PMT(Assumptions!$C$88,Assumptions!$C$93,Debt!$C$9))) -> 349789.85 | G59: =(('Operating Model'!$B$43*(1+0.02)^5)-(-PMT(Assumptions!$C$88,Assumptions!$C$93,Debt!$C$9))+((('Operating Model'!$B$43*(1+0.02)^6)/((Returns!$B$5+0.0025)+Returns!$B$8))*(1-Assumptions!$C$99)-(Debt!$C$9+CUMPRINC(Assumptions!$C$88,Assumptions!$C$93,Debt!$C$9,1,3,0)))) -> 3714282.7 | H59: =IFERROR(IRR(B59:G59),"N/A") -> -0.015279855 | I59: =SUM(C59:G59)/(Capital!$B$12) -> 0.9360596
A60: T1 Entry+25bps / 2.5% | B60: =-(Capital!$B$12) -> -5528040 | C60: =(('Operating Model'!$B$43*(1+0.025)^1)-(Debt!$C$9*Assumptions!$C$88)) -> 385755.81 | D60: =(('Operating Model'!$B$43*(1+0.025)^2)-(Debt!$C$9*Assumptions!$C$88)) -> 411321.45 | E60: =(('Operating Model'!$B$43*(1+0.025)^3)-(-PMT(Assumptions!$C$88,Assumptions!$C$93,Debt!$C$9))) -> 344261.15 | F60: =(('Operating Model'!$B$43*(1+0.025)^4)-(-PMT(Assumptions!$C$88,Assumptions!$C$93,Debt!$C$9))) -> 371121.06 | G60: =(('Operating Model'!$B$43*(1+0.025)^5)-(-PMT(Assumptions!$C$88,Assumptions!$C$93,Debt!$C$9))+((('Operating Model'!$B$43*(1+0.025)^6)/((Returns!$B$5+0.0025)+Returns!$B$8))*(1-Assumptions!$C$99)-(Debt!$C$9+CUMPRINC(Assumptions!$C$88,Assumptions!$C$93,Debt!$C$9,1,3,0)))) -> 4099221.6 | H60: =IFERROR(IRR(B60:G60),"N/A") -> 0.0034874537 | I60: =SUM(C60:G60)/(Capital!$B$12) -> 1.0151303
A61: T1 Entry+25bps / 3.0% | B61: =-(Capital!$B$12) -> -5528040 | C61: =(('Operating Model'!$B$43*(1+0.03)^1)-(Debt!$C$9*Assumptions!$C$88)) -> 390744.23 | D61: =(('Operating Model'!$B$43*(1+0.03)^2)-(Debt!$C$9*Assumptions!$C$88)) -> 421572.65 | E61: =(('Operating Model'!$B$43*(1+0.03)^3)-(-PMT(Assumptions!$C$88,Assumptions!$C$93,Debt!$C$9))) -> 360060.85 | F61: =(('Operating Model'!$B$43*(1+0.03)^4)-(-PMT(Assumptions!$C$88,Assumptions!$C$93,Debt!$C$9))) -> 392766.72 | G61: =(('Operating Model'!$B$43*(1+0.03)^5)-(-PMT(Assumptions!$C$88,Assumptions!$C$93,Debt!$C$9))+((('Operating Model'!$B$43*(1+0.03)^6)/((Returns!$B$5+0.0025)+Returns!$B$8))*(1-Assumptions!$C$99)-(Debt!$C$9+CUMPRINC(Assumptions!$C$88,Assumptions!$C$93,Debt!$C$9,1,3,0)))) -> 4493528.8 | H61: =IFERROR(IRR(B61:G61),"N/A") -> 0.021378239 | I61: =SUM(C61:G61)/(Capital!$B$12) -> 1.0959894
A62: T1 Entry+25bps / 3.5% | B62: =-(Capital!$B$12) -> -5528040 | C62: =(('Operating Model'!$B$43*(1+0.035)^1)-(Debt!$C$9*Assumptions!$C$88)) -> 395732.64 | D62: =(('Operating Model'!$B$43*(1+0.035)^2)-(Debt!$C$9*Assumptions!$C$88)) -> 431873.74 | E62: =(('Operating Model'!$B$43*(1+0.035)^3)-(-PMT(Assumptions!$C$88,Assumptions!$C$93,Debt!$C$9))) -> 376014.68 | F62: =(('Operating Model'!$B$43*(1+0.035)^4)-(-PMT(Assumptions!$C$88,Assumptions!$C$93,Debt!$C$9))) -> 414729.92 | G62: =(('Operating Model'!$B$43*(1+0.035)^5)-(-PMT(Assumptions!$C$88,Assumptions!$C$93,Debt!$C$9))+((('Operating Model'!$B$43*(1+0.035)^6)/((Returns!$B$5+0.0025)+Returns!$B$8))*(1-Assumptions!$C$99)-(Debt!$C$9+CUMPRINC(Assumptions!$C$88,Assumptions!$C$93,Debt!$C$9,1,3,0)))) -> 4897385.6 | H62: =IFERROR(IRR(B62:G62),"N/A") -> 0.03850904 | I62: =SUM(C62:G62)/(Capital!$B$12) -> 1.1786703
A63: T1 Entry+50bps (base) / 1.5% | B63: =-(Capital!$B$12) -> -5528040 | C63: =(('Operating Model'!$B$43*(1+0.015)^1)-(Debt!$C$9*Assumptions!$C$88)) -> 375778.97 | D63: =(('Operating Model'!$B$43*(1+0.015)^2)-(Debt!$C$9*Assumptions!$C$88)) -> 390968.71 | E63: =(('Operating Model'!$B$43*(1+0.015)^3)-(-PMT(Assumptions!$C$88,Assumptions!$C$93,Debt!$C$9))) -> 313121.2 | F63: =(('Operating Model'!$B$43*(1+0.015)^4)-(-PMT(Assumptions!$C$88,Assumptions!$C$93,Debt!$C$9))) -> 328770.04 | G63: =(('Operating Model'!$B$43*(1+0.015)^5)-(-PMT(Assumptions!$C$88,Assumptions!$C$93,Debt!$C$9))+((('Operating Model'!$B$43*(1+0.015)^6)/((Returns!$B$5+0.005)+Returns!$B$8))*(1-Assumptions!$C$99)-(Debt!$C$9+CUMPRINC(Assumptions!$C$88,Assumptions!$C$93,Debt!$C$9,1,3,0)))) -> 3028852.1 | H63: =IFERROR(IRR(B63:G63),"N/A") -> -0.050647209 | I63: =SUM(C63:G63)/(Capital!$B$12) -> 0.80272412
A64: T1 Entry+50bps (base) / 2.0% | B64: =-(Capital!$B$12) -> -5528040 | C64: =(('Operating Model'!$B$43*(1+0.02)^1)-(Debt!$C$9*Assumptions!$C$88)) -> 380767.39 | D64: =(('Operating Model'!$B$43*(1+0.02)^2)-(Debt!$C$9*Assumptions!$C$88)) -> 401120.14 | E64: =(('Operating Model'!$B$43*(1+0.02)^3)-(-PMT(Assumptions!$C$88,Assumptions!$C$93,Debt!$C$9))) -> 328614.85 | F64: =(('Operating Model'!$B$43*(1+0.02)^4)-(-PMT(Assumptions!$C$88,Assumptions!$C$93,Debt!$C$9))) -> 349789.85 | G64: =(('Operating Model'!$B$43*(1+0.02)^5)-(-PMT(Assumptions!$C$88,Assumptions!$C$93,Debt!$C$9))+((('Operating Model'!$B$43*(1+0.02)^6)/((Returns!$B$5+0.005)+Returns!$B$8))*(1-Assumptions!$C$99)-(Debt!$C$9+CUMPRINC(Assumptions!$C$88,Assumptions!$C$93,Debt!$C$9,1,3,0)))) -> 3395335.2 | H64: =IFERROR(IRR(B64:G64),"N/A") -> -0.030005193 | I64: =SUM(C64:G64)/(Capital!$B$12) -> 0.87836329
A65: T1 Entry+50bps (base) / 2.5% | B65: =-(Capital!$B$12) -> -5528040 | C65: =(('Operating Model'!$B$43*(1+0.025)^1)-(Debt!$C$9*Assumptions!$C$88)) -> 385755.81 | D65: =(('Operating Model'!$B$43*(1+0.025)^2)-(Debt!$C$9*Assumptions!$C$88)) -> 411321.45 | E65: =(('Operating Model'!$B$43*(1+0.025)^3)-(-PMT(Assumptions!$C$88,Assumptions!$C$93,Debt!$C$9))) -> 344261.15 | F65: =(('Operating Model'!$B$43*(1+0.025)^4)-(-PMT(Assumptions!$C$88,Assumptions!$C$93,Debt!$C$9))) -> 371121.06 | G65: =(('Operating Model'!$B$43*(1+0.025)^5)-(-PMT(Assumptions!$C$88,Assumptions!$C$93,Debt!$C$9))+((('Operating Model'!$B$43*(1+0.025)^6)/((Returns!$B$5+0.005)+Returns!$B$8))*(1-Assumptions!$C$99)-(Debt!$C$9+CUMPRINC(Assumptions!$C$88,Assumptions!$C$93,Debt!$C$9,1,3,0)))) -> 3770777.6 | H65: =IFERROR(IRR(B65:G65),"N/A") -> -0.010520647 | I65: =SUM(C65:G65)/(Capital!$B$12) -> 0.95571615
A66: T1 Entry+50bps (base) / 3.0% | B66: =-(Capital!$B$12) -> -5528040 | C66: =(('Operating Model'!$B$43*(1+0.03)^1)-(Debt!$C$9*Assumptions!$C$88)) -> 390744.23 | D66: =(('Operating Model'!$B$43*(1+0.03)^2)-(Debt!$C$9*Assumptions!$C$88)) -> 421572.65 | E66: =(('Operating Model'!$B$43*(1+0.03)^3)-(-PMT(Assumptions!$C$88,Assumptions!$C$93,Debt!$C$9))) -> 360060.85 | F66: =(('Operating Model'!$B$43*(1+0.03)^4)-(-PMT(Assumptions!$C$88,Assumptions!$C$93,Debt!$C$9))) -> 392766.72 | G66: =(('Operating Model'!$B$43*(1+0.03)^5)-(-PMT(Assumptions!$C$88,Assumptions!$C$93,Debt!$C$9))+((('Operating Model'!$B$43*(1+0.03)^6)/((Returns!$B$5+0.005)+Returns!$B$8))*(1-Assumptions!$C$99)-(Debt!$C$9+CUMPRINC(Assumptions!$C$88,Assumptions!$C$93,Debt!$C$9,1,3,0)))) -> 4155353.8 | H66: =IFERROR(IRR(B66:G66),"N/A") -> 0.0079816532 | I66: =SUM(C66:G66)/(Capital!$B$12) -> 1.0348149
A67: T1 Entry+50bps (base) / 3.5% | B67: =-(Capital!$B$12) -> -5528040 | C67: =(('Operating Model'!$B$43*(1+0.035)^1)-(Debt!$C$9*Assumptions!$C$88)) -> 395732.64 | D67: =(('Operating Model'!$B$43*(1+0.035)^2)-(Debt!$C$9*Assumptions!$C$88)) -> 431873.74 | E67: =(('Operating Model'!$B$43*(1+0.035)^3)-(-PMT(Assumptions!$C$88,Assumptions!$C$93,Debt!$C$9))) -> 376014.68 | F67: =(('Operating Model'!$B$43*(1+0.035)^4)-(-PMT(Assumptions!$C$88,Assumptions!$C$93,Debt!$C$9))) -> 414729.92 | G67: =(('Operating Model'!$B$43*(1+0.035)^5)-(-PMT(Assumptions!$C$88,Assumptions!$C$93,Debt!$C$9))+((('Operating Model'!$B$43*(1+0.035)^6)/((Returns!$B$5+0.005)+Returns!$B$8))*(1-Assumptions!$C$99)-(Debt!$C$9+CUMPRINC(Assumptions!$C$88,Assumptions!$C$93,Debt!$C$9,1,3,0)))) -> 4549240.5 | H67: =IFERROR(IRR(B67:G67),"N/A") -> 0.025639501 | I67: =SUM(C67:G67)/(Capital!$B$12) -> 1.1156923
A68: T1 Entry+75bps / 1.5% | B68: =-(Capital!$B$12) -> -5528040 | C68: =(('Operating Model'!$B$43*(1+0.015)^1)-(Debt!$C$9*Assumptions!$C$88)) -> 375778.97 | D68: =(('Operating Model'!$B$43*(1+0.015)^2)-(Debt!$C$9*Assumptions!$C$88)) -> 390968.71 | E68: =(('Operating Model'!$B$43*(1+0.015)^3)-(-PMT(Assumptions!$C$88,Assumptions!$C$93,Debt!$C$9))) -> 313121.2 | F68: =(('Operating Model'!$B$43*(1+0.015)^4)-(-PMT(Assumptions!$C$88,Assumptions!$C$93,Debt!$C$9))) -> 328770.04 | G68: =(('Operating Model'!$B$43*(1+0.015)^5)-(-PMT(Assumptions!$C$88,Assumptions!$C$93,Debt!$C$9))+((('Operating Model'!$B$43*(1+0.015)^6)/((Returns!$B$5+0.0075)+Returns!$B$8))*(1-Assumptions!$C$99)-(Debt!$C$9+CUMPRINC(Assumptions!$C$88,Assumptions!$C$93,Debt!$C$9,1,3,0)))) -> 2735190.4 | H68: =IFERROR(IRR(B68:G68),"N/A") -> -0.06651956 | I68: =SUM(C68:G68)/(Capital!$B$12) -> 0.74960191
A69: T1 Entry+75bps / 2.0% | B69: =-(Capital!$B$12) -> -5528040 | C69: =(('Operating Model'!$B$43*(1+0.02)^1)-(Debt!$C$9*Assumptions!$C$88)) -> 380767.39 | D69: =(('Operating Model'!$B$43*(1+0.02)^2)-(Debt!$C$9*Assumptions!$C$88)) -> 401120.14 | E69: =(('Operating Model'!$B$43*(1+0.02)^3)-(-PMT(Assumptions!$C$88,Assumptions!$C$93,Debt!$C$9))) -> 328614.85 | F69: =(('Operating Model'!$B$43*(1+0.02)^4)-(-PMT(Assumptions!$C$88,Assumptions!$C$93,Debt!$C$9))) -> 349789.85 | G69: =(('Operating Model'!$B$43*(1+0.02)^5)-(-PMT(Assumptions!$C$88,Assumptions!$C$93,Debt!$C$9))+((('Operating Model'!$B$43*(1+0.02)^6)/((Returns!$B$5+0.0075)+Returns!$B$8))*(1-Assumptions!$C$99)-(Debt!$C$9+CUMPRINC(Assumptions!$C$88,Assumptions!$C$93,Debt!$C$9,1,3,0)))) -> 3092886.2 | H69: =IFERROR(IRR(B69:G69),"N/A") -> -0.044924497 | I69: =SUM(C69:G69)/(Capital!$B$12) -> 0.8236515
A70: T1 Entry+75bps / 2.5% | B70: =-(Capital!$B$12) -> -5528040 | C70: =(('Operating Model'!$B$43*(1+0.025)^1)-(Debt!$C$9*Assumptions!$C$88)) -> 385755.81 | D70: =(('Operating Model'!$B$43*(1+0.025)^2)-(Debt!$C$9*Assumptions!$C$88)) -> 411321.45 | E70: =(('Operating Model'!$B$43*(1+0.025)^3)-(-PMT(Assumptions!$C$88,Assumptions!$C$93,Debt!$C$9))) -> 344261.15 | F70: =(('Operating Model'!$B$43*(1+0.025)^4)-(-PMT(Assumptions!$C$88,Assumptions!$C$93,Debt!$C$9))) -> 371121.06 | G70: =(('Operating Model'!$B$43*(1+0.025)^5)-(-PMT(Assumptions!$C$88,Assumptions!$C$93,Debt!$C$9))+((('Operating Model'!$B$43*(1+0.025)^6)/((Returns!$B$5+0.0075)+Returns!$B$8))*(1-Assumptions!$C$99)-(Debt!$C$9+CUMPRINC(Assumptions!$C$88,Assumptions!$C$93,Debt!$C$9,1,3,0)))) -> 3459323.3 | H70: =IFERROR(IRR(B70:G70),"N/A") -> -0.024646948 | I70: =SUM(C70:G70)/(Capital!$B$12) -> 0.89937533
A71: T1 Entry+75bps / 3.0% | B71: =-(Capital!$B$12) -> -5528040 | C71: =(('Operating Model'!$B$43*(1+0.03)^1)-(Debt!$C$9*Assumptions!$C$88)) -> 390744.23 | D71: =(('Operating Model'!$B$43*(1+0.03)^2)-(Debt!$C$9*Assumptions!$C$88)) -> 421572.65 | E71: =(('Operating Model'!$B$43*(1+0.03)^3)-(-PMT(Assumptions!$C$88,Assumptions!$C$93,Debt!$C$9))) -> 360060.85 | F71: =(('Operating Model'!$B$43*(1+0.03)^4)-(-PMT(Assumptions!$C$88,Assumptions!$C$93,Debt!$C$9))) -> 392766.72 | G71: =(('Operating Model'!$B$43*(1+0.03)^5)-(-PMT(Assumptions!$C$88,Assumptions!$C$93,Debt!$C$9))+((('Operating Model'!$B$43*(1+0.03)^6)/((Returns!$B$5+0.0075)+Returns!$B$8))*(1-Assumptions!$C$99)-(Debt!$C$9+CUMPRINC(Assumptions!$C$88,Assumptions!$C$93,Debt!$C$9,1,3,0)))) -> 3834671.9 | H71: =IFERROR(IRR(B71:G71),"N/A") -> -0.0054748984 | I71: =SUM(C71:G71)/(Capital!$B$12) -> 0.97680486
A72: T1 Entry+75bps / 3.5% | B72: =-(Capital!$B$12) -> -5528040 | C72: =(('Operating Model'!$B$43*(1+0.035)^1)-(Debt!$C$9*Assumptions!$C$88)) -> 395732.64 | D72: =(('Operating Model'!$B$43*(1+0.035)^2)-(Debt!$C$9*Assumptions!$C$88)) -> 431873.74 | E72: =(('Operating Model'!$B$43*(1+0.035)^3)-(-PMT(Assumptions!$C$88,Assumptions!$C$93,Debt!$C$9))) -> 376014.68 | F72: =(('Operating Model'!$B$43*(1+0.035)^4)-(-PMT(Assumptions!$C$88,Assumptions!$C$93,Debt!$C$9))) -> 414729.92 | G72: =(('Operating Model'!$B$43*(1+0.035)^5)-(-PMT(Assumptions!$C$88,Assumptions!$C$93,Debt!$C$9))+((('Operating Model'!$B$43*(1+0.035)^6)/((Returns!$B$5+0.0075)+Returns!$B$8))*(1-Assumptions!$C$99)-(Debt!$C$9+CUMPRINC(Assumptions!$C$88,Assumptions!$C$93,Debt!$C$9,1,3,0)))) -> 4219104.2 | H72: =IFERROR(IRR(B72:G72),"N/A") -> 0.012755636 | I72: =SUM(C72:G72)/(Capital!$B$12) -> 1.055972
A73: T1 Entry+100bps / 1.5% | B73: =-(Capital!$B$12) -> -5528040 | C73: =(('Operating Model'!$B$43*(1+0.015)^1)-(Debt!$C$9*Assumptions!$C$88)) -> 375778.97 | D73: =(('Operating Model'!$B$43*(1+0.015)^2)-(Debt!$C$9*Assumptions!$C$88)) -> 390968.71 | E73: =(('Operating Model'!$B$43*(1+0.015)^3)-(-PMT(Assumptions!$C$88,Assumptions!$C$93,Debt!$C$9))) -> 313121.2 | F73: =(('Operating Model'!$B$43*(1+0.015)^4)-(-PMT(Assumptions!$C$88,Assumptions!$C$93,Debt!$C$9))) -> 328770.04 | G73: =(('Operating Model'!$B$43*(1+0.015)^5)-(-PMT(Assumptions!$C$88,Assumptions!$C$93,Debt!$C$9))+((('Operating Model'!$B$43*(1+0.015)^6)/((Returns!$B$5+0.01)+Returns!$B$8))*(1-Assumptions!$C$99)-(Debt!$C$9+CUMPRINC(Assumptions!$C$88,Assumptions!$C$93,Debt!$C$9,1,3,0)))) -> 2456336.3 | H73: =IFERROR(IRR(B73:G73),"N/A") -> -0.082764171 | I73: =SUM(C73:G73)/(Capital!$B$12) -> 0.69915832
A74: T1 Entry+100bps / 2.0% | B74: =-(Capital!$B$12) -> -5528040 | C74: =(('Operating Model'!$B$43*(1+0.02)^1)-(Debt!$C$9*Assumptions!$C$88)) -> 380767.39 | D74: =(('Operating Model'!$B$43*(1+0.02)^2)-(Debt!$C$9*Assumptions!$C$88)) -> 401120.14 | E74: =(('Operating Model'!$B$43*(1+0.02)^3)-(-PMT(Assumptions!$C$88,Assumptions!$C$93,Debt!$C$9))) -> 328614.85 | F74: =(('Operating Model'!$B$43*(1+0.02)^4)-(-PMT(Assumptions!$C$88,Assumptions!$C$93,Debt!$C$9))) -> 349789.85 | G74: =(('Operating Model'!$B$43*(1+0.02)^5)-(-PMT(Assumptions!$C$88,Assumptions!$C$93,Debt!$C$9))+((('Operating Model'!$B$43*(1+0.02)^6)/((Returns!$B$5+0.01)+Returns!$B$8))*(1-Assumptions!$C$99)-(Debt!$C$9+CUMPRINC(Assumptions!$C$88,Assumptions!$C$93,Debt!$C$9,1,3,0)))) -> 2805687.9 | H74: =IFERROR(IRR(B74:G74),"N/A") -> -0.060095659 | I74: =SUM(C74:G74)/(Capital!$B$12) -> 0.77169849
A75: T1 Entry+100bps / 2.5% | B75: =-(Capital!$B$12) -> -5528040 | C75: =(('Operating Model'!$B$43*(1+0.025)^1)-(Debt!$C$9*Assumptions!$C$88)) -> 385755.81 | D75: =(('Operating Model'!$B$43*(1+0.025)^2)-(Debt!$C$9*Assumptions!$C$88)) -> 411321.45 | E75: =(('Operating Model'!$B$43*(1+0.025)^3)-(-PMT(Assumptions!$C$88,Assumptions!$C$93,Debt!$C$9))) -> 344261.15 | F75: =(('Operating Model'!$B$43*(1+0.025)^4)-(-PMT(Assumptions!$C$88,Assumptions!$C$93,Debt!$C$9))) -> 371121.06 | G75: =(('Operating Model'!$B$43*(1+0.025)^5)-(-PMT(Assumptions!$C$88,Assumptions!$C$93,Debt!$C$9))+((('Operating Model'!$B$43*(1+0.025)^6)/((Returns!$B$5+0.01)+Returns!$B$8))*(1-Assumptions!$C$99)-(Debt!$C$9+CUMPRINC(Assumptions!$C$88,Assumptions!$C$93,Debt!$C$9,1,3,0)))) -> 3163573.8 | H75: =IFERROR(IRR(B75:G75),"N/A") -> -0.038936483 | I75: =SUM(C75:G75)/(Capital!$B$12) -> 0.84587544
A76: T1 Entry+100bps / 3.0% | B76: =-(Capital!$B$12) -> -5528040 | C76: =(('Operating Model'!$B$43*(1+0.03)^1)-(Debt!$C$9*Assumptions!$C$88)) -> 390744.23 | D76: =(('Operating Model'!$B$43*(1+0.03)^2)-(Debt!$C$9*Assumptions!$C$88)) -> 421572.65 | E76: =(('Operating Model'!$B$43*(1+0.03)^3)-(-PMT(Assumptions!$C$88,Assumptions!$C$93,Debt!$C$9))) -> 360060.85 | F76: =(('Operating Model'!$B$43*(1+0.03)^4)-(-PMT(Assumptions!$C$88,Assumptions!$C$93,Debt!$C$9))) -> 392766.72 | G76: =(('Operating Model'!$B$43*(1+0.03)^5)-(-PMT(Assumptions!$C$88,Assumptions!$C$93,Debt!$C$9))+((('Operating Model'!$B$43*(1+0.03)^6)/((Returns!$B$5+0.01)+Returns!$B$8))*(1-Assumptions!$C$99)-(Debt!$C$9+CUMPRINC(Assumptions!$C$88,Assumptions!$C$93,Debt!$C$9,1,3,0)))) -> 3530160 | H76: =IFERROR(IRR(B76:G76),"N/A") -> -0.019027706 | I76: =SUM(C76:G76)/(Capital!$B$12) -> 0.92171989
A77: T1 Entry+100bps / 3.5% | B77: =-(Capital!$B$12) -> -5528040 | C77: =(('Operating Model'!$B$43*(1+0.035)^1)-(Debt!$C$9*Assumptions!$C$88)) -> 395732.64 | D77: =(('Operating Model'!$B$43*(1+0.035)^2)-(Debt!$C$9*Assumptions!$C$88)) -> 431873.74 | E77: =(('Operating Model'!$B$43*(1+0.035)^3)-(-PMT(Assumptions!$C$88,Assumptions!$C$93,Debt!$C$9))) -> 376014.68 | F77: =(('Operating Model'!$B$43*(1+0.035)^4)-(-PMT(Assumptions!$C$88,Assumptions!$C$93,Debt!$C$9))) -> 414729.92 | G77: =(('Operating Model'!$B$43*(1+0.035)^5)-(-PMT(Assumptions!$C$88,Assumptions!$C$93,Debt!$C$9))+((('Operating Model'!$B$43*(1+0.035)^6)/((Returns!$B$5+0.01)+Returns!$B$8))*(1-Assumptions!$C$99)-(Debt!$C$9+CUMPRINC(Assumptions!$C$88,Assumptions!$C$93,Debt!$C$9,1,3,0)))) -> 3905614.8 | H77: =IFERROR(IRR(B77:G77),"N/A") -> -0.00017273995 | I77: =SUM(C77:G77)/(Capital!$B$12) -> 0.99926298
A78: T2 -10% / Entry+0bps | B78: =-((((Assumptions!$C$7*(1+-0.1))*(1+Assumptions!$C$10)+(Capital!$B$8-Assumptions!$C$7*(1+Assumptions!$C$10)))-((Assumptions!$C$7*(1+-0.1))*Assumptions!$C$89))) -> -5024340 | C78: =((('Operating Model'!$B$43+Assumptions!$C$20-(((Assumptions!$C$7*(1+-0.1))*Assumptions!$C$16)*Assumptions!$C$14))*(1+Assumptions!$C$53)^0)-(((Assumptions!$C$7*(1+-0.1))*Assumptions!$C$89)*Assumptions!$C$88)) -> 447772.33 | D78: =((('Operating Model'!$B$43+Assumptions!$C$20-(((Assumptions!$C$7*(1+-0.1))*Assumptions!$C$16)*Assumptions!$C$14))*(1+Assumptions!$C$53)^1)-(((Assumptions!$C$7*(1+-0.1))*Assumptions!$C$89)*Assumptions!$C$88)) -> 478400.99 | E78: =((('Operating Model'!$B$43+Assumptions!$C$20-(((Assumptions!$C$7*(1+-0.1))*Assumptions!$C$16)*Assumptions!$C$14))*(1+Assumptions!$C$53)^2)-(-PMT(Assumptions!$C$88,Assumptions!$C$93,((Assumptions!$C$7*(1+-0.1))*Assumptions!$C$89)))) -> 426009.93 | F78: =((('Operating Model'!$B$43+Assumptions!$C$20-(((Assumptions!$C$7*(1+-0.1))*Assumptions!$C$16)*Assumptions!$C$14))*(1+Assumptions!$C$53)^3)-(-PMT(Assumptions!$C$88,Assumptions!$C$93,((Assumptions!$C$7*(1+-0.1))*Assumptions!$C$89)))) -> 458503.88 | G78: =((('Operating Model'!$B$43+Assumptions!$C$20-(((Assumptions!$C$7*(1+-0.1))*Assumptions!$C$16)*Assumptions!$C$14))*(1+Assumptions!$C$53)^4)-(-PMT(Assumptions!$C$88,Assumptions!$C$93,((Assumptions!$C$7*(1+-0.1))*Assumptions!$C$89)))+(((('Operating Model'!$B$43+Assumptions!$C$20-(((Assumptions!$C$7*(1+-0.1))*Assumptions!$C$16)*Assumptions!$C$14))*(1+Assumptions!$C$53)^5)/(((('Operating Model'!$B$43+Assumptions!$C$20-(((Assumptions!$C$7*(1+-0.1))*Assumptions!$C$16)*Assumptions!$C$14))/(Assumptions!$C$7*(1+-0.1)))+0)+Returns!$B$8))*(1-Assumptions!$C$99)-(((Assumptions!$C$7*(1+-0.1))*Assumptions!$C$89)+CUMPRINC(Assumptions!$C$88,Assumptions!$C$93,((Assumptions!$C$7*(1+-0.1))*Assumptions!$C$89),1,3,0)))) -> 4397401.6 | H78: =IFERROR(IRR(B78:G78),"N/A") -> 0.051332659 | I78: =SUM(C78:G78)/((((Assumptions!$C$7*(1+-0.1))*(1+Assumptions!$C$10)+(Capital!$B$8-Assumptions!$C$7*(1+Assumptions!$C$10)))-((Assumptions!$C$7*(1+-0.1))*Assumptions!$C$89))) -> 1.2356028
A79: T2 -10% / Entry+25bps | B79: =-((((Assumptions!$C$7*(1+-0.1))*(1+Assumptions!$C$10)+(Capital!$B$8-Assumptions!$C$7*(1+Assumptions!$C$10)))-((Assumptions!$C$7*(1+-0.1))*Assumptions!$C$89))) -> -5024340 | C79: =((('Operating Model'!$B$43+Assumptions!$C$20-(((Assumptions!$C$7*(1+-0.1))*Assumptions!$C$16)*Assumptions!$C$14))*(1+Assumptions!$C$53)^0)-(((Assumptions!$C$7*(1+-0.1))*Assumptions!$C$89)*Assumptions!$C$88)) -> 447772.33 | D79: =((('Operating Model'!$B$43+Assumptions!$C$20-(((Assumptions!$C$7*(1+-0.1))*Assumptions!$C$16)*Assumptions!$C$14))*(1+Assumptions!$C$53)^1)-(((Assumptions!$C$7*(1+-0.1))*Assumptions!$C$89)*Assumptions!$C$88)) -> 478400.99 | E79: =((('Operating Model'!$B$43+Assumptions!$C$20-(((Assumptions!$C$7*(1+-0.1))*Assumptions!$C$16)*Assumptions!$C$14))*(1+Assumptions!$C$53)^2)-(-PMT(Assumptions!$C$88,Assumptions!$C$93,((Assumptions!$C$7*(1+-0.1))*Assumptions!$C$89)))) -> 426009.93 | F79: =((('Operating Model'!$B$43+Assumptions!$C$20-(((Assumptions!$C$7*(1+-0.1))*Assumptions!$C$16)*Assumptions!$C$14))*(1+Assumptions!$C$53)^3)-(-PMT(Assumptions!$C$88,Assumptions!$C$93,((Assumptions!$C$7*(1+-0.1))*Assumptions!$C$89)))) -> 458503.88 | G79: =((('Operating Model'!$B$43+Assumptions!$C$20-(((Assumptions!$C$7*(1+-0.1))*Assumptions!$C$16)*Assumptions!$C$14))*(1+Assumptions!$C$53)^4)-(-PMT(Assumptions!$C$88,Assumptions!$C$93,((Assumptions!$C$7*(1+-0.1))*Assumptions!$C$89)))+(((('Operating Model'!$B$43+Assumptions!$C$20-(((Assumptions!$C$7*(1+-0.1))*Assumptions!$C$16)*Assumptions!$C$14))*(1+Assumptions!$C$53)^5)/(((('Operating Model'!$B$43+Assumptions!$C$20-(((Assumptions!$C$7*(1+-0.1))*Assumptions!$C$16)*Assumptions!$C$14))/(Assumptions!$C$7*(1+-0.1)))+0.0025)+Returns!$B$8))*(1-Assumptions!$C$99)-(((Assumptions!$C$7*(1+-0.1))*Assumptions!$C$89)+CUMPRINC(Assumptions!$C$88,Assumptions!$C$93,((Assumptions!$C$7*(1+-0.1))*Assumptions!$C$89),1,3,0)))) -> 4109207 | H79: =IFERROR(IRR(B79:G79),"N/A") -> 0.039832924 | I79: =SUM(C79:G79)/((((Assumptions!$C$7*(1+-0.1))*(1+Assumptions!$C$10)+(Capital!$B$8-Assumptions!$C$7*(1+Assumptions!$C$10)))-((Assumptions!$C$7*(1+-0.1))*Assumptions!$C$89))) -> 1.1782431
A80: T2 -10% / Entry+50bps (base) | B80: =-((((Assumptions!$C$7*(1+-0.1))*(1+Assumptions!$C$10)+(Capital!$B$8-Assumptions!$C$7*(1+Assumptions!$C$10)))-((Assumptions!$C$7*(1+-0.1))*Assumptions!$C$89))) -> -5024340 | C80: =((('Operating Model'!$B$43+Assumptions!$C$20-(((Assumptions!$C$7*(1+-0.1))*Assumptions!$C$16)*Assumptions!$C$14))*(1+Assumptions!$C$53)^0)-(((Assumptions!$C$7*(1+-0.1))*Assumptions!$C$89)*Assumptions!$C$88)) -> 447772.33 | D80: =((('Operating Model'!$B$43+Assumptions!$C$20-(((Assumptions!$C$7*(1+-0.1))*Assumptions!$C$16)*Assumptions!$C$14))*(1+Assumptions!$C$53)^1)-(((Assumptions!$C$7*(1+-0.1))*Assumptions!$C$89)*Assumptions!$C$88)) -> 478400.99 | E80: =((('Operating Model'!$B$43+Assumptions!$C$20-(((Assumptions!$C$7*(1+-0.1))*Assumptions!$C$16)*Assumptions!$C$14))*(1+Assumptions!$C$53)^2)-(-PMT(Assumptions!$C$88,Assumptions!$C$93,((Assumptions!$C$7*(1+-0.1))*Assumptions!$C$89)))) -> 426009.93 | F80: =((('Operating Model'!$B$43+Assumptions!$C$20-(((Assumptions!$C$7*(1+-0.1))*Assumptions!$C$16)*Assumptions!$C$14))*(1+Assumptions!$C$53)^3)-(-PMT(Assumptions!$C$88,Assumptions!$C$93,((Assumptions!$C$7*(1+-0.1))*Assumptions!$C$89)))) -> 458503.88 | G80: =((('Operating Model'!$B$43+Assumptions!$C$20-(((Assumptions!$C$7*(1+-0.1))*Assumptions!$C$16)*Assumptions!$C$14))*(1+Assumptions!$C$53)^4)-(-PMT(Assumptions!$C$88,Assumptions!$C$93,((Assumptions!$C$7*(1+-0.1))*Assumptions!$C$89)))+(((('Operating Model'!$B$43+Assumptions!$C$20-(((Assumptions!$C$7*(1+-0.1))*Assumptions!$C$16)*Assumptions!$C$14))*(1+Assumptions!$C$53)^5)/(((('Operating Model'!$B$43+Assumptions!$C$20-(((Assumptions!$C$7*(1+-0.1))*Assumptions!$C$16)*Assumptions!$C$14))/(Assumptions!$C$7*(1+-0.1)))+0.005)+Returns!$B$8))*(1-Assumptions!$C$99)-(((Assumptions!$C$7*(1+-0.1))*Assumptions!$C$89)+CUMPRINC(Assumptions!$C$88,Assumptions!$C$93,((Assumptions!$C$7*(1+-0.1))*Assumptions!$C$89),1,3,0)))) -> 3834859.1 | H80: =IFERROR(IRR(B80:G80),"N/A") -> 0.028340946 | I80: =SUM(C80:G80)/((((Assumptions!$C$7*(1+-0.1))*(1+Assumptions!$C$10)+(Capital!$B$8-Assumptions!$C$7*(1+Assumptions!$C$10)))-((Assumptions!$C$7*(1+-0.1))*Assumptions!$C$89))) -> 1.1236394
A81: T2 -10% / Entry+75bps | B81: =-((((Assumptions!$C$7*(1+-0.1))*(1+Assumptions!$C$10)+(Capital!$B$8-Assumptions!$C$7*(1+Assumptions!$C$10)))-((Assumptions!$C$7*(1+-0.1))*Assumptions!$C$89))) -> -5024340 | C81: =((('Operating Model'!$B$43+Assumptions!$C$20-(((Assumptions!$C$7*(1+-0.1))*Assumptions!$C$16)*Assumptions!$C$14))*(1+Assumptions!$C$53)^0)-(((Assumptions!$C$7*(1+-0.1))*Assumptions!$C$89)*Assumptions!$C$88)) -> 447772.33 | D81: =((('Operating Model'!$B$43+Assumptions!$C$20-(((Assumptions!$C$7*(1+-0.1))*Assumptions!$C$16)*Assumptions!$C$14))*(1+Assumptions!$C$53)^1)-(((Assumptions!$C$7*(1+-0.1))*Assumptions!$C$89)*Assumptions!$C$88)) -> 478400.99 | E81: =((('Operating Model'!$B$43+Assumptions!$C$20-(((Assumptions!$C$7*(1+-0.1))*Assumptions!$C$16)*Assumptions!$C$14))*(1+Assumptions!$C$53)^2)-(-PMT(Assumptions!$C$88,Assumptions!$C$93,((Assumptions!$C$7*(1+-0.1))*Assumptions!$C$89)))) -> 426009.93 | F81: =((('Operating Model'!$B$43+Assumptions!$C$20-(((Assumptions!$C$7*(1+-0.1))*Assumptions!$C$16)*Assumptions!$C$14))*(1+Assumptions!$C$53)^3)-(-PMT(Assumptions!$C$88,Assumptions!$C$93,((Assumptions!$C$7*(1+-0.1))*Assumptions!$C$89)))) -> 458503.88 | G81: =((('Operating Model'!$B$43+Assumptions!$C$20-(((Assumptions!$C$7*(1+-0.1))*Assumptions!$C$16)*Assumptions!$C$14))*(1+Assumptions!$C$53)^4)-(-PMT(Assumptions!$C$88,Assumptions!$C$93,((Assumptions!$C$7*(1+-0.1))*Assumptions!$C$89)))+(((('Operating Model'!$B$43+Assumptions!$C$20-(((Assumptions!$C$7*(1+-0.1))*Assumptions!$C$16)*Assumptions!$C$14))*(1+Assumptions!$C$53)^5)/(((('Operating Model'!$B$43+Assumptions!$C$20-(((Assumptions!$C$7*(1+-0.1))*Assumptions!$C$16)*Assumptions!$C$14))/(Assumptions!$C$7*(1+-0.1)))+0.0075)+Returns!$B$8))*(1-Assumptions!$C$99)-(((Assumptions!$C$7*(1+-0.1))*Assumptions!$C$89)+CUMPRINC(Assumptions!$C$88,Assumptions!$C$93,((Assumptions!$C$7*(1+-0.1))*Assumptions!$C$89),1,3,0)))) -> 3573383.4 | H81: =IFERROR(IRR(B81:G81),"N/A") -> 0.016835101 | I81: =SUM(C81:G81)/((((Assumptions!$C$7*(1+-0.1))*(1+Assumptions!$C$10)+(Capital!$B$8-Assumptions!$C$7*(1+Assumptions!$C$10)))-((Assumptions!$C$7*(1+-0.1))*Assumptions!$C$89))) -> 1.0715976
A82: T2 -10% / Entry+100bps | B82: =-((((Assumptions!$C$7*(1+-0.1))*(1+Assumptions!$C$10)+(Capital!$B$8-Assumptions!$C$7*(1+Assumptions!$C$10)))-((Assumptions!$C$7*(1+-0.1))*Assumptions!$C$89))) -> -5024340 | C82: =((('Operating Model'!$B$43+Assumptions!$C$20-(((Assumptions!$C$7*(1+-0.1))*Assumptions!$C$16)*Assumptions!$C$14))*(1+Assumptions!$C$53)^0)-(((Assumptions!$C$7*(1+-0.1))*Assumptions!$C$89)*Assumptions!$C$88)) -> 447772.33 | D82: =((('Operating Model'!$B$43+Assumptions!$C$20-(((Assumptions!$C$7*(1+-0.1))*Assumptions!$C$16)*Assumptions!$C$14))*(1+Assumptions!$C$53)^1)-(((Assumptions!$C$7*(1+-0.1))*Assumptions!$C$89)*Assumptions!$C$88)) -> 478400.99 | E82: =((('Operating Model'!$B$43+Assumptions!$C$20-(((Assumptions!$C$7*(1+-0.1))*Assumptions!$C$16)*Assumptions!$C$14))*(1+Assumptions!$C$53)^2)-(-PMT(Assumptions!$C$88,Assumptions!$C$93,((Assumptions!$C$7*(1+-0.1))*Assumptions!$C$89)))) -> 426009.93 | F82: =((('Operating Model'!$B$43+Assumptions!$C$20-(((Assumptions!$C$7*(1+-0.1))*Assumptions!$C$16)*Assumptions!$C$14))*(1+Assumptions!$C$53)^3)-(-PMT(Assumptions!$C$88,Assumptions!$C$93,((Assumptions!$C$7*(1+-0.1))*Assumptions!$C$89)))) -> 458503.88 | G82: =((('Operating Model'!$B$43+Assumptions!$C$20-(((Assumptions!$C$7*(1+-0.1))*Assumptions!$C$16)*Assumptions!$C$14))*(1+Assumptions!$C$53)^4)-(-PMT(Assumptions!$C$88,Assumptions!$C$93,((Assumptions!$C$7*(1+-0.1))*Assumptions!$C$89)))+(((('Operating Model'!$B$43+Assumptions!$C$20-(((Assumptions!$C$7*(1+-0.1))*Assumptions!$C$16)*Assumptions!$C$14))*(1+Assumptions!$C$53)^5)/(((('Operating Model'!$B$43+Assumptions!$C$20-(((Assumptions!$C$7*(1+-0.1))*Assumptions!$C$16)*Assumptions!$C$14))/(Assumptions!$C$7*(1+-0.1)))+0.01)+Returns!$B$8))*(1-Assumptions!$C$99)-(((Assumptions!$C$7*(1+-0.1))*Assumptions!$C$89)+CUMPRINC(Assumptions!$C$88,Assumptions!$C$93,((Assumptions!$C$7*(1+-0.1))*Assumptions!$C$89),1,3,0)))) -> 3323894.8 | H82: =IFERROR(IRR(B82:G82),"N/A") -> 0.0052929423 | I82: =SUM(C82:G82)/((((Assumptions!$C$7*(1+-0.1))*(1+Assumptions!$C$10)+(Capital!$B$8-Assumptions!$C$7*(1+Assumptions!$C$10)))-((Assumptions!$C$7*(1+-0.1))*Assumptions!$C$89))) -> 1.0219416
A83: T2 -5% / Entry+0bps | B83: =-((((Assumptions!$C$7*(1+-0.05))*(1+Assumptions!$C$10)+(Capital!$B$8-Assumptions!$C$7*(1+Assumptions!$C$10)))-((Assumptions!$C$7*(1+-0.05))*Assumptions!$C$89))) -> -5276190 | C83: =((('Operating Model'!$B$43+Assumptions!$C$20-(((Assumptions!$C$7*(1+-0.05))*Assumptions!$C$16)*Assumptions!$C$14))*(1+Assumptions!$C$53)^0)-(((Assumptions!$C$7*(1+-0.05))*Assumptions!$C$89)*Assumptions!$C$88)) -> 404293.02 | D83: =((('Operating Model'!$B$43+Assumptions!$C$20-(((Assumptions!$C$7*(1+-0.05))*Assumptions!$C$16)*Assumptions!$C$14))*(1+Assumptions!$C$53)^1)-(((Assumptions!$C$7*(1+-0.05))*Assumptions!$C$89)*Assumptions!$C$88)) -> 434572.61 | E83: =((('Operating Model'!$B$43+Assumptions!$C$20-(((Assumptions!$C$7*(1+-0.05))*Assumptions!$C$16)*Assumptions!$C$14))*(1+Assumptions!$C$53)^2)-(-PMT(Assumptions!$C$88,Assumptions!$C$93,((Assumptions!$C$7*(1+-0.05))*Assumptions!$C$89)))) -> 377158.75 | F83: =((('Operating Model'!$B$43+Assumptions!$C$20-(((Assumptions!$C$7*(1+-0.05))*Assumptions!$C$16)*Assumptions!$C$14))*(1+Assumptions!$C$53)^3)-(-PMT(Assumptions!$C$88,Assumptions!$C$93,((Assumptions!$C$7*(1+-0.05))*Assumptions!$C$89)))) -> 409282.36 | G83: =((('Operating Model'!$B$43+Assumptions!$C$20-(((Assumptions!$C$7*(1+-0.05))*Assumptions!$C$16)*Assumptions!$C$14))*(1+Assumptions!$C$53)^4)-(-PMT(Assumptions!$C$88,Assumptions!$C$93,((Assumptions!$C$7*(1+-0.05))*Assumptions!$C$89)))+(((('Operating Model'!$B$43+Assumptions!$C$20-(((Assumptions!$C$7*(1+-0.05))*Assumptions!$C$16)*Assumptions!$C$14))*(1+Assumptions!$C$53)^5)/(((('Operating Model'!$B$43+Assumptions!$C$20-(((Assumptions!$C$7*(1+-0.05))*Assumptions!$C$16)*Assumptions!$C$14))/(Assumptions!$C$7*(1+-0.05)))+0)+Returns!$B$8))*(1-Assumptions!$C$99)-(((Assumptions!$C$7*(1+-0.05))*Assumptions!$C$89)+CUMPRINC(Assumptions!$C$88,Assumptions!$C$93,((Assumptions!$C$7*(1+-0.05))*Assumptions!$C$89),1,3,0)))) -> 4423914.2 | H83: =IFERROR(IRR(B83:G83),"N/A") -> 0.032313923 | I83: =SUM(C83:G83)/((((Assumptions!$C$7*(1+-0.05))*(1+Assumptions!$C$10)+(Capital!$B$8-Assumptions!$C$7*(1+Assumptions!$C$10)))-((Assumptions!$C$7*(1+-0.05))*Assumptions!$C$89))) -> 1.1465131
A84: T2 -5% / Entry+25bps | B84: =-((((Assumptions!$C$7*(1+-0.05))*(1+Assumptions!$C$10)+(Capital!$B$8-Assumptions!$C$7*(1+Assumptions!$C$10)))-((Assumptions!$C$7*(1+-0.05))*Assumptions!$C$89))) -> -5276190 | C84: =((('Operating Model'!$B$43+Assumptions!$C$20-(((Assumptions!$C$7*(1+-0.05))*Assumptions!$C$16)*Assumptions!$C$14))*(1+Assumptions!$C$53)^0)-(((Assumptions!$C$7*(1+-0.05))*Assumptions!$C$89)*Assumptions!$C$88)) -> 404293.02 | D84: =((('Operating Model'!$B$43+Assumptions!$C$20-(((Assumptions!$C$7*(1+-0.05))*Assumptions!$C$16)*Assumptions!$C$14))*(1+Assumptions!$C$53)^1)-(((Assumptions!$C$7*(1+-0.05))*Assumptions!$C$89)*Assumptions!$C$88)) -> 434572.61 | E84: =((('Operating Model'!$B$43+Assumptions!$C$20-(((Assumptions!$C$7*(1+-0.05))*Assumptions!$C$16)*Assumptions!$C$14))*(1+Assumptions!$C$53)^2)-(-PMT(Assumptions!$C$88,Assumptions!$C$93,((Assumptions!$C$7*(1+-0.05))*Assumptions!$C$89)))) -> 377158.75 | F84: =((('Operating Model'!$B$43+Assumptions!$C$20-(((Assumptions!$C$7*(1+-0.05))*Assumptions!$C$16)*Assumptions!$C$14))*(1+Assumptions!$C$53)^3)-(-PMT(Assumptions!$C$88,Assumptions!$C$93,((Assumptions!$C$7*(1+-0.05))*Assumptions!$C$89)))) -> 409282.36 | G84: =((('Operating Model'!$B$43+Assumptions!$C$20-(((Assumptions!$C$7*(1+-0.05))*Assumptions!$C$16)*Assumptions!$C$14))*(1+Assumptions!$C$53)^4)-(-PMT(Assumptions!$C$88,Assumptions!$C$93,((Assumptions!$C$7*(1+-0.05))*Assumptions!$C$89)))+(((('Operating Model'!$B$43+Assumptions!$C$20-(((Assumptions!$C$7*(1+-0.05))*Assumptions!$C$16)*Assumptions!$C$14))*(1+Assumptions!$C$53)^5)/(((('Operating Model'!$B$43+Assumptions!$C$20-(((Assumptions!$C$7*(1+-0.05))*Assumptions!$C$16)*Assumptions!$C$14))/(Assumptions!$C$7*(1+-0.05)))+0.0025)+Returns!$B$8))*(1-Assumptions!$C$99)-(((Assumptions!$C$7*(1+-0.05))*Assumptions!$C$89)+CUMPRINC(Assumptions!$C$88,Assumptions!$C$93,((Assumptions!$C$7*(1+-0.05))*Assumptions!$C$89),1,3,0)))) -> 4106901.7 | H84: =IFERROR(IRR(B84:G84),"N/A") -> 0.019597144 | I84: =SUM(C84:G84)/((((Assumptions!$C$7*(1+-0.05))*(1+Assumptions!$C$10)+(Capital!$B$8-Assumptions!$C$7*(1+Assumptions!$C$10)))-((Assumptions!$C$7*(1+-0.05))*Assumptions!$C$89))) -> 1.0864295
A85: T2 -5% / Entry+50bps (base) | B85: =-((((Assumptions!$C$7*(1+-0.05))*(1+Assumptions!$C$10)+(Capital!$B$8-Assumptions!$C$7*(1+Assumptions!$C$10)))-((Assumptions!$C$7*(1+-0.05))*Assumptions!$C$89))) -> -5276190 | C85: =((('Operating Model'!$B$43+Assumptions!$C$20-(((Assumptions!$C$7*(1+-0.05))*Assumptions!$C$16)*Assumptions!$C$14))*(1+Assumptions!$C$53)^0)-(((Assumptions!$C$7*(1+-0.05))*Assumptions!$C$89)*Assumptions!$C$88)) -> 404293.02 | D85: =((('Operating Model'!$B$43+Assumptions!$C$20-(((Assumptions!$C$7*(1+-0.05))*Assumptions!$C$16)*Assumptions!$C$14))*(1+Assumptions!$C$53)^1)-(((Assumptions!$C$7*(1+-0.05))*Assumptions!$C$89)*Assumptions!$C$88)) -> 434572.61 | E85: =((('Operating Model'!$B$43+Assumptions!$C$20-(((Assumptions!$C$7*(1+-0.05))*Assumptions!$C$16)*Assumptions!$C$14))*(1+Assumptions!$C$53)^2)-(-PMT(Assumptions!$C$88,Assumptions!$C$93,((Assumptions!$C$7*(1+-0.05))*Assumptions!$C$89)))) -> 377158.75 | F85: =((('Operating Model'!$B$43+Assumptions!$C$20-(((Assumptions!$C$7*(1+-0.05))*Assumptions!$C$16)*Assumptions!$C$14))*(1+Assumptions!$C$53)^3)-(-PMT(Assumptions!$C$88,Assumptions!$C$93,((Assumptions!$C$7*(1+-0.05))*Assumptions!$C$89)))) -> 409282.36 | G85: =((('Operating Model'!$B$43+Assumptions!$C$20-(((Assumptions!$C$7*(1+-0.05))*Assumptions!$C$16)*Assumptions!$C$14))*(1+Assumptions!$C$53)^4)-(-PMT(Assumptions!$C$88,Assumptions!$C$93,((Assumptions!$C$7*(1+-0.05))*Assumptions!$C$89)))+(((('Operating Model'!$B$43+Assumptions!$C$20-(((Assumptions!$C$7*(1+-0.05))*Assumptions!$C$16)*Assumptions!$C$14))*(1+Assumptions!$C$53)^5)/(((('Operating Model'!$B$43+Assumptions!$C$20-(((Assumptions!$C$7*(1+-0.05))*Assumptions!$C$16)*Assumptions!$C$14))/(Assumptions!$C$7*(1+-0.05)))+0.005)+Returns!$B$8))*(1-Assumptions!$C$99)-(((Assumptions!$C$7*(1+-0.05))*Assumptions!$C$89)+CUMPRINC(Assumptions!$C$88,Assumptions!$C$93,((Assumptions!$C$7*(1+-0.05))*Assumptions!$C$89),1,3,0)))) -> 3805923.8 | H85: =IFERROR(IRR(B85:G85),"N/A") -> 0.0068504523 | I85: =SUM(C85:G85)/((((Assumptions!$C$7*(1+-0.05))*(1+Assumptions!$C$10)+(Capital!$B$8-Assumptions!$C$7*(1+Assumptions!$C$10)))-((Assumptions!$C$7*(1+-0.05))*Assumptions!$C$89))) -> 1.0293849
A86: T2 -5% / Entry+75bps | B86: =-((((Assumptions!$C$7*(1+-0.05))*(1+Assumptions!$C$10)+(Capital!$B$8-Assumptions!$C$7*(1+Assumptions!$C$10)))-((Assumptions!$C$7*(1+-0.05))*Assumptions!$C$89))) -> -5276190 | C86: =((('Operating Model'!$B$43+Assumptions!$C$20-(((Assumptions!$C$7*(1+-0.05))*Assumptions!$C$16)*Assumptions!$C$14))*(1+Assumptions!$C$53)^0)-(((Assumptions!$C$7*(1+-0.05))*Assumptions!$C$89)*Assumptions!$C$88)) -> 404293.02 | D86: =((('Operating Model'!$B$43+Assumptions!$C$20-(((Assumptions!$C$7*(1+-0.05))*Assumptions!$C$16)*Assumptions!$C$14))*(1+Assumptions!$C$53)^1)-(((Assumptions!$C$7*(1+-0.05))*Assumptions!$C$89)*Assumptions!$C$88)) -> 434572.61 | E86: =((('Operating Model'!$B$43+Assumptions!$C$20-(((Assumptions!$C$7*(1+-0.05))*Assumptions!$C$16)*Assumptions!$C$14))*(1+Assumptions!$C$53)^2)-(-PMT(Assumptions!$C$88,Assumptions!$C$93,((Assumptions!$C$7*(1+-0.05))*Assumptions!$C$89)))) -> 377158.75 | F86: =((('Operating Model'!$B$43+Assumptions!$C$20-(((Assumptions!$C$7*(1+-0.05))*Assumptions!$C$16)*Assumptions!$C$14))*(1+Assumptions!$C$53)^3)-(-PMT(Assumptions!$C$88,Assumptions!$C$93,((Assumptions!$C$7*(1+-0.05))*Assumptions!$C$89)))) -> 409282.36 | G86: =((('Operating Model'!$B$43+Assumptions!$C$20-(((Assumptions!$C$7*(1+-0.05))*Assumptions!$C$16)*Assumptions!$C$14))*(1+Assumptions!$C$53)^4)-(-PMT(Assumptions!$C$88,Assumptions!$C$93,((Assumptions!$C$7*(1+-0.05))*Assumptions!$C$89)))+(((('Operating Model'!$B$43+Assumptions!$C$20-(((Assumptions!$C$7*(1+-0.05))*Assumptions!$C$16)*Assumptions!$C$14))*(1+Assumptions!$C$53)^5)/(((('Operating Model'!$B$43+Assumptions!$C$20-(((Assumptions!$C$7*(1+-0.05))*Assumptions!$C$16)*Assumptions!$C$14))/(Assumptions!$C$7*(1+-0.05)))+0.0075)+Returns!$B$8))*(1-Assumptions!$C$99)-(((Assumptions!$C$7*(1+-0.05))*Assumptions!$C$89)+CUMPRINC(Assumptions!$C$88,Assumptions!$C$93,((Assumptions!$C$7*(1+-0.05))*Assumptions!$C$89),1,3,0)))) -> 3519794 | H86: =IFERROR(IRR(B86:G86),"N/A") -> -0.0059563133 | I86: =SUM(C86:G86)/((((Assumptions!$C$7*(1+-0.05))*(1+Assumptions!$C$10)+(Capital!$B$8-Assumptions!$C$7*(1+Assumptions!$C$10)))-((Assumptions!$C$7*(1+-0.05))*Assumptions!$C$89))) -> 0.97515457
A87: T2 -5% / Entry+100bps | B87: =-((((Assumptions!$C$7*(1+-0.05))*(1+Assumptions!$C$10)+(Capital!$B$8-Assumptions!$C$7*(1+Assumptions!$C$10)))-((Assumptions!$C$7*(1+-0.05))*Assumptions!$C$89))) -> -5276190 | C87: =((('Operating Model'!$B$43+Assumptions!$C$20-(((Assumptions!$C$7*(1+-0.05))*Assumptions!$C$16)*Assumptions!$C$14))*(1+Assumptions!$C$53)^0)-(((Assumptions!$C$7*(1+-0.05))*Assumptions!$C$89)*Assumptions!$C$88)) -> 404293.02 | D87: =((('Operating Model'!$B$43+Assumptions!$C$20-(((Assumptions!$C$7*(1+-0.05))*Assumptions!$C$16)*Assumptions!$C$14))*(1+Assumptions!$C$53)^1)-(((Assumptions!$C$7*(1+-0.05))*Assumptions!$C$89)*Assumptions!$C$88)) -> 434572.61 | E87: =((('Operating Model'!$B$43+Assumptions!$C$20-(((Assumptions!$C$7*(1+-0.05))*Assumptions!$C$16)*Assumptions!$C$14))*(1+Assumptions!$C$53)^2)-(-PMT(Assumptions!$C$88,Assumptions!$C$93,((Assumptions!$C$7*(1+-0.05))*Assumptions!$C$89)))) -> 377158.75 | F87: =((('Operating Model'!$B$43+Assumptions!$C$20-(((Assumptions!$C$7*(1+-0.05))*Assumptions!$C$16)*Assumptions!$C$14))*(1+Assumptions!$C$53)^3)-(-PMT(Assumptions!$C$88,Assumptions!$C$93,((Assumptions!$C$7*(1+-0.05))*Assumptions!$C$89)))) -> 409282.36 | G87: =((('Operating Model'!$B$43+Assumptions!$C$20-(((Assumptions!$C$7*(1+-0.05))*Assumptions!$C$16)*Assumptions!$C$14))*(1+Assumptions!$C$53)^4)-(-PMT(Assumptions!$C$88,Assumptions!$C$93,((Assumptions!$C$7*(1+-0.05))*Assumptions!$C$89)))+(((('Operating Model'!$B$43+Assumptions!$C$20-(((Assumptions!$C$7*(1+-0.05))*Assumptions!$C$16)*Assumptions!$C$14))*(1+Assumptions!$C$53)^5)/(((('Operating Model'!$B$43+Assumptions!$C$20-(((Assumptions!$C$7*(1+-0.05))*Assumptions!$C$16)*Assumptions!$C$14))/(Assumptions!$C$7*(1+-0.05)))+0.01)+Returns!$B$8))*(1-Assumptions!$C$99)-(((Assumptions!$C$7*(1+-0.05))*Assumptions!$C$89)+CUMPRINC(Assumptions!$C$88,Assumptions!$C$93,((Assumptions!$C$7*(1+-0.05))*Assumptions!$C$89),1,3,0)))) -> 3247440.1 | H87: =IFERROR(IRR(B87:G87),"N/A") -> -0.018855204 | I87: =SUM(C87:G87)/((((Assumptions!$C$7*(1+-0.05))*(1+Assumptions!$C$10)+(Capital!$B$8-Assumptions!$C$7*(1+Assumptions!$C$10)))-((Assumptions!$C$7*(1+-0.05))*Assumptions!$C$89))) -> 0.92353514
A88: T2 Base ($13.8M) / Entry+0bps | B88: =-((((Assumptions!$C$7*(1+0))*(1+Assumptions!$C$10)+(Capital!$B$8-Assumptions!$C$7*(1+Assumptions!$C$10)))-((Assumptions!$C$7*(1+0))*Assumptions!$C$89))) -> -5528040 | C88: =((('Operating Model'!$B$43+Assumptions!$C$20-(((Assumptions!$C$7*(1+0))*Assumptions!$C$16)*Assumptions!$C$14))*(1+Assumptions!$C$53)^0)-(((Assumptions!$C$7*(1+0))*Assumptions!$C$89)*Assumptions!$C$88)) -> 360813.71 | D88: =((('Operating Model'!$B$43+Assumptions!$C$20-(((Assumptions!$C$7*(1+0))*Assumptions!$C$16)*Assumptions!$C$14))*(1+Assumptions!$C$53)^1)-(((Assumptions!$C$7*(1+0))*Assumptions!$C$89)*Assumptions!$C$88)) -> 390744.23 | E88: =((('Operating Model'!$B$43+Assumptions!$C$20-(((Assumptions!$C$7*(1+0))*Assumptions!$C$16)*Assumptions!$C$14))*(1+Assumptions!$C$53)^2)-(-PMT(Assumptions!$C$88,Assumptions!$C$93,((Assumptions!$C$7*(1+0))*Assumptions!$C$89)))) -> 328307.57 | F88: =((('Operating Model'!$B$43+Assumptions!$C$20-(((Assumptions!$C$7*(1+0))*Assumptions!$C$16)*Assumptions!$C$14))*(1+Assumptions!$C$53)^3)-(-PMT(Assumptions!$C$88,Assumptions!$C$93,((Assumptions!$C$7*(1+0))*Assumptions!$C$89)))) -> 360060.85 | G88: =((('Operating Model'!$B$43+Assumptions!$C$20-(((Assumptions!$C$7*(1+0))*Assumptions!$C$16)*Assumptions!$C$14))*(1+Assumptions!$C$53)^4)-(-PMT(Assumptions!$C$88,Assumptions!$C$93,((Assumptions!$C$7*(1+0))*Assumptions!$C$89)))+(((('Operating Model'!$B$43+Assumptions!$C$20-(((Assumptions!$C$7*(1+0))*Assumptions!$C$16)*Assumptions!$C$14))*(1+Assumptions!$C$53)^5)/(((('Operating Model'!$B$43+Assumptions!$C$20-(((Assumptions!$C$7*(1+0))*Assumptions!$C$16)*Assumptions!$C$14))/(Assumptions!$C$7*(1+0)))+0)+Returns!$B$8))*(1-Assumptions!$C$99)-(((Assumptions!$C$7*(1+0))*Assumptions!$C$89)+CUMPRINC(Assumptions!$C$88,Assumptions!$C$93,((Assumptions!$C$7*(1+0))*Assumptions!$C$89),1,3,0)))) -> 4435600.3 | H88: =IFERROR(IRR(B88:G88),"N/A") -> 0.014043546 | I88: =SUM(C88:G88)/((((Assumptions!$C$7*(1+0))*(1+Assumptions!$C$10)+(Capital!$B$8-Assumptions!$C$7*(1+Assumptions!$C$10)))-((Assumptions!$C$7*(1+0))*Assumptions!$C$89))) -> 1.0628589
A89: T2 Base ($13.8M) / Entry+25bps | B89: =-((((Assumptions!$C$7*(1+0))*(1+Assumptions!$C$10)+(Capital!$B$8-Assumptions!$C$7*(1+Assumptions!$C$10)))-((Assumptions!$C$7*(1+0))*Assumptions!$C$89))) -> -5528040 | C89: =((('Operating Model'!$B$43+Assumptions!$C$20-(((Assumptions!$C$7*(1+0))*Assumptions!$C$16)*Assumptions!$C$14))*(1+Assumptions!$C$53)^0)-(((Assumptions!$C$7*(1+0))*Assumptions!$C$89)*Assumptions!$C$88)) -> 360813.71 | D89: =((('Operating Model'!$B$43+Assumptions!$C$20-(((Assumptions!$C$7*(1+0))*Assumptions!$C$16)*Assumptions!$C$14))*(1+Assumptions!$C$53)^1)-(((Assumptions!$C$7*(1+0))*Assumptions!$C$89)*Assumptions!$C$88)) -> 390744.23 | E89: =((('Operating Model'!$B$43+Assumptions!$C$20-(((Assumptions!$C$7*(1+0))*Assumptions!$C$16)*Assumptions!$C$14))*(1+Assumptions!$C$53)^2)-(-PMT(Assumptions!$C$88,Assumptions!$C$93,((Assumptions!$C$7*(1+0))*Assumptions!$C$89)))) -> 328307.57 | F89: =((('Operating Model'!$B$43+Assumptions!$C$20-(((Assumptions!$C$7*(1+0))*Assumptions!$C$16)*Assumptions!$C$14))*(1+Assumptions!$C$53)^3)-(-PMT(Assumptions!$C$88,Assumptions!$C$93,((Assumptions!$C$7*(1+0))*Assumptions!$C$89)))) -> 360060.85 | G89: =((('Operating Model'!$B$43+Assumptions!$C$20-(((Assumptions!$C$7*(1+0))*Assumptions!$C$16)*Assumptions!$C$14))*(1+Assumptions!$C$53)^4)-(-PMT(Assumptions!$C$88,Assumptions!$C$93,((Assumptions!$C$7*(1+0))*Assumptions!$C$89)))+(((('Operating Model'!$B$43+Assumptions!$C$20-(((Assumptions!$C$7*(1+0))*Assumptions!$C$16)*Assumptions!$C$14))*(1+Assumptions!$C$53)^5)/(((('Operating Model'!$B$43+Assumptions!$C$20-(((Assumptions!$C$7*(1+0))*Assumptions!$C$16)*Assumptions!$C$14))/(Assumptions!$C$7*(1+0)))+0.0025)+Returns!$B$8))*(1-Assumptions!$C$99)-(((Assumptions!$C$7*(1+0))*Assumptions!$C$89)+CUMPRINC(Assumptions!$C$88,Assumptions!$C$93,((Assumptions!$C$7*(1+0))*Assumptions!$C$89),1,3,0)))) -> 4088862.8 | H89: =IFERROR(IRR(B89:G89),"N/A") -> 3.1200431e-05 | I89: =SUM(C89:G89)/((((Assumptions!$C$7*(1+0))*(1+Assumptions!$C$10)+(Capital!$B$8-Assumptions!$C$7*(1+Assumptions!$C$10)))-((Assumptions!$C$7*(1+0))*Assumptions!$C$89))) -> 1.0001355
A90: T2 Base ($13.8M) / Entry+50bps (base) | B90: =-((((Assumptions!$C$7*(1+0))*(1+Assumptions!$C$10)+(Capital!$B$8-Assumptions!$C$7*(1+Assumptions!$C$10)))-((Assumptions!$C$7*(1+0))*Assumptions!$C$89))) -> -5528040 | C90: =((('Operating Model'!$B$43+Assumptions!$C$20-(((Assumptions!$C$7*(1+0))*Assumptions!$C$16)*Assumptions!$C$14))*(1+Assumptions!$C$53)^0)-(((Assumptions!$C$7*(1+0))*Assumptions!$C$89)*Assumptions!$C$88)) -> 360813.71 | D90: =((('Operating Model'!$B$43+Assumptions!$C$20-(((Assumptions!$C$7*(1+0))*Assumptions!$C$16)*Assumptions!$C$14))*(1+Assumptions!$C$53)^1)-(((Assumptions!$C$7*(1+0))*Assumptions!$C$89)*Assumptions!$C$88)) -> 390744.23 | E90: =((('Operating Model'!$B$43+Assumptions!$C$20-(((Assumptions!$C$7*(1+0))*Assumptions!$C$16)*Assumptions!$C$14))*(1+Assumptions!$C$53)^2)-(-PMT(Assumptions!$C$88,Assumptions!$C$93,((Assumptions!$C$7*(1+0))*Assumptions!$C$89)))) -> 328307.57 | F90: =((('Operating Model'!$B$43+Assumptions!$C$20-(((Assumptions!$C$7*(1+0))*Assumptions!$C$16)*Assumptions!$C$14))*(1+Assumptions!$C$53)^3)-(-PMT(Assumptions!$C$88,Assumptions!$C$93,((Assumptions!$C$7*(1+0))*Assumptions!$C$89)))) -> 360060.85 | G90: =((('Operating Model'!$B$43+Assumptions!$C$20-(((Assumptions!$C$7*(1+0))*Assumptions!$C$16)*Assumptions!$C$14))*(1+Assumptions!$C$53)^4)-(-PMT(Assumptions!$C$88,Assumptions!$C$93,((Assumptions!$C$7*(1+0))*Assumptions!$C$89)))+(((('Operating Model'!$B$43+Assumptions!$C$20-(((Assumptions!$C$7*(1+0))*Assumptions!$C$16)*Assumptions!$C$14))*(1+Assumptions!$C$53)^5)/(((('Operating Model'!$B$43+Assumptions!$C$20-(((Assumptions!$C$7*(1+0))*Assumptions!$C$16)*Assumptions!$C$14))/(Assumptions!$C$7*(1+0)))+0.005)+Returns!$B$8))*(1-Assumptions!$C$99)-(((Assumptions!$C$7*(1+0))*Assumptions!$C$89)+CUMPRINC(Assumptions!$C$88,Assumptions!$C$93,((Assumptions!$C$7*(1+0))*Assumptions!$C$89),1,3,0)))) -> 3760537.5 | H90: =IFERROR(IRR(B90:G90),"N/A") -> -0.014063502 | I90: =SUM(C90:G90)/((((Assumptions!$C$7*(1+0))*(1+Assumptions!$C$10)+(Capital!$B$8-Assumptions!$C$7*(1+Assumptions!$C$10)))-((Assumptions!$C$7*(1+0))*Assumptions!$C$89))) -> 0.9407428
A91: T2 Base ($13.8M) / Entry+75bps | B91: =-((((Assumptions!$C$7*(1+0))*(1+Assumptions!$C$10)+(Capital!$B$8-Assumptions!$C$7*(1+Assumptions!$C$10)))-((Assumptions!$C$7*(1+0))*Assumptions!$C$89))) -> -5528040 | C91: =((('Operating Model'!$B$43+Assumptions!$C$20-(((Assumptions!$C$7*(1+0))*Assumptions!$C$16)*Assumptions!$C$14))*(1+Assumptions!$C$53)^0)-(((Assumptions!$C$7*(1+0))*Assumptions!$C$89)*Assumptions!$C$88)) -> 360813.71 | D91: =((('Operating Model'!$B$43+Assumptions!$C$20-(((Assumptions!$C$7*(1+0))*Assumptions!$C$16)*Assumptions!$C$14))*(1+Assumptions!$C$53)^1)-(((Assumptions!$C$7*(1+0))*Assumptions!$C$89)*Assumptions!$C$88)) -> 390744.23 | E91: =((('Operating Model'!$B$43+Assumptions!$C$20-(((Assumptions!$C$7*(1+0))*Assumptions!$C$16)*Assumptions!$C$14))*(1+Assumptions!$C$53)^2)-(-PMT(Assumptions!$C$88,Assumptions!$C$93,((Assumptions!$C$7*(1+0))*Assumptions!$C$89)))) -> 328307.57 | F91: =((('Operating Model'!$B$43+Assumptions!$C$20-(((Assumptions!$C$7*(1+0))*Assumptions!$C$16)*Assumptions!$C$14))*(1+Assumptions!$C$53)^3)-(-PMT(Assumptions!$C$88,Assumptions!$C$93,((Assumptions!$C$7*(1+0))*Assumptions!$C$89)))) -> 360060.85 | G91: =((('Operating Model'!$B$43+Assumptions!$C$20-(((Assumptions!$C$7*(1+0))*Assumptions!$C$16)*Assumptions!$C$14))*(1+Assumptions!$C$53)^4)-(-PMT(Assumptions!$C$88,Assumptions!$C$93,((Assumptions!$C$7*(1+0))*Assumptions!$C$89)))+(((('Operating Model'!$B$43+Assumptions!$C$20-(((Assumptions!$C$7*(1+0))*Assumptions!$C$16)*Assumptions!$C$14))*(1+Assumptions!$C$53)^5)/(((('Operating Model'!$B$43+Assumptions!$C$20-(((Assumptions!$C$7*(1+0))*Assumptions!$C$16)*Assumptions!$C$14))/(Assumptions!$C$7*(1+0)))+0.0075)+Returns!$B$8))*(1-Assumptions!$C$99)-(((Assumptions!$C$7*(1+0))*Assumptions!$C$89)+CUMPRINC(Assumptions!$C$88,Assumptions!$C$93,((Assumptions!$C$7*(1+0))*Assumptions!$C$89),1,3,0)))) -> 3449195.9 | H91: =IFERROR(IRR(B91:G91),"N/A") -> -0.028282761 | I91: =SUM(C91:G91)/((((Assumptions!$C$7*(1+0))*(1+Assumptions!$C$10)+(Capital!$B$8-Assumptions!$C$7*(1+Assumptions!$C$10)))-((Assumptions!$C$7*(1+0))*Assumptions!$C$89))) -> 0.88442237
A92: T2 Base ($13.8M) / Entry+100bps | B92: =-((((Assumptions!$C$7*(1+0))*(1+Assumptions!$C$10)+(Capital!$B$8-Assumptions!$C$7*(1+Assumptions!$C$10)))-((Assumptions!$C$7*(1+0))*Assumptions!$C$89))) -> -5528040 | C92: =((('Operating Model'!$B$43+Assumptions!$C$20-(((Assumptions!$C$7*(1+0))*Assumptions!$C$16)*Assumptions!$C$14))*(1+Assumptions!$C$53)^0)-(((Assumptions!$C$7*(1+0))*Assumptions!$C$89)*Assumptions!$C$88)) -> 360813.71 | D92: =((('Operating Model'!$B$43+Assumptions!$C$20-(((Assumptions!$C$7*(1+0))*Assumptions!$C$16)*Assumptions!$C$14))*(1+Assumptions!$C$53)^1)-(((Assumptions!$C$7*(1+0))*Assumptions!$C$89)*Assumptions!$C$88)) -> 390744.23 | E92: =((('Operating Model'!$B$43+Assumptions!$C$20-(((Assumptions!$C$7*(1+0))*Assumptions!$C$16)*Assumptions!$C$14))*(1+Assumptions!$C$53)^2)-(-PMT(Assumptions!$C$88,Assumptions!$C$93,((Assumptions!$C$7*(1+0))*Assumptions!$C$89)))) -> 328307.57 | F92: =((('Operating Model'!$B$43+Assumptions!$C$20-(((Assumptions!$C$7*(1+0))*Assumptions!$C$16)*Assumptions!$C$14))*(1+Assumptions!$C$53)^3)-(-PMT(Assumptions!$C$88,Assumptions!$C$93,((Assumptions!$C$7*(1+0))*Assumptions!$C$89)))) -> 360060.85 | G92: =((('Operating Model'!$B$43+Assumptions!$C$20-(((Assumptions!$C$7*(1+0))*Assumptions!$C$16)*Assumptions!$C$14))*(1+Assumptions!$C$53)^4)-(-PMT(Assumptions!$C$88,Assumptions!$C$93,((Assumptions!$C$7*(1+0))*Assumptions!$C$89)))+(((('Operating Model'!$B$43+Assumptions!$C$20-(((Assumptions!$C$7*(1+0))*Assumptions!$C$16)*Assumptions!$C$14))*(1+Assumptions!$C$53)^5)/(((('Operating Model'!$B$43+Assumptions!$C$20-(((Assumptions!$C$7*(1+0))*Assumptions!$C$16)*Assumptions!$C$14))/(Assumptions!$C$7*(1+0)))+0.01)+Returns!$B$8))*(1-Assumptions!$C$99)-(((Assumptions!$C$7*(1+0))*Assumptions!$C$89)+CUMPRINC(Assumptions!$C$88,Assumptions!$C$93,((Assumptions!$C$7*(1+0))*Assumptions!$C$89),1,3,0)))) -> 3153553.3 | H92: =IFERROR(IRR(B92:G92),"N/A") -> -0.042672601 | I92: =SUM(C92:G92)/((((Assumptions!$C$7*(1+0))*(1+Assumptions!$C$10)+(Capital!$B$8-Assumptions!$C$7*(1+Assumptions!$C$10)))-((Assumptions!$C$7*(1+0))*Assumptions!$C$89))) -> 0.83094182
A93: T2 +5% / Entry+0bps | B93: =-((((Assumptions!$C$7*(1+0.05))*(1+Assumptions!$C$10)+(Capital!$B$8-Assumptions!$C$7*(1+Assumptions!$C$10)))-((Assumptions!$C$7*(1+0.05))*Assumptions!$C$89))) -> -5779890 | C93: =((('Operating Model'!$B$43+Assumptions!$C$20-(((Assumptions!$C$7*(1+0.05))*Assumptions!$C$16)*Assumptions!$C$14))*(1+Assumptions!$C$53)^0)-(((Assumptions!$C$7*(1+0.05))*Assumptions!$C$89)*Assumptions!$C$88)) -> 317334.41 | D93: =((('Operating Model'!$B$43+Assumptions!$C$20-(((Assumptions!$C$7*(1+0.05))*Assumptions!$C$16)*Assumptions!$C$14))*(1+Assumptions!$C$53)^1)-(((Assumptions!$C$7*(1+0.05))*Assumptions!$C$89)*Assumptions!$C$88)) -> 346915.84 | E93: =((('Operating Model'!$B$43+Assumptions!$C$20-(((Assumptions!$C$7*(1+0.05))*Assumptions!$C$16)*Assumptions!$C$14))*(1+Assumptions!$C$53)^2)-(-PMT(Assumptions!$C$88,Assumptions!$C$93,((Assumptions!$C$7*(1+0.05))*Assumptions!$C$89)))) -> 279456.38 | F93: =((('Operating Model'!$B$43+Assumptions!$C$20-(((Assumptions!$C$7*(1+0.05))*Assumptions!$C$16)*Assumptions!$C$14))*(1+Assumptions!$C$53)^3)-(-PMT(Assumptions!$C$88,Assumptions!$C$93,((Assumptions!$C$7*(1+0.05))*Assumptions!$C$89)))) -> 310839.33 | G93: =((('Operating Model'!$B$43+Assumptions!$C$20-(((Assumptions!$C$7*(1+0.05))*Assumptions!$C$16)*Assumptions!$C$14))*(1+Assumptions!$C$53)^4)-(-PMT(Assumptions!$C$88,Assumptions!$C$93,((Assumptions!$C$7*(1+0.05))*Assumptions!$C$89)))+(((('Operating Model'!$B$43+Assumptions!$C$20-(((Assumptions!$C$7*(1+0.05))*Assumptions!$C$16)*Assumptions!$C$14))*(1+Assumptions!$C$53)^5)/(((('Operating Model'!$B$43+Assumptions!$C$20-(((Assumptions!$C$7*(1+0.05))*Assumptions!$C$16)*Assumptions!$C$14))/(Assumptions!$C$7*(1+0.05)))+0)+Returns!$B$8))*(1-Assumptions!$C$99)-(((Assumptions!$C$7*(1+0.05))*Assumptions!$C$89)+CUMPRINC(Assumptions!$C$88,Assumptions!$C$93,((Assumptions!$C$7*(1+0.05))*Assumptions!$C$89),1,3,0)))) -> 4432459.7 | H93: =IFERROR(IRR(B93:G93),"N/A") -> -0.0036394209 | I93: =SUM(C93:G93)/((((Assumptions!$C$7*(1+0.05))*(1+Assumptions!$C$10)+(Capital!$B$8-Assumptions!$C$7*(1+Assumptions!$C$10)))-((Assumptions!$C$7*(1+0.05))*Assumptions!$C$89))) -> 0.98392974
A94: T2 +5% / Entry+25bps | B94: =-((((Assumptions!$C$7*(1+0.05))*(1+Assumptions!$C$10)+(Capital!$B$8-Assumptions!$C$7*(1+Assumptions!$C$10)))-((Assumptions!$C$7*(1+0.05))*Assumptions!$C$89))) -> -5779890 | C94: =((('Operating Model'!$B$43+Assumptions!$C$20-(((Assumptions!$C$7*(1+0.05))*Assumptions!$C$16)*Assumptions!$C$14))*(1+Assumptions!$C$53)^0)-(((Assumptions!$C$7*(1+0.05))*Assumptions!$C$89)*Assumptions!$C$88)) -> 317334.41 | D94: =((('Operating Model'!$B$43+Assumptions!$C$20-(((Assumptions!$C$7*(1+0.05))*Assumptions!$C$16)*Assumptions!$C$14))*(1+Assumptions!$C$53)^1)-(((Assumptions!$C$7*(1+0.05))*Assumptions!$C$89)*Assumptions!$C$88)) -> 346915.84 | E94: =((('Operating Model'!$B$43+Assumptions!$C$20-(((Assumptions!$C$7*(1+0.05))*Assumptions!$C$16)*Assumptions!$C$14))*(1+Assumptions!$C$53)^2)-(-PMT(Assumptions!$C$88,Assumptions!$C$93,((Assumptions!$C$7*(1+0.05))*Assumptions!$C$89)))) -> 279456.38 | F94: =((('Operating Model'!$B$43+Assumptions!$C$20-(((Assumptions!$C$7*(1+0.05))*Assumptions!$C$16)*Assumptions!$C$14))*(1+Assumptions!$C$53)^3)-(-PMT(Assumptions!$C$88,Assumptions!$C$93,((Assumptions!$C$7*(1+0.05))*Assumptions!$C$89)))) -> 310839.33 | G94: =((('Operating Model'!$B$43+Assumptions!$C$20-(((Assumptions!$C$7*(1+0.05))*Assumptions!$C$16)*Assumptions!$C$14))*(1+Assumptions!$C$53)^4)-(-PMT(Assumptions!$C$88,Assumptions!$C$93,((Assumptions!$C$7*(1+0.05))*Assumptions!$C$89)))+(((('Operating Model'!$B$43+Assumptions!$C$20-(((Assumptions!$C$7*(1+0.05))*Assumptions!$C$16)*Assumptions!$C$14))*(1+Assumptions!$C$53)^5)/(((('Operating Model'!$B$43+Assumptions!$C$20-(((Assumptions!$C$7*(1+0.05))*Assumptions!$C$16)*Assumptions!$C$14))/(Assumptions!$C$7*(1+0.05)))+0.0025)+Returns!$B$8))*(1-Assumptions!$C$99)-(((Assumptions!$C$7*(1+0.05))*Assumptions!$C$89)+CUMPRINC(Assumptions!$C$88,Assumptions!$C$93,((Assumptions!$C$7*(1+0.05))*Assumptions!$C$89),1,3,0)))) -> 4055154.6 | H94: =IFERROR(IRR(B94:G94),"N/A") -> -0.019035295 | I94: =SUM(C94:G94)/((((Assumptions!$C$7*(1+0.05))*(1+Assumptions!$C$10)+(Capital!$B$8-Assumptions!$C$7*(1+Assumptions!$C$10)))-((Assumptions!$C$7*(1+0.05))*Assumptions!$C$89))) -> 0.91865079
A95: T2 +5% / Entry+50bps (base) | B95: =-((((Assumptions!$C$7*(1+0.05))*(1+Assumptions!$C$10)+(Capital!$B$8-Assumptions!$C$7*(1+Assumptions!$C$10)))-((Assumptions!$C$7*(1+0.05))*Assumptions!$C$89))) -> -5779890 | C95: =((('Operating Model'!$B$43+Assumptions!$C$20-(((Assumptions!$C$7*(1+0.05))*Assumptions!$C$16)*Assumptions!$C$14))*(1+Assumptions!$C$53)^0)-(((Assumptions!$C$7*(1+0.05))*Assumptions!$C$89)*Assumptions!$C$88)) -> 317334.41 | D95: =((('Operating Model'!$B$43+Assumptions!$C$20-(((Assumptions!$C$7*(1+0.05))*Assumptions!$C$16)*Assumptions!$C$14))*(1+Assumptions!$C$53)^1)-(((Assumptions!$C$7*(1+0.05))*Assumptions!$C$89)*Assumptions!$C$88)) -> 346915.84 | E95: =((('Operating Model'!$B$43+Assumptions!$C$20-(((Assumptions!$C$7*(1+0.05))*Assumptions!$C$16)*Assumptions!$C$14))*(1+Assumptions!$C$53)^2)-(-PMT(Assumptions!$C$88,Assumptions!$C$93,((Assumptions!$C$7*(1+0.05))*Assumptions!$C$89)))) -> 279456.38 | F95: =((('Operating Model'!$B$43+Assumptions!$C$20-(((Assumptions!$C$7*(1+0.05))*Assumptions!$C$16)*Assumptions!$C$14))*(1+Assumptions!$C$53)^3)-(-PMT(Assumptions!$C$88,Assumptions!$C$93,((Assumptions!$C$7*(1+0.05))*Assumptions!$C$89)))) -> 310839.33 | G95: =((('Operating Model'!$B$43+Assumptions!$C$20-(((Assumptions!$C$7*(1+0.05))*Assumptions!$C$16)*Assumptions!$C$14))*(1+Assumptions!$C$53)^4)-(-PMT(Assumptions!$C$88,Assumptions!$C$93,((Assumptions!$C$7*(1+0.05))*Assumptions!$C$89)))+(((('Operating Model'!$B$43+Assumptions!$C$20-(((Assumptions!$C$7*(1+0.05))*Assumptions!$C$16)*Assumptions!$C$14))*(1+Assumptions!$C$53)^5)/(((('Operating Model'!$B$43+Assumptions!$C$20-(((Assumptions!$C$7*(1+0.05))*Assumptions!$C$16)*Assumptions!$C$14))/(Assumptions!$C$7*(1+0.05)))+0.005)+Returns!$B$8))*(1-Assumptions!$C$99)-(((Assumptions!$C$7*(1+0.05))*Assumptions!$C$89)+CUMPRINC(Assumptions!$C$88,Assumptions!$C$93,((Assumptions!$C$7*(1+0.05))*Assumptions!$C$89),1,3,0)))) -> 3698831 | H95: =IFERROR(IRR(B95:G95),"N/A") -> -0.034584761 | I95: =SUM(C95:G95)/((((Assumptions!$C$7*(1+0.05))*(1+Assumptions!$C$10)+(Capital!$B$8-Assumptions!$C$7*(1+Assumptions!$C$10)))-((Assumptions!$C$7*(1+0.05))*Assumptions!$C$89))) -> 0.85700194
A96: T2 +5% / Entry+75bps | B96: =-((((Assumptions!$C$7*(1+0.05))*(1+Assumptions!$C$10)+(Capital!$B$8-Assumptions!$C$7*(1+Assumptions!$C$10)))-((Assumptions!$C$7*(1+0.05))*Assumptions!$C$89))) -> -5779890 | C96: =((('Operating Model'!$B$43+Assumptions!$C$20-(((Assumptions!$C$7*(1+0.05))*Assumptions!$C$16)*Assumptions!$C$14))*(1+Assumptions!$C$53)^0)-(((Assumptions!$C$7*(1+0.05))*Assumptions!$C$89)*Assumptions!$C$88)) -> 317334.41 | D96: =((('Operating Model'!$B$43+Assumptions!$C$20-(((Assumptions!$C$7*(1+0.05))*Assumptions!$C$16)*Assumptions!$C$14))*(1+Assumptions!$C$53)^1)-(((Assumptions!$C$7*(1+0.05))*Assumptions!$C$89)*Assumptions!$C$88)) -> 346915.84 | E96: =((('Operating Model'!$B$43+Assumptions!$C$20-(((Assumptions!$C$7*(1+0.05))*Assumptions!$C$16)*Assumptions!$C$14))*(1+Assumptions!$C$53)^2)-(-PMT(Assumptions!$C$88,Assumptions!$C$93,((Assumptions!$C$7*(1+0.05))*Assumptions!$C$89)))) -> 279456.38 | F96: =((('Operating Model'!$B$43+Assumptions!$C$20-(((Assumptions!$C$7*(1+0.05))*Assumptions!$C$16)*Assumptions!$C$14))*(1+Assumptions!$C$53)^3)-(-PMT(Assumptions!$C$88,Assumptions!$C$93,((Assumptions!$C$7*(1+0.05))*Assumptions!$C$89)))) -> 310839.33 | G96: =((('Operating Model'!$B$43+Assumptions!$C$20-(((Assumptions!$C$7*(1+0.05))*Assumptions!$C$16)*Assumptions!$C$14))*(1+Assumptions!$C$53)^4)-(-PMT(Assumptions!$C$88,Assumptions!$C$93,((Assumptions!$C$7*(1+0.05))*Assumptions!$C$89)))+(((('Operating Model'!$B$43+Assumptions!$C$20-(((Assumptions!$C$7*(1+0.05))*Assumptions!$C$16)*Assumptions!$C$14))*(1+Assumptions!$C$53)^5)/(((('Operating Model'!$B$43+Assumptions!$C$20-(((Assumptions!$C$7*(1+0.05))*Assumptions!$C$16)*Assumptions!$C$14))/(Assumptions!$C$7*(1+0.05)))+0.0075)+Returns!$B$8))*(1-Assumptions!$C$99)-(((Assumptions!$C$7*(1+0.05))*Assumptions!$C$89)+CUMPRINC(Assumptions!$C$88,Assumptions!$C$93,((Assumptions!$C$7*(1+0.05))*Assumptions!$C$89),1,3,0)))) -> 3361786.1 | H96: =IFERROR(IRR(B96:G96),"N/A") -> -0.050347067 | I96: =SUM(C96:G96)/((((Assumptions!$C$7*(1+0.05))*(1+Assumptions!$C$10)+(Capital!$B$8-Assumptions!$C$7*(1+Assumptions!$C$10)))-((Assumptions!$C$7*(1+0.05))*Assumptions!$C$89))) -> 0.79868856
A97: T2 +5% / Entry+100bps | B97: =-((((Assumptions!$C$7*(1+0.05))*(1+Assumptions!$C$10)+(Capital!$B$8-Assumptions!$C$7*(1+Assumptions!$C$10)))-((Assumptions!$C$7*(1+0.05))*Assumptions!$C$89))) -> -5779890 | C97: =((('Operating Model'!$B$43+Assumptions!$C$20-(((Assumptions!$C$7*(1+0.05))*Assumptions!$C$16)*Assumptions!$C$14))*(1+Assumptions!$C$53)^0)-(((Assumptions!$C$7*(1+0.05))*Assumptions!$C$89)*Assumptions!$C$88)) -> 317334.41 | D97: =((('Operating Model'!$B$43+Assumptions!$C$20-(((Assumptions!$C$7*(1+0.05))*Assumptions!$C$16)*Assumptions!$C$14))*(1+Assumptions!$C$53)^1)-(((Assumptions!$C$7*(1+0.05))*Assumptions!$C$89)*Assumptions!$C$88)) -> 346915.84 | E97: =((('Operating Model'!$B$43+Assumptions!$C$20-(((Assumptions!$C$7*(1+0.05))*Assumptions!$C$16)*Assumptions!$C$14))*(1+Assumptions!$C$53)^2)-(-PMT(Assumptions!$C$88,Assumptions!$C$93,((Assumptions!$C$7*(1+0.05))*Assumptions!$C$89)))) -> 279456.38 | F97: =((('Operating Model'!$B$43+Assumptions!$C$20-(((Assumptions!$C$7*(1+0.05))*Assumptions!$C$16)*Assumptions!$C$14))*(1+Assumptions!$C$53)^3)-(-PMT(Assumptions!$C$88,Assumptions!$C$93,((Assumptions!$C$7*(1+0.05))*Assumptions!$C$89)))) -> 310839.33 | G97: =((('Operating Model'!$B$43+Assumptions!$C$20-(((Assumptions!$C$7*(1+0.05))*Assumptions!$C$16)*Assumptions!$C$14))*(1+Assumptions!$C$53)^4)-(-PMT(Assumptions!$C$88,Assumptions!$C$93,((Assumptions!$C$7*(1+0.05))*Assumptions!$C$89)))+(((('Operating Model'!$B$43+Assumptions!$C$20-(((Assumptions!$C$7*(1+0.05))*Assumptions!$C$16)*Assumptions!$C$14))*(1+Assumptions!$C$53)^5)/(((('Operating Model'!$B$43+Assumptions!$C$20-(((Assumptions!$C$7*(1+0.05))*Assumptions!$C$16)*Assumptions!$C$14))/(Assumptions!$C$7*(1+0.05)))+0.01)+Returns!$B$8))*(1-Assumptions!$C$99)-(((Assumptions!$C$7*(1+0.05))*Assumptions!$C$89)+CUMPRINC(Assumptions!$C$88,Assumptions!$C$93,((Assumptions!$C$7*(1+0.05))*Assumptions!$C$89),1,3,0)))) -> 3042496.5 | H97: =IFERROR(IRR(B97:G97),"N/A") -> -0.066388702 | I97: =SUM(C97:G97)/((((Assumptions!$C$7*(1+0.05))*(1+Assumptions!$C$10)+(Capital!$B$8-Assumptions!$C$7*(1+Assumptions!$C$10)))-((Assumptions!$C$7*(1+0.05))*Assumptions!$C$89))) -> 0.7434471
A98: T2 +10% / Entry+0bps | B98: =-((((Assumptions!$C$7*(1+0.1))*(1+Assumptions!$C$10)+(Capital!$B$8-Assumptions!$C$7*(1+Assumptions!$C$10)))-((Assumptions!$C$7*(1+0.1))*Assumptions!$C$89))) -> -6031740 | C98: =((('Operating Model'!$B$43+Assumptions!$C$20-(((Assumptions!$C$7*(1+0.1))*Assumptions!$C$16)*Assumptions!$C$14))*(1+Assumptions!$C$53)^0)-(((Assumptions!$C$7*(1+0.1))*Assumptions!$C$89)*Assumptions!$C$88)) -> 273855.1 | D98: =((('Operating Model'!$B$43+Assumptions!$C$20-(((Assumptions!$C$7*(1+0.1))*Assumptions!$C$16)*Assumptions!$C$14))*(1+Assumptions!$C$53)^1)-(((Assumptions!$C$7*(1+0.1))*Assumptions!$C$89)*Assumptions!$C$88)) -> 303087.46 | E98: =((('Operating Model'!$B$43+Assumptions!$C$20-(((Assumptions!$C$7*(1+0.1))*Assumptions!$C$16)*Assumptions!$C$14))*(1+Assumptions!$C$53)^2)-(-PMT(Assumptions!$C$88,Assumptions!$C$93,((Assumptions!$C$7*(1+0.1))*Assumptions!$C$89)))) -> 230605.2 | F98: =((('Operating Model'!$B$43+Assumptions!$C$20-(((Assumptions!$C$7*(1+0.1))*Assumptions!$C$16)*Assumptions!$C$14))*(1+Assumptions!$C$53)^3)-(-PMT(Assumptions!$C$88,Assumptions!$C$93,((Assumptions!$C$7*(1+0.1))*Assumptions!$C$89)))) -> 261617.82 | G98: =((('Operating Model'!$B$43+Assumptions!$C$20-(((Assumptions!$C$7*(1+0.1))*Assumptions!$C$16)*Assumptions!$C$14))*(1+Assumptions!$C$53)^4)-(-PMT(Assumptions!$C$88,Assumptions!$C$93,((Assumptions!$C$7*(1+0.1))*Assumptions!$C$89)))+(((('Operating Model'!$B$43+Assumptions!$C$20-(((Assumptions!$C$7*(1+0.1))*Assumptions!$C$16)*Assumptions!$C$14))*(1+Assumptions!$C$53)^5)/(((('Operating Model'!$B$43+Assumptions!$C$20-(((Assumptions!$C$7*(1+0.1))*Assumptions!$C$16)*Assumptions!$C$14))/(Assumptions!$C$7*(1+0.1)))+0)+Returns!$B$8))*(1-Assumptions!$C$99)-(((Assumptions!$C$7*(1+0.1))*Assumptions!$C$89)+CUMPRINC(Assumptions!$C$88,Assumptions!$C$93,((Assumptions!$C$7*(1+0.1))*Assumptions!$C$89),1,3,0)))) -> 4414492.5 | H98: =IFERROR(IRR(B98:G98),"N/A") -> -0.020874882 | I98: =SUM(C98:G98)/((((Assumptions!$C$7*(1+0.1))*(1+Assumptions!$C$10)+(Capital!$B$8-Assumptions!$C$7*(1+Assumptions!$C$10)))-((Assumptions!$C$7*(1+0.1))*Assumptions!$C$89))) -> 0.9091337
A99: T2 +10% / Entry+25bps | B99: =-((((Assumptions!$C$7*(1+0.1))*(1+Assumptions!$C$10)+(Capital!$B$8-Assumptions!$C$7*(1+Assumptions!$C$10)))-((Assumptions!$C$7*(1+0.1))*Assumptions!$C$89))) -> -6031740 | C99: =((('Operating Model'!$B$43+Assumptions!$C$20-(((Assumptions!$C$7*(1+0.1))*Assumptions!$C$16)*Assumptions!$C$14))*(1+Assumptions!$C$53)^0)-(((Assumptions!$C$7*(1+0.1))*Assumptions!$C$89)*Assumptions!$C$88)) -> 273855.1 | D99: =((('Operating Model'!$B$43+Assumptions!$C$20-(((Assumptions!$C$7*(1+0.1))*Assumptions!$C$16)*Assumptions!$C$14))*(1+Assumptions!$C$53)^1)-(((Assumptions!$C$7*(1+0.1))*Assumptions!$C$89)*Assumptions!$C$88)) -> 303087.46 | E99: =((('Operating Model'!$B$43+Assumptions!$C$20-(((Assumptions!$C$7*(1+0.1))*Assumptions!$C$16)*Assumptions!$C$14))*(1+Assumptions!$C$53)^2)-(-PMT(Assumptions!$C$88,Assumptions!$C$93,((Assumptions!$C$7*(1+0.1))*Assumptions!$C$89)))) -> 230605.2 | F99: =((('Operating Model'!$B$43+Assumptions!$C$20-(((Assumptions!$C$7*(1+0.1))*Assumptions!$C$16)*Assumptions!$C$14))*(1+Assumptions!$C$53)^3)-(-PMT(Assumptions!$C$88,Assumptions!$C$93,((Assumptions!$C$7*(1+0.1))*Assumptions!$C$89)))) -> 261617.82 | G99: =((('Operating Model'!$B$43+Assumptions!$C$20-(((Assumptions!$C$7*(1+0.1))*Assumptions!$C$16)*Assumptions!$C$14))*(1+Assumptions!$C$53)^4)-(-PMT(Assumptions!$C$88,Assumptions!$C$93,((Assumptions!$C$7*(1+0.1))*Assumptions!$C$89)))+(((('Operating Model'!$B$43+Assumptions!$C$20-(((Assumptions!$C$7*(1+0.1))*Assumptions!$C$16)*Assumptions!$C$14))*(1+Assumptions!$C$53)^5)/(((('Operating Model'!$B$43+Assumptions!$C$20-(((Assumptions!$C$7*(1+0.1))*Assumptions!$C$16)*Assumptions!$C$14))/(Assumptions!$C$7*(1+0.1)))+0.0025)+Returns!$B$8))*(1-Assumptions!$C$99)-(((Assumptions!$C$7*(1+0.1))*Assumptions!$C$89)+CUMPRINC(Assumptions!$C$88,Assumptions!$C$93,((Assumptions!$C$7*(1+0.1))*Assumptions!$C$89),1,3,0)))) -> 4005841 | H99: =IFERROR(IRR(B99:G99),"N/A") -> -0.037753717 | I99: =SUM(C99:G99)/((((Assumptions!$C$7*(1+0.1))*(1+Assumptions!$C$10)+(Capital!$B$8-Assumptions!$C$7*(1+Assumptions!$C$10)))-((Assumptions!$C$7*(1+0.1))*Assumptions!$C$89))) -> 0.84138352
A100: T2 +10% / Entry+50bps (base) | B100: =-((((Assumptions!$C$7*(1+0.1))*(1+Assumptions!$C$10)+(Capital!$B$8-Assumptions!$C$7*(1+Assumptions!$C$10)))-((Assumptions!$C$7*(1+0.1))*Assumptions!$C$89))) -> -6031740 | C100: =((('Operating Model'!$B$43+Assumptions!$C$20-(((Assumptions!$C$7*(1+0.1))*Assumptions!$C$16)*Assumptions!$C$14))*(1+Assumptions!$C$53)^0)-(((Assumptions!$C$7*(1+0.1))*Assumptions!$C$89)*Assumptions!$C$88)) -> 273855.1 | D100: =((('Operating Model'!$B$43+Assumptions!$C$20-(((Assumptions!$C$7*(1+0.1))*Assumptions!$C$16)*Assumptions!$C$14))*(1+Assumptions!$C$53)^1)-(((Assumptions!$C$7*(1+0.1))*Assumptions!$C$89)*Assumptions!$C$88)) -> 303087.46 | E100: =((('Operating Model'!$B$43+Assumptions!$C$20-(((Assumptions!$C$7*(1+0.1))*Assumptions!$C$16)*Assumptions!$C$14))*(1+Assumptions!$C$53)^2)-(-PMT(Assumptions!$C$88,Assumptions!$C$93,((Assumptions!$C$7*(1+0.1))*Assumptions!$C$89)))) -> 230605.2 | F100: =((('Operating Model'!$B$43+Assumptions!$C$20-(((Assumptions!$C$7*(1+0.1))*Assumptions!$C$16)*Assumptions!$C$14))*(1+Assumptions!$C$53)^3)-(-PMT(Assumptions!$C$88,Assumptions!$C$93,((Assumptions!$C$7*(1+0.1))*Assumptions!$C$89)))) -> 261617.82 | G100: =((('Operating Model'!$B$43+Assumptions!$C$20-(((Assumptions!$C$7*(1+0.1))*Assumptions!$C$16)*Assumptions!$C$14))*(1+Assumptions!$C$53)^4)-(-PMT(Assumptions!$C$88,Assumptions!$C$93,((Assumptions!$C$7*(1+0.1))*Assumptions!$C$89)))+(((('Operating Model'!$B$43+Assumptions!$C$20-(((Assumptions!$C$7*(1+0.1))*Assumptions!$C$16)*Assumptions!$C$14))*(1+Assumptions!$C$53)^5)/(((('Operating Model'!$B$43+Assumptions!$C$20-(((Assumptions!$C$7*(1+0.1))*Assumptions!$C$16)*Assumptions!$C$14))/(Assumptions!$C$7*(1+0.1)))+0.005)+Returns!$B$8))*(1-Assumptions!$C$99)-(((Assumptions!$C$7*(1+0.1))*Assumptions!$C$89)+CUMPRINC(Assumptions!$C$88,Assumptions!$C$93,((Assumptions!$C$7*(1+0.1))*Assumptions!$C$89),1,3,0)))) -> 3620933.5 | H100: =IFERROR(IRR(B100:G100),"N/A") -> -0.054881374 | I100: =SUM(C100:G100)/((((Assumptions!$C$7*(1+0.1))*(1+Assumptions!$C$10)+(Capital!$B$8-Assumptions!$C$7*(1+Assumptions!$C$10)))-((Assumptions!$C$7*(1+0.1))*Assumptions!$C$89))) -> 0.77756983
A101: T2 +10% / Entry+75bps | B101: =-((((Assumptions!$C$7*(1+0.1))*(1+Assumptions!$C$10)+(Capital!$B$8-Assumptions!$C$7*(1+Assumptions!$C$10)))-((Assumptions!$C$7*(1+0.1))*Assumptions!$C$89))) -> -6031740 | C101: =((('Operating Model'!$B$43+Assumptions!$C$20-(((Assumptions!$C$7*(1+0.1))*Assumptions!$C$16)*Assumptions!$C$14))*(1+Assumptions!$C$53)^0)-(((Assumptions!$C$7*(1+0.1))*Assumptions!$C$89)*Assumptions!$C$88)) -> 273855.1 | D101: =((('Operating Model'!$B$43+Assumptions!$C$20-(((Assumptions!$C$7*(1+0.1))*Assumptions!$C$16)*Assumptions!$C$14))*(1+Assumptions!$C$53)^1)-(((Assumptions!$C$7*(1+0.1))*Assumptions!$C$89)*Assumptions!$C$88)) -> 303087.46 | E101: =((('Operating Model'!$B$43+Assumptions!$C$20-(((Assumptions!$C$7*(1+0.1))*Assumptions!$C$16)*Assumptions!$C$14))*(1+Assumptions!$C$53)^2)-(-PMT(Assumptions!$C$88,Assumptions!$C$93,((Assumptions!$C$7*(1+0.1))*Assumptions!$C$89)))) -> 230605.2 | F101: =((('Operating Model'!$B$43+Assumptions!$C$20-(((Assumptions!$C$7*(1+0.1))*Assumptions!$C$16)*Assumptions!$C$14))*(1+Assumptions!$C$53)^3)-(-PMT(Assumptions!$C$88,Assumptions!$C$93,((Assumptions!$C$7*(1+0.1))*Assumptions!$C$89)))) -> 261617.82 | G101: =((('Operating Model'!$B$43+Assumptions!$C$20-(((Assumptions!$C$7*(1+0.1))*Assumptions!$C$16)*Assumptions!$C$14))*(1+Assumptions!$C$53)^4)-(-PMT(Assumptions!$C$88,Assumptions!$C$93,((Assumptions!$C$7*(1+0.1))*Assumptions!$C$89)))+(((('Operating Model'!$B$43+Assumptions!$C$20-(((Assumptions!$C$7*(1+0.1))*Assumptions!$C$16)*Assumptions!$C$14))*(1+Assumptions!$C$53)^5)/(((('Operating Model'!$B$43+Assumptions!$C$20-(((Assumptions!$C$7*(1+0.1))*Assumptions!$C$16)*Assumptions!$C$14))/(Assumptions!$C$7*(1+0.1)))+0.0075)+Returns!$B$8))*(1-Assumptions!$C$99)-(((Assumptions!$C$7*(1+0.1))*Assumptions!$C$89)+CUMPRINC(Assumptions!$C$88,Assumptions!$C$93,((Assumptions!$C$7*(1+0.1))*Assumptions!$C$89),1,3,0)))) -> 3257758.8 | H101: =IFERROR(IRR(B101:G101),"N/A") -> -0.072341368 | I101: =SUM(C101:G101)/((((Assumptions!$C$7*(1+0.1))*(1+Assumptions!$C$10)+(Capital!$B$8-Assumptions!$C$7*(1+Assumptions!$C$10)))-((Assumptions!$C$7*(1+0.1))*Assumptions!$C$89))) -> 0.71735924
A102: T2 +10% / Entry+100bps | B102: =-((((Assumptions!$C$7*(1+0.1))*(1+Assumptions!$C$10)+(Capital!$B$8-Assumptions!$C$7*(1+Assumptions!$C$10)))-((Assumptions!$C$7*(1+0.1))*Assumptions!$C$89))) -> -6031740 | C102: =((('Operating Model'!$B$43+Assumptions!$C$20-(((Assumptions!$C$7*(1+0.1))*Assumptions!$C$16)*Assumptions!$C$14))*(1+Assumptions!$C$53)^0)-(((Assumptions!$C$7*(1+0.1))*Assumptions!$C$89)*Assumptions!$C$88)) -> 273855.1 | D102: =((('Operating Model'!$B$43+Assumptions!$C$20-(((Assumptions!$C$7*(1+0.1))*Assumptions!$C$16)*Assumptions!$C$14))*(1+Assumptions!$C$53)^1)-(((Assumptions!$C$7*(1+0.1))*Assumptions!$C$89)*Assumptions!$C$88)) -> 303087.46 | E102: =((('Operating Model'!$B$43+Assumptions!$C$20-(((Assumptions!$C$7*(1+0.1))*Assumptions!$C$16)*Assumptions!$C$14))*(1+Assumptions!$C$53)^2)-(-PMT(Assumptions!$C$88,Assumptions!$C$93,((Assumptions!$C$7*(1+0.1))*Assumptions!$C$89)))) -> 230605.2 | F102: =((('Operating Model'!$B$43+Assumptions!$C$20-(((Assumptions!$C$7*(1+0.1))*Assumptions!$C$16)*Assumptions!$C$14))*(1+Assumptions!$C$53)^3)-(-PMT(Assumptions!$C$88,Assumptions!$C$93,((Assumptions!$C$7*(1+0.1))*Assumptions!$C$89)))) -> 261617.82 | G102: =((('Operating Model'!$B$43+Assumptions!$C$20-(((Assumptions!$C$7*(1+0.1))*Assumptions!$C$16)*Assumptions!$C$14))*(1+Assumptions!$C$53)^4)-(-PMT(Assumptions!$C$88,Assumptions!$C$93,((Assumptions!$C$7*(1+0.1))*Assumptions!$C$89)))+(((('Operating Model'!$B$43+Assumptions!$C$20-(((Assumptions!$C$7*(1+0.1))*Assumptions!$C$16)*Assumptions!$C$14))*(1+Assumptions!$C$53)^5)/(((('Operating Model'!$B$43+Assumptions!$C$20-(((Assumptions!$C$7*(1+0.1))*Assumptions!$C$16)*Assumptions!$C$14))/(Assumptions!$C$7*(1+0.1)))+0.01)+Returns!$B$8))*(1-Assumptions!$C$99)-(((Assumptions!$C$7*(1+0.1))*Assumptions!$C$89)+CUMPRINC(Assumptions!$C$88,Assumptions!$C$93,((Assumptions!$C$7*(1+0.1))*Assumptions!$C$89),1,3,0)))) -> 2914527 | H102: =IFERROR(IRR(B102:G102),"N/A") -> -0.090230416 | I102: =SUM(C102:G102)/((((Assumptions!$C$7*(1+0.1))*(1+Assumptions!$C$10)+(Capital!$B$8-Assumptions!$C$7*(1+Assumptions!$C$10)))-((Assumptions!$C$7*(1+0.1))*Assumptions!$C$89))) -> 0.66045495
A103: T3 $100/mo / -20% | B103: =-((Capital!$B$12+(('Unit Mix'!$C$10*(Assumptions!$C$34*(1+-0.2)))-'Unit Mix'!$D$18))) -> -5429832 | C103: =(('Operating Model'!$B$43+((100-Assumptions!$C$36)*12*'Unit Mix'!$C$10)*Assumptions!$C$38)-(Debt!$C$9*Assumptions!$C$88)) -> 350013.71 | D103: =((('Operating Model'!$B$43+((100-Assumptions!$C$36)*12*'Unit Mix'!$C$10)*Assumptions!$C$38)+((100-Assumptions!$C$36)*12*'Unit Mix'!$C$10))-(Debt!$C$9*Assumptions!$C$88)) -> 328413.71 | E103: =((('Operating Model'!$B$43+((100-Assumptions!$C$36)*12*'Unit Mix'!$C$10)*Assumptions!$C$38)+((100-Assumptions!$C$36)*12*'Unit Mix'!$C$10))-(-PMT(Assumptions!$C$88,Assumptions!$C$93,Debt!$C$9))) -> 235148.63 | F103: =((('Operating Model'!$B$43+((100-Assumptions!$C$36)*12*'Unit Mix'!$C$10)*Assumptions!$C$38)+((100-Assumptions!$C$36)*12*'Unit Mix'!$C$10))-(-PMT(Assumptions!$C$88,Assumptions!$C$93,Debt!$C$9))) -> 235148.63 | G103: =((('Operating Model'!$B$43+((100-Assumptions!$C$36)*12*'Unit Mix'!$C$10)*Assumptions!$C$38)+((100-Assumptions!$C$36)*12*'Unit Mix'!$C$10))-(-PMT(Assumptions!$C$88,Assumptions!$C$93,Debt!$C$9))+((((('Operating Model'!$B$43+((100-Assumptions!$C$36)*12*'Unit Mix'!$C$10)*Assumptions!$C$38)+((100-Assumptions!$C$36)*12*'Unit Mix'!$C$10))*(1+Assumptions!$C$53))/(Returns!$B$6+Returns!$B$8))*(1-Assumptions!$C$99)-(Debt!$C$9+CUMPRINC(Assumptions!$C$88,Assumptions!$C$93,Debt!$C$9,1,3,0)))) -> 1913234.8 | H103: =IFERROR(IRR(B103:G103),"N/A") -> -0.12952934 | I103: =SUM(C103:G103)/((Capital!$B$12+(('Unit Mix'!$C$10*(Assumptions!$C$34*(1+-0.2)))-'Unit Mix'!$D$18))) -> 0.56391423
A104: T3 $100/mo / -10% | B104: =-((Capital!$B$12+(('Unit Mix'!$C$10*(Assumptions!$C$34*(1+-0.1)))-'Unit Mix'!$D$18))) -> -5478936 | C104: =(('Operating Model'!$B$43+((100-Assumptions!$C$36)*12*'Unit Mix'!$C$10)*Assumptions!$C$38)-(Debt!$C$9*Assumptions!$C$88)) -> 350013.71 | D104: =((('Operating Model'!$B$43+((100-Assumptions!$C$36)*12*'Unit Mix'!$C$10)*Assumptions!$C$38)+((100-Assumptions!$C$36)*12*'Unit Mix'!$C$10))-(Debt!$C$9*Assumptions!$C$88)) -> 328413.71 | E104: =((('Operating Model'!$B$43+((100-Assumptions!$C$36)*12*'Unit Mix'!$C$10)*Assumptions!$C$38)+((100-Assumptions!$C$36)*12*'Unit Mix'!$C$10))-(-PMT(Assumptions!$C$88,Assumptions!$C$93,Debt!$C$9))) -> 235148.63 | F104: =((('Operating Model'!$B$43+((100-Assumptions!$C$36)*12*'Unit Mix'!$C$10)*Assumptions!$C$38)+((100-Assumptions!$C$36)*12*'Unit Mix'!$C$10))-(-PMT(Assumptions!$C$88,Assumptions!$C$93,Debt!$C$9))) -> 235148.63 | G104: =((('Operating Model'!$B$43+((100-Assumptions!$C$36)*12*'Unit Mix'!$C$10)*Assumptions!$C$38)+((100-Assumptions!$C$36)*12*'Unit Mix'!$C$10))-(-PMT(Assumptions!$C$88,Assumptions!$C$93,Debt!$C$9))+((((('Operating Model'!$B$43+((100-Assumptions!$C$36)*12*'Unit Mix'!$C$10)*Assumptions!$C$38)+((100-Assumptions!$C$36)*12*'Unit Mix'!$C$10))*(1+Assumptions!$C$53))/(Returns!$B$6+Returns!$B$8))*(1-Assumptions!$C$99)-(Debt!$C$9+CUMPRINC(Assumptions!$C$88,Assumptions!$C$93,Debt!$C$9,1,3,0)))) -> 1913234.8 | H104: =IFERROR(IRR(B104:G104),"N/A") -> -0.13136725 | I104: =SUM(C104:G104)/((Capital!$B$12+(('Unit Mix'!$C$10*(Assumptions!$C$34*(1+-0.1)))-'Unit Mix'!$D$18))) -> 0.55886024
A105: T3 $100/mo / Base ($20,460) | B105: =-((Capital!$B$12+(('Unit Mix'!$C$10*(Assumptions!$C$34*(1+0)))-'Unit Mix'!$D$18))) -> -5528040 | C105: =(('Operating Model'!$B$43+((100-Assumptions!$C$36)*12*'Unit Mix'!$C$10)*Assumptions!$C$38)-(Debt!$C$9*Assumptions!$C$88)) -> 350013.71 | D105: =((('Operating Model'!$B$43+((100-Assumptions!$C$36)*12*'Unit Mix'!$C$10)*Assumptions!$C$38)+((100-Assumptions!$C$36)*12*'Unit Mix'!$C$10))-(Debt!$C$9*Assumptions!$C$88)) -> 328413.71 | E105: =((('Operating Model'!$B$43+((100-Assumptions!$C$36)*12*'Unit Mix'!$C$10)*Assumptions!$C$38)+((100-Assumptions!$C$36)*12*'Unit Mix'!$C$10))-(-PMT(Assumptions!$C$88,Assumptions!$C$93,Debt!$C$9))) -> 235148.63 | F105: =((('Operating Model'!$B$43+((100-Assumptions!$C$36)*12*'Unit Mix'!$C$10)*Assumptions!$C$38)+((100-Assumptions!$C$36)*12*'Unit Mix'!$C$10))-(-PMT(Assumptions!$C$88,Assumptions!$C$93,Debt!$C$9))) -> 235148.63 | G105: =((('Operating Model'!$B$43+((100-Assumptions!$C$36)*12*'Unit Mix'!$C$10)*Assumptions!$C$38)+((100-Assumptions!$C$36)*12*'Unit Mix'!$C$10))-(-PMT(Assumptions!$C$88,Assumptions!$C$93,Debt!$C$9))+((((('Operating Model'!$B$43+((100-Assumptions!$C$36)*12*'Unit Mix'!$C$10)*Assumptions!$C$38)+((100-Assumptions!$C$36)*12*'Unit Mix'!$C$10))*(1+Assumptions!$C$53))/(Returns!$B$6+Returns!$B$8))*(1-Assumptions!$C$99)-(Debt!$C$9+CUMPRINC(Assumptions!$C$88,Assumptions!$C$93,Debt!$C$9,1,3,0)))) -> 1913234.8 | H105: =IFERROR(IRR(B105:G105),"N/A") -> -0.13318343 | I105: =SUM(C105:G105)/((Capital!$B$12+(('Unit Mix'!$C$10*(Assumptions!$C$34*(1+0)))-'Unit Mix'!$D$18))) -> 0.55389605
A106: T3 $100/mo / +10% | B106: =-((Capital!$B$12+(('Unit Mix'!$C$10*(Assumptions!$C$34*(1+0.1)))-'Unit Mix'!$D$18))) -> -5577144 | C106: =(('Operating Model'!$B$43+((100-Assumptions!$C$36)*12*'Unit Mix'!$C$10)*Assumptions!$C$38)-(Debt!$C$9*Assumptions!$C$88)) -> 350013.71 | D106: =((('Operating Model'!$B$43+((100-Assumptions!$C$36)*12*'Unit Mix'!$C$10)*Assumptions!$C$38)+((100-Assumptions!$C$36)*12*'Unit Mix'!$C$10))-(Debt!$C$9*Assumptions!$C$88)) -> 328413.71 | E106: =((('Operating Model'!$B$43+((100-Assumptions!$C$36)*12*'Unit Mix'!$C$10)*Assumptions!$C$38)+((100-Assumptions!$C$36)*12*'Unit Mix'!$C$10))-(-PMT(Assumptions!$C$88,Assumptions!$C$93,Debt!$C$9))) -> 235148.63 | F106: =((('Operating Model'!$B$43+((100-Assumptions!$C$36)*12*'Unit Mix'!$C$10)*Assumptions!$C$38)+((100-Assumptions!$C$36)*12*'Unit Mix'!$C$10))-(-PMT(Assumptions!$C$88,Assumptions!$C$93,Debt!$C$9))) -> 235148.63 | G106: =((('Operating Model'!$B$43+((100-Assumptions!$C$36)*12*'Unit Mix'!$C$10)*Assumptions!$C$38)+((100-Assumptions!$C$36)*12*'Unit Mix'!$C$10))-(-PMT(Assumptions!$C$88,Assumptions!$C$93,Debt!$C$9))+((((('Operating Model'!$B$43+((100-Assumptions!$C$36)*12*'Unit Mix'!$C$10)*Assumptions!$C$38)+((100-Assumptions!$C$36)*12*'Unit Mix'!$C$10))*(1+Assumptions!$C$53))/(Returns!$B$6+Returns!$B$8))*(1-Assumptions!$C$99)-(Debt!$C$9+CUMPRINC(Assumptions!$C$88,Assumptions!$C$93,Debt!$C$9,1,3,0)))) -> 1913234.8 | H106: =IFERROR(IRR(B106:G106),"N/A") -> -0.13497834 | I106: =SUM(C106:G106)/((Capital!$B$12+(('Unit Mix'!$C$10*(Assumptions!$C$34*(1+0.1)))-'Unit Mix'!$D$18))) -> 0.54901927
A107: T3 $100/mo / +20% | B107: =-((Capital!$B$12+(('Unit Mix'!$C$10*(Assumptions!$C$34*(1+0.2)))-'Unit Mix'!$D$18))) -> -5626248 | C107: =(('Operating Model'!$B$43+((100-Assumptions!$C$36)*12*'Unit Mix'!$C$10)*Assumptions!$C$38)-(Debt!$C$9*Assumptions!$C$88)) -> 350013.71 | D107: =((('Operating Model'!$B$43+((100-Assumptions!$C$36)*12*'Unit Mix'!$C$10)*Assumptions!$C$38)+((100-Assumptions!$C$36)*12*'Unit Mix'!$C$10))-(Debt!$C$9*Assumptions!$C$88)) -> 328413.71 | E107: =((('Operating Model'!$B$43+((100-Assumptions!$C$36)*12*'Unit Mix'!$C$10)*Assumptions!$C$38)+((100-Assumptions!$C$36)*12*'Unit Mix'!$C$10))-(-PMT(Assumptions!$C$88,Assumptions!$C$93,Debt!$C$9))) -> 235148.63 | F107: =((('Operating Model'!$B$43+((100-Assumptions!$C$36)*12*'Unit Mix'!$C$10)*Assumptions!$C$38)+((100-Assumptions!$C$36)*12*'Unit Mix'!$C$10))-(-PMT(Assumptions!$C$88,Assumptions!$C$93,Debt!$C$9))) -> 235148.63 | G107: =((('Operating Model'!$B$43+((100-Assumptions!$C$36)*12*'Unit Mix'!$C$10)*Assumptions!$C$38)+((100-Assumptions!$C$36)*12*'Unit Mix'!$C$10))-(-PMT(Assumptions!$C$88,Assumptions!$C$93,Debt!$C$9))+((((('Operating Model'!$B$43+((100-Assumptions!$C$36)*12*'Unit Mix'!$C$10)*Assumptions!$C$38)+((100-Assumptions!$C$36)*12*'Unit Mix'!$C$10))*(1+Assumptions!$C$53))/(Returns!$B$6+Returns!$B$8))*(1-Assumptions!$C$99)-(Debt!$C$9+CUMPRINC(Assumptions!$C$88,Assumptions!$C$93,Debt!$C$9,1,3,0)))) -> 1913234.8 | H107: =IFERROR(IRR(B107:G107),"N/A") -> -0.13675241 | I107: =SUM(C107:G107)/((Capital!$B$12+(('Unit Mix'!$C$10*(Assumptions!$C$34*(1+0.2)))-'Unit Mix'!$D$18))) -> 0.54422761
A108: T3 $137.50/mo / -20% | B108: =-((Capital!$B$12+(('Unit Mix'!$C$10*(Assumptions!$C$34*(1+-0.2)))-'Unit Mix'!$D$18))) -> -5429832 | C108: =(('Operating Model'!$B$43+((137.5-Assumptions!$C$36)*12*'Unit Mix'!$C$10)*Assumptions!$C$38)-(Debt!$C$9*Assumptions!$C$88)) -> 355413.71 | D108: =((('Operating Model'!$B$43+((137.5-Assumptions!$C$36)*12*'Unit Mix'!$C$10)*Assumptions!$C$38)+((137.5-Assumptions!$C$36)*12*'Unit Mix'!$C$10))-(Debt!$C$9*Assumptions!$C$88)) -> 344613.71 | E108: =((('Operating Model'!$B$43+((137.5-Assumptions!$C$36)*12*'Unit Mix'!$C$10)*Assumptions!$C$38)+((137.5-Assumptions!$C$36)*12*'Unit Mix'!$C$10))-(-PMT(Assumptions!$C$88,Assumptions!$C$93,Debt!$C$9))) -> 251348.63 | F108: =((('Operating Model'!$B$43+((137.5-Assumptions!$C$36)*12*'Unit Mix'!$C$10)*Assumptions!$C$38)+((137.5-Assumptions!$C$36)*12*'Unit Mix'!$C$10))-(-PMT(Assumptions!$C$88,Assumptions!$C$93,Debt!$C$9))) -> 251348.63 | G108: =((('Operating Model'!$B$43+((137.5-Assumptions!$C$36)*12*'Unit Mix'!$C$10)*Assumptions!$C$38)+((137.5-Assumptions!$C$36)*12*'Unit Mix'!$C$10))-(-PMT(Assumptions!$C$88,Assumptions!$C$93,Debt!$C$9))+((((('Operating Model'!$B$43+((137.5-Assumptions!$C$36)*12*'Unit Mix'!$C$10)*Assumptions!$C$38)+((137.5-Assumptions!$C$36)*12*'Unit Mix'!$C$10))*(1+Assumptions!$C$53))/(Returns!$B$6+Returns!$B$8))*(1-Assumptions!$C$99)-(Debt!$C$9+CUMPRINC(Assumptions!$C$88,Assumptions!$C$93,Debt!$C$9,1,3,0)))) -> 2103100.7 | H108: =IFERROR(IRR(B108:G108),"N/A") -> -0.11279001 | I108: =SUM(C108:G108)/((Capital!$B$12+(('Unit Mix'!$C$10*(Assumptions!$C$34*(1+-0.2)))-'Unit Mix'!$D$18))) -> 0.60882646
A109: T3 $137.50/mo / -10% | B109: =-((Capital!$B$12+(('Unit Mix'!$C$10*(Assumptions!$C$34*(1+-0.1)))-'Unit Mix'!$D$18))) -> -5478936 | C109: =(('Operating Model'!$B$43+((137.5-Assumptions!$C$36)*12*'Unit Mix'!$C$10)*Assumptions!$C$38)-(Debt!$C$9*Assumptions!$C$88)) -> 355413.71 | D109: =((('Operating Model'!$B$43+((137.5-Assumptions!$C$36)*12*'Unit Mix'!$C$10)*Assumptions!$C$38)+((137.5-Assumptions!$C$36)*12*'Unit Mix'!$C$10))-(Debt!$C$9*Assumptions!$C$88)) -> 344613.71 | E109: =((('Operating Model'!$B$43+((137.5-Assumptions!$C$36)*12*'Unit Mix'!$C$10)*Assumptions!$C$38)+((137.5-Assumptions!$C$36)*12*'Unit Mix'!$C$10))-(-PMT(Assumptions!$C$88,Assumptions!$C$93,Debt!$C$9))) -> 251348.63 | F109: =((('Operating Model'!$B$43+((137.5-Assumptions!$C$36)*12*'Unit Mix'!$C$10)*Assumptions!$C$38)+((137.5-Assumptions!$C$36)*12*'Unit Mix'!$C$10))-(-PMT(Assumptions!$C$88,Assumptions!$C$93,Debt!$C$9))) -> 251348.63 | G109: =((('Operating Model'!$B$43+((137.5-Assumptions!$C$36)*12*'Unit Mix'!$C$10)*Assumptions!$C$38)+((137.5-Assumptions!$C$36)*12*'Unit Mix'!$C$10))-(-PMT(Assumptions!$C$88,Assumptions!$C$93,Debt!$C$9))+((((('Operating Model'!$B$43+((137.5-Assumptions!$C$36)*12*'Unit Mix'!$C$10)*Assumptions!$C$38)+((137.5-Assumptions!$C$36)*12*'Unit Mix'!$C$10))*(1+Assumptions!$C$53))/(Returns!$B$6+Returns!$B$8))*(1-Assumptions!$C$99)-(Debt!$C$9+CUMPRINC(Assumptions!$C$88,Assumptions!$C$93,Debt!$C$9,1,3,0)))) -> 2103100.7 | H109: =IFERROR(IRR(B109:G109),"N/A") -> -0.11466408 | I109: =SUM(C109:G109)/((Capital!$B$12+(('Unit Mix'!$C$10*(Assumptions!$C$34*(1+-0.1)))-'Unit Mix'!$D$18))) -> 0.60336996
...

Sheet Checks
A1: CHECKS
A4: 1. SOURCES = USES
A5: Sources - Uses (Capital tab) | B5: =Capital!$B$19 -> 0 | C5: =IF(ABS(B5)<0.01,"OK","FAIL") -> OK
A7: 2. LEVERED CF INDEPENDENTLY REBUILT FROM OPERATING + DEBT TABS (each year)
A8: Year 1: (Operating UCF - Debt Svc) - Returns Levered-from-Ops | B8: =('Operating Model'!B$49-Debt!$E$17)-Returns!C22 -> 0 | C8: =IF(ABS(B8)<0.01,"OK","FAIL") -> OK
A9: Year 2: (Operating UCF - Debt Svc) - Returns Levered-from-Ops | B9: =('Operating Model'!C$49-Debt!$E$18)-Returns!D22 -> 0 | C9: =IF(ABS(B9)<0.01,"OK","FAIL") -> OK
A10: Year 3: (Operating UCF - Debt Svc) - Returns Levered-from-Ops | B10: =('Operating Model'!D$49-Debt!$E$19)-Returns!E22 -> 0 | C10: =IF(ABS(B10)<0.01,"OK","FAIL") -> OK
A11: Year 4: (Operating UCF - Debt Svc) - Returns Levered-from-Ops | B11: =('Operating Model'!E$49-Debt!$E$20)-Returns!F22 -> 0 | C11: =IF(ABS(B11)<0.01,"OK","FAIL") -> OK
A12: Year 5: (Operating UCF - Debt Svc) - Returns Levered-from-Ops | B12: =('Operating Model'!F$49-Debt!$E$21)-Returns!G22 -> 0 | C12: =IF(ABS(B12)<0.01,"OK","FAIL") -> OK
A14: 3. NOI RECOMPUTATION (EGI + Opex - NOI, each year)
A15: Year 1: EGI+OpexTotal-NOI | B15: ='Operating Model'!B28+'Operating Model'!B41-'Operating Model'!B43 -> 0 | C15: =IF(ABS(B15)<0.01,"OK","FAIL") -> OK
A16: Year 2: EGI+OpexTotal-NOI | B16: ='Operating Model'!C28+'Operating Model'!C41-'Operating Model'!C43 -> 0 | C16: =IF(ABS(B16)<0.01,"OK","FAIL") -> OK
A17: Year 3: EGI+OpexTotal-NOI | B17: ='Operating Model'!D28+'Operating Model'!D41-'Operating Model'!D43 -> 0 | C17: =IF(ABS(B17)<0.01,"OK","FAIL") -> OK
A18: Year 4: EGI+OpexTotal-NOI | B18: ='Operating Model'!E28+'Operating Model'!E41-'Operating Model'!E43 -> 0 | C18: =IF(ABS(B18)<0.01,"OK","FAIL") -> OK
A19: Year 5: EGI+OpexTotal-NOI | B19: ='Operating Model'!F28+'Operating Model'!F41-'Operating Model'!F43 -> 0 | C19: =IF(ABS(B19)<0.01,"OK","FAIL") -> OK
A21: 4. WATERFALL DISTRIBUTIONS = AVAILABLE CASH (each year)
A22: Year 1: LP+GP-Available | B22: =Waterfall!C34 -> 0 | C22: =IF(ABS(B22)<0.01,"OK","FAIL") -> OK
A23: Year 2: LP+GP-Available | B23: =Waterfall!D34 -> 0 | C23: =IF(ABS(B23)<0.01,"OK","FAIL") -> OK
A24: Year 3: LP+GP-Available | B24: =Waterfall!E34 -> 0 | C24: =IF(ABS(B24)<0.01,"OK","FAIL") -> OK
A25: Year 4: LP+GP-Available | B25: =Waterfall!F34 -> 0 | C25: =IF(ABS(B25)<0.01,"OK","FAIL") -> OK
A26: Year 5: LP+GP-Available | B26: =Waterfall!G34 -> 0 | C26: =IF(ABS(B26)<0.01,"OK","FAIL") -> OK
A28: 5. WATERFALL HURDLE BALANCES NEVER GO NEGATIVE
A29: MIN Tier-1 hurdle balance (should be >= 0) | B29: =MIN(Waterfall!C11:G11) -> 211804.27 | C29: =IF(B29>=-0.01,"OK","FAIL") -> OK
A30: MIN Tier-2 hurdle balance (should be >= 0) | B30: =MIN(Waterfall!C17:G17) -> 1407248.9 | C30: =IF(B30>=-0.01,"OK","FAIL") -> OK
A32: 6. LP EQUITY + GP EQUITY = TOTAL EQUITY
A33: LP+GP Equity - Total Equity | B33: =Capital!$B$16+Capital!$B$17-Capital!$B$12 -> 0 | C33: =IF(ABS(B33)<0.01,"OK","FAIL") -> OK
A35: 7. DEBT SCHEDULE INTERNAL CONSISTENCY
A36: Loan - Cumulative Principal Paid - Year5 End Balance | B36: =Debt!$C$9-SUM(Debt!D17:D22)-Debt!F22 -> 0 | C36: =IF(ABS(B36)<0.01,"OK","FAIL") -> OK
A38: 8. FORMULA ERROR SCAN
A39: See Phase 3 verification report for a full-workbook #REF!/#DIV/0!/#VALUE!/#NAME? scan (done via LibreOffice headless recalculation + openpyxl re-read, not a formula on this tab).

Sheet Summary
A1: SUMMARY — Parkview Crossing
A3: 97-unit garden apartment community, Pompano Beach, FL, built 1958. Light value-add / core-plus: 75% of units already renovated by the prior owner; this plan finishes the remaining ~24 classic units, burns off loss-to-lease on the rest, and underwrites Florida's post-sale property-tax reassessment (and a tax-adjusted exit) explicitly rather than ignoring them.
A6: SOURCES & USES
A7: Purchase Price | B7: =Assumptions!$C$7 -> 13800000
A8: Total Uses | B8: =Capital!$B$8 -> 14498040
A9: Senior Loan | B9: =Debt!$C$9 -> 8970000
A10: Sponsor Equity | B10: =Capital!$B$12 -> 5528040
A11: LP Equity (90%) | B11: =Capital!$B$16 -> 4975236
A12: GP Equity (10%) | B12: =Capital!$B$17 -> 552804
A14: KEY METRICS
A15: Broker-Stated Cap Rate | B15: =Assumptions!$C$8 -> 0.07
A16: Going-In Cap Rate (Year-1 model NOI, reassessed tax) | B16: =Returns!$B$5 -> 0.072295921
A17: Exit Cap Rate (base case, entry+50bps) | B17: =Returns!$B$6 -> 0.077295921
A18: Loan-to-Value | B18: =Debt!C9/Assumptions!$C$7 -> 0.65
A19: Binding Debt Constraint | B19: =Debt!C10 -> LTV
A20: Hold Period | B20: =Assumptions!$C$96 -> 5
A22: RETURNS
A23: Unlevered IRR | B23: =Returns!B29 -> 0.050257644
A24: Levered IRR (deal-level) | B24: =Returns!B30 -> 0.044995327
A25: Unlevered Equity Multiple | B25: =Returns!B31 -> 1.244904
A26: Levered Equity Multiple (deal-level) | B26: =Returns!B32 -> 1.2020154
A27: LP IRR | B27: =Waterfall!B37 -> 0.072203953
A28: LP Equity Multiple | B28: =Waterfall!B39 -> 1.3355726
A29: GP IRR | B29: =Waterfall!B38 -> N/A - GP receives $0 in this scenario, IRR undefined
A30: GP Equity Multiple | B30: =Waterfall!B40 -> 0
A32: DEAL THESIS
A33: Light value-add / core-plus acquisition of a 1958-vintage, 97-unit Broward County garden apartment community that is 75% already renovated. Return drivers: (1) finishing the ~24 remaining classic units on a bottom-up $20,460/unit scope, (2) loss-to-lease burn-off on units still priced below the broker-disclosed 20.76% market gap, (3) modest, Broward-Class-C-sourced market rent growth capped at 3.0% terminal, and (4) expense discipline given real insurance and property-tax exposure on a 68-year-old building. Property tax is modeled on Florida's actual post-sale reassessment mechanic (Fla. Stat. 193.011(8) cost-of-sale method), and exit value uses a tax-adjusted formula so the exit buyer's own reassessment isn't ignored. Roof condition and the building's 40/50-Year recertification status are undisclosed and treated as flagged diligence items, not assumptions.
